Workbook

Sheet Strategy & explanation
A1: Launch File – Davy Koopman
A2: Updated 16-10-2026 · per store a product tab and a '– Links' tab · list ±15-25 per store per day · listers fill in Lister / Status / Comment on the Links tab
A4: How to use (listers) | B4: 1) Open the '– Links' tab of your store. 2) Pick your name under Lister. 3) List the product from the link at the advised price. 4) Set Status: Live (published), Draft (prepared, not yet live), Duplicate (already in store) or Issues + a Comment. Work from top to bottom (list order). Always reach your daily target: skip duplicates and list the next one.
A5: Sources (import links) | B5: Only 19 competitors with a verified SimilarWeb figure of ≥75K visits/month, the same dropshipping model and no own label. Smaller or unverified stores only count as confirmation ('also at …, small') and for saturation, never as source.
A6: Source choice per product | B6: Preferably a competitor in a different country than your market (same photo + price at a domestic competitor = direct competition). Then: selling well, best photos, same currency, highest price. '⚠ own market' = only a domestic big source exists: follow the photo advice.
A7: Price | B7: Advised price = price of the source link (take it over; other currency → converted, ending in .95). Never underprice. Below the category sweet spot (P25–P75 of bestsellers) → 'can go higher'.
A8: Photos | B8: Photo score 0-100 (≥6 photos, 1st photo ≥1200 px, portrait 3:4/4:5). Counts in the order; weak photos are removed.
A9: Season & order | B9: Week 1-2 autumn layers, week 3 winter coats/boots (cold markets), week 4 Christmas.
A10: Duplicate check | B10: Products already in your store are removed (photo match). Stores sharing a market (UK) never get the same product.
A12: A · Proven elsewhere, open in your market | B12: Bestseller at big competitor(s) in another country, while no competitor sells it in your market yet. Best chance: proven product without price competition.
A13: B · Broadly proven | B13: Sold by 3+ competitors and a bestseller at a big one. Several strong stores bet on it: low risk.
A14: C · New & rising | B14: Live ≤21 days at a big competitor and already in the top 40% of its ranking. Get in early before it is everywhere.
A15: D · Proven in your market | B15: Bestseller at one competitor in your country (3+ competitors there = skipped). Demand is proven; you compete on ads and photos, not on price.
A16: E · New at a top competitor | B16: Just added (≤14 days) by a store with 150K+ visits. Not yet proven, but these stores test deliberately.
A18: Note | B18: Bestseller rank = position in the store's own 'best selling' sort, not a sales count. Preferably use supplier photos or your own texts rather than copying everything 1:1 from the competitor.
A20: Per store
A21: Stellamea | B21: Market: Spain · EUR · catalogue 491 products (62% women) · 757 products · status: Not listed 366, Draft 0, Live 344, Issues 6, Duplicate 41 Strategy: A 450, B 166, C 78, E 32 Categories: Sweater / hoodie 213, Transition jacket 164, Cardigan 105, Trousers 51, Blazer 49, Boots 44, Blouse / shirt 36, Shoes 36, Set 24, Other 18, Dress 11, Winter coat 6 List weeks: week 1: 596, week 2: 157, week 4: 4 Sources: Lozenda Fashion (315K) 178×, Nordheim Mode (546K) 63×, Harper & Wells Boston (1700K) 48×, Lozenda Fashion (192K) 46×, Leon Boutique (243K) 43×, Leon Boutique (344K) 32×, Nordheim Mode (896K) 30×, Dolce Paris (172K) 26×, Harper & Wells Boston (1500K) 25×, Karlson Berlin (981K) 20×, Vitelli Moda (121K) 18×, Oliver & Blake (199K) 15×, Lumière Boutique (146K) 12×, Lumière Boutique (275K) 10×, Laurent Monaco (269K) 10×, Boutique Paris (166K) 10×, Cole & Harrison (154K) 10×, Look de Paris (236K) 9×, Vitelli Moda (103K) 9×, Laurent Monaco (204K) 8×, Look de Paris (111K) 7×, Alpenkind Mode (118K) 7×, Falkenberg Mode (84K) 6×, Oliver & Blake (98K) 6×, dolce-paris.com (172K) 6×, harperwells-boston.com (1700K) 6×, Wilson & Carter (200K) 5×, Velareeh Haus (134K) 5×, Alpenkind Mode (77K) 4×, North Style Fashion 4×, Davento (own store) · bestseller Davento 4×, nordheim-mode.de (896K) 4×, Velareeh Haus (95K) 3×, Parisane (77K) 3×, Armand et Fils (195K) 3×, Anna Vera 3×, Davies & Cooper 3×, lozendafashion.com (314K) · look-alike 3×, Montarello (206K) 3×, Manchester Boutique 2×, lookdeparis.com (111K) · look-alike 2×, dolce-paris.com (172K) · look-alike 2×, northstyle-fashion.com · look-alike 2×, urbanase.com · look-alike 2×, wilson-and-carter.com (68K) · look-alike 2×, Mayfair & Finch 2×, Risora (115K) 2×, Wentworth London (87K) 1×, Risora (121K) 1×, Nordspur (89K) 1×, Margaret Robinson 1×, Nicole Modehaus (32K) 1×, Marlovale 1×, Marlow & Quinn (20K) 1×, Rosati Milano (55K) 1×, Michael Claire Vancouver 1×, Curve Bloom Nashville 1×, lozendafashion.com · bestseller Davento 1×, parisane.fr · bestseller Davento 1×, armandetfils.fr · bestseller Davento 1×, nordheim-mode.de · bestseller Niaali 1×, velareehhaus.com · bestseller Niaali 1×, Niaali (own store) · bestseller Niaali 1×, boutique-paris.fr (59K) · look-alike 1×, falkenhof-mode.de · look-alike 1×, mayfairandfinch.co.uk · look-alike 1×, annavera.it · look-alike 1×, harperwells-boston.com (1700K) · look-alike 1×, parisane.fr (66K) · look-alike 1×, velareehhaus.com (134K) · look-alike 1×, larkandclover.com (214K) · look-alike 1×, lookdeparis.com (111K) 1×, lumiereboutique.fr (145K) 1×, Boutique Paris (60K) 1×, Rowan Shoes 1×, Moreau Lyon (290K) 1×, Wilson & Carter (68K) 1×, Boutique Élégance Bordeaux (34K) 1×, Armand et Fils (136K) 1×, Amara Fiore 1×, Lune Mode 1×
A22: Davento | B22: Market: Italy, Germany · EUR · catalogue 945 products (62% women) · 669 products · status: Not listed 289, Draft 0, Live 327, Issues 1, Duplicate 52 Strategy: A 309, B 218, C 93, E 39 Categories: Transition jacket 209, Sweater / hoodie 106, Cardigan 87, Trousers 68, Boots 54, Winter coat 34, Shoes 32, Blouse / shirt 26, Blazer 19, Dress 13, Set 11, Other 10 List weeks: week 1: 378, week 2: 204, week 3: 86, week 4: 1 Sources: Harper & Wells Boston (1700K) 103×, Lozenda Fashion (192K) 65×, Harper & Wells Boston (1500K) 62×, Dolce Paris (172K) 62×, Oliver & Blake (199K) 47×, Cole & Harrison (154K) 32×, Lumière Boutique (146K) 24×, Laurent Monaco (204K) 22×, Boutique Paris (166K) 21×, Lumière Boutique (275K) 19×, Nordspur (89K) 18×, Laurent Monaco (269K) 16×, Look de Paris (111K) 15×, Look de Paris (236K) 14×, Montarello (206K) 14×, Wentworth London (106K) 14×, Wilson & Carter (200K) 12×, Oliver & Blake (98K) 12×, Nordheim Mode (546K) 10×, Parisane (77K) 10×, Alpenkind Mode (77K) 9×, Lozenda Fashion (315K) 6×, Nordheim Mode (896K) 6×, Leon Boutique (344K) 5×, dolce-paris.com (172K) 4×, harperwells-boston.com (1700K) 4×, Karlson Berlin (981K) 3×, Moreau Lyon (426K) 2×, Parisane (66K) 2×, Boutique Élégance Bordeaux (34K) 2×, Chaps London 2×, North Style Fashion 2×, Niaali (own store) · bestseller Niaali 2×, urbanase.com · look-alike 2×, Vitelli Moda (103K) 2×, Armand et Fils (136K) 2×, Wentworth London (87K) 1×, Vitelli Moda (121K) 1×, Armand et Fils (195K) 1×, Risora (121K) 1×, Soof & Clay 1×, Emma Claire Hamptons (54K) 1×, Emily Carter Manchester 1×, Leon Boutique (243K) 1×, Wilson & Carter (68K) 1×, Curve Bloom Nashville 1×, Davies & Cooper 1×, Marlow & Quinn (20K) 1×, Walther Mode (32K) 1×, boutique-paris.fr (59K) · look-alike 1×, marlowandquinn.com (19K) · look-alike 1×, wilson-and-carter.com (68K) · look-alike 1×, larkandclover.com (214K) · look-alike 1×, ana-cortez.com · look-alike 1×, lookdeparis.com (111K) · look-alike 1×, nordheim-mode.de (896K) 1×, lumiereboutique.fr (145K) 1×, Velareeh Haus (134K) 1×
A23: Niaali | B23: Market: Poland, United Kingdom · PLN · catalogue 733 products (63% women) · 629 products · status: Not listed 301, Draft 0, Live 259, Issues 7, Duplicate 62 Strategy: A 323, B 97, C 86, E 97 Categories: Transition jacket 224, Sweater / hoodie 115, Winter coat 84, Boots 76, Cardigan 45, Trousers 40, Set 16, Other 14, Blouse / shirt 5, Dress 4, Blazer 3, Shoes 3 List weeks: week 1: 317, week 2: 156, week 3: 155, week 4: 1 Sources: Lozenda Fashion (315K) 104×, Lozenda Fashion (192K) 83×, Dolce Paris (172K) 43×, Oliver & Blake (199K) 35×, Nordheim Mode (896K) 28×, Leon Boutique (344K) 26×, Nordheim Mode (546K) 23×, Harper & Wells Boston (1500K) 20×, Harper & Wells Boston (1700K) 19×, Boutique Paris (166K) 15×, Nordspur (89K) 15×, Vitelli Moda (103K) 15×, Laurent Monaco (269K) 13×, Leon Boutique (243K) 13×, Lumière Boutique (275K) 12×, Vitelli Moda (121K) 12×, Parisane (77K) 11×, Look de Paris (236K) 11×, Look de Paris (111K) 8×, Lumière Boutique (146K) 7×, Velareeh Haus (95K) 6×, Oliver & Blake (98K) 6×, Falkenberg Mode (84K) 6×, Montarello (206K) 6×, Alpenkind Mode (77K) 5×, Risora (115K) 5×, Laurent Monaco (204K) 5×, Velareeh Haus (134K) 5×, Davento (own store) · bestseller Davento 5×, Karlson Berlin (981K) 4×, North Style Fashion 4×, dolce-paris.com (172K) 4×, nordheim-mode.de (896K) 4×, Moreau Lyon (290K) 3×, harperwells-boston.com (1700K) 3×, Risora (121K) 2×, Wilson & Carter (200K) 2×, Vientovida (85K) 2×, Boutique Élégance Bordeaux (34K) 2×, Parisane (66K) 2×, Alpenkind Mode (118K) 2×, leonboutique.co (343K) · look-alike 2×, annavera.it · look-alike 2×, urbanase.com · look-alike 2×, harperwells-boston.com (1700K) · look-alike 2×, lozendafashion.com (314K) · look-alike 2×, Karlson Berlin (301K) 1×, Armand et Fils (195K) 1×, luzestilo.es · bestseller Davento 1×, karlson-berlin.com (301K) · look-alike 1×, Emma Claire Hamptons (54K) 1×, amara-fiore.com · look-alike 1×, marlowandquinn.com (19K) · look-alike 1×, marlovale.com · look-alike 1×, parisane.fr (66K) · look-alike 1×, velareehhaus.com (134K) · look-alike 1×, larkandclover.com (214K) · look-alike 1×, northstyle-fashion.com · look-alike 1×, ana-cortez.com · look-alike 1×, lozendafashion.com (314K) 1×, lumiereboutique.fr (145K) 1×, Nordspur (50K) 1×, Anna Vera 1×, Falkenhof Mode 1×, Paul's Wardrobe 1×, Amara Fiore 1×, Armand et Fils (136K) 1×, Mercer & Bloom 1×, Falkenberg Mode (54K) 1×
A24: Dujje | B24: Market: United Kingdom · GBP · catalogue 392 products (76% women) · 735 products · status: Not listed 300, Draft 0, Live 367, Issues 6, Duplicate 62 Strategy: A 324, B 208, C 109, E 54 Categories: Transition jacket 218, Sweater / hoodie 182, Cardigan 96, Boots 76, Trousers 37, Winter coat 37, Blazer 20, Set 17, Shoes 17, Other 17, Blouse / shirt 15, Dress 3 List weeks: week 1: 398, week 2: 229, week 3: 106, week 4: 2 Sources: Lozenda Fashion (315K) 204×, Lozenda Fashion (192K) 60×, Nordheim Mode (546K) 59×, Dolce Paris (172K) 44×, Leon Boutique (243K) 38×, Harper & Wells Boston (1700K) 30×, Harper & Wells Boston (1500K) 25×, Leon Boutique (344K) 24×, Nordheim Mode (896K) 17×, Karlson Berlin (981K) 16×, Lumière Boutique (275K) 16×, Boutique Paris (166K) 13×, Lumière Boutique (146K) 13×, Oliver & Blake (199K) 10×, Davento (own store) · bestseller Davento 10×, Vitelli Moda (121K) 9×, Look de Paris (236K) 9×, Oliver & Blake (98K) 9×, Alpenkind Mode (118K) 9×, Look de Paris (111K) 8×, Laurent Monaco (269K) 6×, harperwells-boston.com (1700K) 6×, Montarello (206K) 6×, Velareeh Haus (95K) 5×, Vitelli Moda (103K) 5×, Alpenkind Mode (77K) 4×, dolce-paris.com (172K) 4×, nordheim-mode.de (896K) 4×, Falkenberg Mode (84K) 3×, Parisane (77K) 3×, Nordspur (89K) 3×, Anna Vera 3×, Risora (115K) 3×, dolce-paris.com (172K) · look-alike 3×, Nicole Modehaus (32K) 2×, Cole & Harrison (154K) 2×, Rosati Milano (55K) 2×, Laurent Monaco (204K) 2×, oliverandblake.com (198K) · look-alike 2×, mercerandbloom.com · look-alike 2×, urbanase.com · look-alike 2×, lozendafashion.com (314K) · look-alike 2×, northstyle-fashion.com · look-alike 2×, leonboutique.co (343K) · look-alike 2×, Risora (121K) 1×, Moreau Lyon (426K) 1×, Wilson & Carter (200K) 1×, Armand et Fils (195K) 1×, Michael Claire Vancouver 1×, Karlson Berlin (301K) 1×, Boutique Paris (60K) 1×, Marlow & Quinn (20K) 1×, Falkenhof Mode 1×, Margaret Robinson 1×, Falkenberg Mode (54K) 1×, lozendafashion.com · bestseller Davento 1×, marlowandquinn.com · bestseller Davento 1×, amara-fiore.com · bestseller Davento 1×, parisane.fr · bestseller Davento 1×, serentimoda.com · bestseller Davento 1×, velareehhaus.com · bestseller Niaali 1×, lozendafashion.com · bestseller Niaali 1×, Niaali (own store) · bestseller Niaali 1×, lookdeparis.com (111K) · look-alike 1×, margaret-robinson.com · look-alike 1×, annavera.it · look-alike 1×, harperwells-boston.com (1700K) · look-alike 1×, parisane.fr (66K) · look-alike 1×, velareehhaus.com (134K) · look-alike 1×, larkandclover.com (214K) · look-alike 1×, lookdeparis.com (111K) 1×, lumiereboutique.fr (145K) 1×, Velareeh Haus (134K) 1×, North Style Fashion 1×, Moreau Lyon (290K) 1×, Rowan Shoes 1×, Lune Mode 1×, Emma Claire Hamptons (54K) 1×
A25: Migesi | B25: Market: United Kingdom · GBP · catalogue 605 products (53% women) · 711 products · status: Not listed 365, Draft 0, Live 284, Issues 2, Duplicate 60 Strategy: A 368, B 174, C 87, E 62 Categories: Transition jacket 191, Sweater / hoodie 171, Cardigan 109, Boots 86, Trousers 34, Winter coat 33, Blazer 23, Shoes 17, Blouse / shirt 16, Dress 12, Other 10, Set 9 List weeks: week 1: 372, week 2: 218, week 3: 117, week 4: 4 Sources: Lozenda Fashion (315K) 135×, Lozenda Fashion (192K) 79×, Nordheim Mode (896K) 43×, Oliver & Blake (199K) 41×, Harper & Wells Boston (1700K) 39×, Harper & Wells Boston (1500K) 33×, Leon Boutique (344K) 31×, Dolce Paris (172K) 30×, Nordheim Mode (546K) 27×, Leon Boutique (243K) 25×, Boutique Paris (166K) 19×, Vitelli Moda (121K) 15×, Nordspur (89K) 12×, Karlson Berlin (981K) 12×, Falkenberg Mode (84K) 11×, Lumière Boutique (146K) 11×, Alpenkind Mode (118K) 9×, Montarello (206K) 9×, Vitelli Moda (103K) 9×, Alpenkind Mode (77K) 8×, Oliver & Blake (98K) 8×, Laurent Monaco (269K) 7×, Look de Paris (236K) 7×, Wilson & Carter (200K) 5×, Lumière Boutique (275K) 5×, Parisane (77K) 5×, Laurent Monaco (204K) 5×, North Style Fashion 5×, Risora (121K) 4×, Look de Paris (111K) 4×, Nicole Modehaus (32K) 4×, Velareeh Haus (134K) 4×, Davento (own store) · bestseller Davento 4×, dolce-paris.com (172K) 4×, northstyle-fashion.com · look-alike 3×, harperwells-boston.com (1700K) 3×, nordheim-mode.de (896K) 3×, Velareeh Haus (95K) 2×, Armand et Fils (195K) 2×, Anna Vera 2×, lozendafashion.com (314K) · look-alike 2×, Moreau Lyon (290K) 2×, Karlson Berlin (301K) 2×, Cole & Harrison (154K) 1×, Curve Bloom Nashville 1×, Michael Claire Vancouver 1×, Marlow & Quinn (20K) 1×, marlowandquinn.com · bestseller Davento 1×, nordheim-mode.de · bestseller Niaali 1×, oliverandblake.com (198K) · look-alike 1×, lookdeparis.com (111K) · look-alike 1×, nordheim-mode.de (896K) · look-alike 1×, annavera.it · look-alike 1×, urbanase.com · look-alike 1×, harperwells-boston.com (1700K) · look-alike 1×, parisane.fr (66K) · look-alike 1×, velareehhaus.com (134K) · look-alike 1×, larkandclover.com (214K) · look-alike 1×, Risora (115K) 1×, Margaret Robinson 1×, Parisane (66K) 1×, Armand et Fils (136K) 1×, Urbanase 1×, Amara Fiore 1×
A26: Newmae | B26: Market: United States · USD · catalogue 724 products (63% women) · 723 products · status: Not listed 316, Draft 0, Live 327, Issues 2, Duplicate 78 Strategy: A 348, B 210, C 103, E 47 Categories: Transition jacket 203, Sweater / hoodie 185, Boots 102, Cardigan 85, Winter coat 54, Trousers 24, Set 16, Other 14, Dress 12, Blouse / shirt 10, Blazer 9, Shoes 9 List weeks: week 1: 353, week 2: 213, week 3: 152, week 4: 5 Sources: Lozenda Fashion (315K) 216×, Lozenda Fashion (192K) 67×, Nordheim Mode (546K) 57×, Leon Boutique (243K) 41×, Dolce Paris (172K) 38×, Leon Boutique (344K) 34×, Nordheim Mode (896K) 31×, Cole & Harrison (154K) 19×, Karlson Berlin (981K) 15×, Lumière Boutique (275K) 15×, Lumière Boutique (146K) 15×, Boutique Paris (166K) 13×, Alpenkind Mode (118K) 12×, Laurent Monaco (269K) 9×, Wilson & Carter (200K) 8×, Vitelli Moda (121K) 8×, Velareeh Haus (95K) 7×, Parisane (77K) 6×, Laurent Monaco (204K) 6×, Look de Paris (111K) 6×, Alpenkind Mode (77K) 5×, Oliver & Blake (98K) 5×, Falkenberg Mode (84K) 5×, Nordspur (89K) 5×, Vitelli Moda (103K) 5×, Harper & Wells Boston (1700K) 5×, Oliver & Blake (199K) 5×, dolce-paris.com (172K) 5×, Look de Paris (236K) 4×, nordheim-mode.de (896K) 4×, Risora (121K) 3×, Velareeh Haus (134K) 3×, Davento (own store) · bestseller Davento 3×, Harper & Wells Boston (1500K) 2×, Emily Carter Manchester 2×, Rosati Milano (55K) 2×, Anna Vera 2×, wilson-and-carter.com (68K) · look-alike 2×, lozendafashion.com (314K) · look-alike 2×, lumiereboutique.fr (145K) 2×, lozendafashion.com (314K) 2×, Davies & Cooper 2×, Wilson & Carter (68K) 2×, Moreau Lyon (426K) 1×, Wentworth London (87K) 1×, Armand et Fils (195K) 1×, Parisane (66K) 1×, Manchester Boutique 1×, Vientovida (85K) 1×, Karlson Berlin (301K) 1×, boutique-paris.fr (59K) · look-alike 1×, lookdeparis.com (111K) · look-alike 1×, marlovale.com · look-alike 1×, annavera.it · look-alike 1×, chapslondon.co.uk · look-alike 1×, parisane.fr (66K) · look-alike 1×, ana-cortez.com · look-alike 1×, lookdeparis.com (111K) 1×, Nicole Modehaus (32K) 1×, Soof & Clay 1×, Mayfair & Finch 1×, Boutique Paris (60K) 1×, Boutique Élégance Bordeaux (34K) 1×, Moreau Lyon (290K) 1×, Armand et Fils (136K) 1×, Risora (115K) 1×
A28: Allowed sources
A29: Harper & Wells Boston | B29: US · 1,700,000 visits/month
A30: Drune | B30: DE · 1,500,000 visits/month
A31: Nordheim Mode | B31: DE · 896,300 visits/month
A32: Leon Boutique | B32: DE · 343,500 visits/month
A33: Lozenda Fashion | B33: DE · 314,800 visits/month
A34: Moreau Lyon | B34: FR · 289,800 visits/month
A35: Montarello | B35: US · 206,400 visits/month
A36: Laurent Monaco | B36: FR · 204,400 visits/month
A37: Oliver & Blake | B37: US · 198,900 visits/month
A38: Dolce Paris | B38: FR · 172,500 visits/month
A39: Cole & Harrison | B39: UK · 153,900 visits/month
A40: Lumière Boutique | B40: FR · 145,900 visits/month
... A47: Vitelli Moda | B47: IT · 103,300 visits/month

Sheet Stellamea
A1: Stellamea – 757 products to list (Spain, EUR)
A2: Sorted by list order · sources only big competitors (≥75K visits/month, verified) · status is set on the Links tab
A4: # | B4: Photo | C4: List week | D4: Strategy | E4: Score | F4: Product (source title) | G4: Category | H4: W/M | I4: Why this product | J4: Advised price (EUR) | K4: Category sweet spot (EUR) | L4: Price note | M4: Cost price – fill in (EUR) | N4: Margin % | O4: Source (import link) | P4: Source | Q4: Source country | R4: Photo score | S4: Photos | T4: Photo advice | U4: Other (big) sources | V4: Status (from Links) | W4: Added on
A5: 1 | C5: Week 1 | D5: A · Proven elsewhere, open in your market | E5: 102.1 | F5: Pull rayé à col montant pour femme chaud et moderne | G5: Sweater / hoodie | H5: ? | I5: top 17% bestseller at Lumière Boutique (FR, 275K visits/mo) · also at Karlson Berlin (DE), Lozenda Fashion (DE), Nordheim Mode (DE), Boutique Élégance Bordeaux (FR, small) +3 · no competitor sells it in ES yet → open space · added 2 days ago · season fit 1.0 | J5: 44.95 | K5: 44–60 | L5: take over the source link price | N5: =IF(M5="","",(J5-M5)/J5) | O5: Open | P5: Lumière Boutique (275K) | Q5: FR | R5: 93 | S5: 6 photos, 1st 1264×1264 | T5: Main photo free to use (no competitor in your market) | U5: https://karlson-berlin.com/products/carlotta-oversized-rollkragenpullover-mit-kontraststreifen https://nordheim-mode.de/products/clara-gestreifter-rollkragenpullover https://lozendafashion.com/products/rollkragenpullover-damen-oversized-angenehm-warm | V5: ='Stellamea – Links'!H5 | W5: 2026-10-02
A6: 2 | C6: Week 1 | D6: A · Proven elsewhere, open in your market | E6: 101.3 | F6: Elly™ - Hochkragen Weiches Stricktop | G6: Sweater / hoodie | H6: ? | I6: top 11% bestseller at Nordheim Mode (DE, 546K visits/mo) · also at Leon Boutique (DE), Lozenda Fashion (DE), Parisane (FR), Mayfair & Finch (UK, small) +1 · no competitor sells it in ES yet → open space · added 0 days ago · season fit 1.0 | J6: 39.95 | K6: 44–60 | L6: take over the source link price; below the category sweet spot, can go higher: 54.95 | N6: =IF(M6="","",(J6-M6)/J6) | O6: Open | P6: Nordheim Mode (546K) | Q6: DE | R6: 93 | S6: 8 photos, 1st 1200×1200 | T6: Main photo free to use (no competitor in your market) | U6: https://lozendafashion.com/products/strickpullover-damen-hochkragen-weicher-komfort https://leonboutique.co/products/mia-damen-oversized-strickpullover-mit-hochkragen-und-weitem-schnitt https://parisane.fr/products/pull-oversize-femme-a-col-montant-manches-longues | V6: ='Stellamea – Links'!H6 | W6: 2026-10-02
A7: 3 | C7: Week 1 | D7: A · Proven elsewhere, open in your market | E7: 100.2 | F7: Sevira | Entspannter Komfort-Pullover | G7: Sweater / hoodie | H7: ? | I7: top 2% bestseller at Karlson Berlin (DE, 981K visits/mo) · also at Leon Boutique (DE), Maison Villard (FR), Parisane (FR), Boutique Élégance Bordeaux (FR, small) +2 · no competitor sells it in ES yet → open space · added 15 days ago · season fit 1.0 | J7: 49.95 | K7: 44–60 | L7: take over the source link price | N7: =IF(M7="","",(J7-M7)/J7) | O7: Open | P7: Karlson Berlin (981K) | Q7: DE | R7: 100 | S7: 10 photos, 1st 1773×2364 | T7: Main photo free to use (no competitor in your market) | U7: https://leonboutique.co/products/sophie-damen-oversized-strukturstrick-pullover https://maisonvillard.fr/products/pull-oversize-en-maille-gaufree-pour-femme-col-rond-et-longue-coupe-ample-en-coton https://parisane.fr/products/pull-femme-oversize-en-tricot-gaufre-a-col-rond-et-manches-longues | V7: ='Stellamea – Links'!H7 | W7: 2026-10-02
A8: 4 | C8: Week 1 | D8: B · Broadly proven | E8: 99.9 | F8: Victor - Veste Cuir Élégante Moderne Homme | G8: Transition jacket | H8: M | I8: top 1% bestseller at Look de Paris (FR, 236K visits/mo) · also at Boutique Paris (FR), Drune (DE), Boutique Élégance Bordeaux (FR, small), Vientovida (ES, small) · 1 competitor(s) in ES · added 3 days ago · season fit 1.0 | J8: 69.99 | K8: 55–70 | L8: take over the source link price; note: already a bestseller at 1 competitor(s) in your market | N8: =IF(M8="","",(J8-M8)/J8) | O8: Open | P8: Look de Paris (236K) | Q8: FR | R8: 83 | S8: 5 photos, 1st 1080×1080 | T8: Same main photo as 1 competitor(s) in your market → use photo 2 (or a model photo) as main image | U8: https://drune.de/products/ww-elegant-herbstjacke https://boutique-paris.fr/products/pierre-veste-en-cuir-elegante-et-moderne | V8: ='Stellamea – Links'!H8 | W8: 2026-10-02
A9: 5 | C9: Week 1 | D9: A · Proven elsewhere, open in your market | E9: 99.8 | F9: Annika | Damen Bürojacke Figurbetonter Blazer | G9: Blazer | H9: W | I9: top 1% bestseller at Leon Boutique (DE, 243K visits/mo) · also at Harper & Wells Boston (US), Lozenda Fashion (DE), Parisane (FR), Velareeh Haus (DE) +3 · no competitor sells it in ES yet → open space · added 2 days ago · season fit 1.0 | J9: 35.95 | K9: 50–70 | L9: take over the source link price; below the category sweet spot, can go higher: 59.95 | N9: =IF(M9="","",(J9-M9)/J9) | O9: Open | P9: Leon Boutique (243K) | Q9: DE | R9: 87 | S9: 6 photos, 1st 1024×1024 | T9: Main photo free to use (no competitor in your market) | U9: https://lozendafashion.com/products/blazer-damen-tailliert-fur-die-perfekte-silhouette https://velareehhaus.com/products/annika-figurbetonter-buero-blazer https://parisane.fr/products/blazer-femme-cintre-a-col-crante-un-bouton | V9: ='Stellamea – Links'!H9 | W9: 2026-10-02
A10: 6 | C10: Week 1 | D10: A · Proven elsewhere, open in your market | E10: 99.7 | F10: Annika | Damen Eleganter Oversized Pullover | G10: Sweater / hoodie | H10: ? | I10: top 15% bestseller at Leon Boutique (DE, 243K visits/mo) · also at Boutique Paris (FR), Karlson Berlin (DE), Look de Paris (FR), Lozenda Fashion (DE) +12 · no competitor sells it in ES yet → open space · added 7 days ago · season fit 1.0 | J10: 54.95 | K10: 44–60 | L10: take over the source link price | N10: =IF(M10="","",(J10-M10)/J10) | O10: Open | P10: Leon Boutique (243K) | Q10: DE | R10: 90 | S10: 11 photos, 1st 900×1200 | T10: Main photo free to use (no competitor in your market) | U10: https://karlson-berlin.com/products/jane-oversized-pullover-mit-asymmetrischem-saum https://nordheim-mode.de/products/jane-oversized-pullover https://lozendafashion.com/products/strickpullover-damen-oversized | V10: ='Stellamea – Links'!H10 | W10: 2026-10-02
A11: 7 | C11: Week 1 | D11: A · Proven elsewhere, open in your market | E11: 99.5 | F11: Clara | Damen Oversized-Bomberjacke | G11: Transition jacket | H11: W | I11: top 3% bestseller at Nordheim Mode (DE, 546K visits/mo) · also at Karlson Berlin (DE), Leon Boutique (DE), Lozenda Fashion (DE), Lune Mode (IT, small) · no competitor sells it in ES yet → open space · added 7 days ago · season fit 1.0 | J11: 49.95 | K11: 55–70 | L11: take over the source link price; below the category sweet spot, can go higher: 59.95 | N11: =IF(M11="","",(J11-M11)/J11) | O11: Open | P11: Nordheim Mode (546K) | Q11: DE | R11: 94 | S11: 11 photos, 1st 1010×1200 | T11: Main photo free to use (no competitor in your market) | U11: https://karlson-berlin.com/products/clara-oversized-bomberjacke-mit-rippbuendchen https://lozendafashion.com/products/bomberjacke-damen-oversized-schnitt-rippbundchen https://leonboutique.co/products/elisabeth-damen-oversized-steppjacke-bomberjacke-kontrastnaht-kunstleder | V11: ='Stellamea – Links'!H11 | W11: 2026-10-02
A12: 8 | C12: Week 1 | D12: A · Proven elsewhere, open in your market | E12: 99.1 | F12: Isabella™ - Eleganter Rollkragenpullover | G12: Sweater / hoodie | H12: ? | I12: top 5% bestseller at Nordheim Mode (DE, 546K visits/mo) · also at Boutique Paris (FR), Falkenberg Mode (DE), Karlson Berlin (DE), Leon Boutique (DE) +7 · no competitor sells it in ES yet → open space · added 5 days ago · season fit 1.0 | J12: 49.95 | K12: 44–60 | L12: take over the source link price | N12: =IF(M12="","",(J12-M12)/J12) | O12: Open | P12: Nordheim Mode (546K) | Q12: DE | R12: 85 | S12: 6 photos, 1st 750×1000 | T12: Main photo free to use (no competitor in your market) | U12: https://karlson-berlin.com/products/isabella-rollkragenpullover-mit-ueberschnittenen-schultern https://lozendafashion.com/products/rollkragenpullover-damen-weicher-fall-warme-strickflache https://falkenberg-mode.de/products/isabella-rollkragenpullover-aus-kaschmir | V12: ='Stellamea – Links'!H12 | W12: 2026-10-02
A13: 9 | C13: Week 1 | D13: A · Proven elsewhere, open in your market | E13: 98.7 | F13: Eleganter Komfort-Pullover | G13: Sweater / hoodie | H13: ? | I13: top 1% bestseller at Lozenda Fashion (DE, 192K visits/mo) · also at Boutique Paris (FR), Look de Paris (FR), Nordheim Mode (DE), Velareeh Haus (DE) · no competitor sells it in ES yet → open space · added 8 days ago · season fit 1.0 | J13: 32.95 | K13: 44–60 | L13: take over the source link price; below the category sweet spot, can go higher: 54.95 | N13: =IF(M13="","",(J13-M13)/J13) | O13: Open | P13: Lozenda Fashion (192K) | Q13: DE | R13: 87 | S13: 12 photos, 1st 800×1067 | T13: Main photo free to use (no competitor in your market) | U13: https://nordheim-mode.de/products/grace-stilvoller-pullover https://velareehhaus.com/products/freya-weicher-rundhals-strickpullover https://lookdeparis.com/products/sandrine-pull-elegant-texture-col-zippe | V13: ='Stellamea – Links'!H13 | W13: 2026-10-02
A14: 10 | C14: Week 1 | D14: A · Proven elsewhere, open in your market | E14: 98.7 | F14: LONG SLEEVE POLO FOR MEN | G14: Blouse / shirt | H14: M | I14: top 3% bestseller at Wentworth London (UK, 87K visits/mo) · also at Alpenkind Mode (DE), Falkenberg Mode (DE), Karlson Berlin (DE), Leon Boutique (DE) +8 · no competitor sells it in ES yet → open space · added 13 days ago · season fit 1.0 | J14: 28.95 | K14: 39–52 | L14: source link price (24.95 GBP) converted; below the category sweet spot, can go higher: 39.95 | N14: =IF(M14="","",(J14-M14)/J14) | O14: Open | P14: Wentworth London (87K) | Q14: UK | R14: 90 | S14: 12 photos, 1st 900×1200 | T14: Main photo free to use (no competitor in your market) | U14: https://karlson-berlin.com/products/max-langarm-poloshirt-mit-karo-kontrastkragen https://nordheim-mode.de/products/max-langarm-polohemd https://velareehhaus.com/products/chris-herren-warmes-langarm-poloshirt-fw | V14: ='Stellamea – Links'!H14 | W14: 2026-10-02
A15: 11 | C15: Week 1 | D15: B · Broadly proven | E15: 98.7 | F15: Maximilian | Herren Vintage Biker Quilted Jacket Echtleder Reißverschluss | G15: Transition jacket | H15: ? | I15: top 13% bestseller at Leon Boutique (DE, 243K visits/mo) · also at Karlson Berlin (DE), Lozenda Fashion (DE), Nordheim Mode (DE), Velareeh Haus (DE) +2 · 1 competitor(s) in ES · added 6 days ago · season fit 1.0 | J15: 91.95 | K15: 55–70 | L15: take over the source link price; note: already a bestseller at 1 competitor(s) in your market | N15: =IF(M15="","",(J15-M15)/J15) | O15: Open | P15: Leon Boutique (243K) | Q15: DE | R15: 93 | S15: 7 photos, 1st 1200×1200 | T15: Same main photo as 1 competitor(s) in your market → use photo 2 (or a model photo) as main image | U15: https://karlson-berlin.com/products/hawthorne-vintage-jacke-mit-vier-taschen https://nordheim-mode.de/products/vintage-hawthorne-jacke https://lozendafashion.com/products/vintage-jacke-herren-kurzer-schnitt-vier-taschen | V15: ='Stellamea – Links'!H15 | W15: 2026-10-02
A16: 12 | C16: Week 1 | D16: B · Broadly proven | E16: 98.7 | F16: Juliette - Ensemble blazer élégant femme | G16: Blazer | H16: W | I16: top 6% bestseller at Look de Paris (FR, 236K visits/mo) · also at Boutique Paris (FR), Drune (DE), Lune Mode (IT, small), Vientovida (ES, small) · 1 competitor(s) in ES · added 2 days ago · season fit 1.0 | J16: 59.99 | K16: 50–70 | L16: take over the source link price; note: already a bestseller at 1 competitor(s) in your market | N16: =IF(M16="","",(J16-M16)/J16) | O16: Open | P16: Look de Paris (236K) | Q16: FR | R16: 96 | S16: 6 photos, 1st 1075×1344 | T16: Same main photo as 1 competitor(s) in your market → use photo 2 (or a model photo) as main image | U16: https://drune.de/products/drune-elegantes-blazer-set-o4u8u1 https://boutique-paris.fr/products/lina-ensemble-blazer-femme-elegant | V16: ='Stellamea – Links'!H16 | W16: 2026-10-02
... A142: 138 | C142: Week 1 | D142: A · Proven elsewhere, open in your market | E142: 84.2 | F142: Bridget | Relaxed Open-Front Cardigan | G142: Cardigan | H142: ? | I142: top 24% bestseller at Harper & Wells Boston (US, 1500K visits/mo) · also at Look de Paris (FR), Wilson & Carter (UK) · no competitor sells it in ES yet → open space · season fit 1.0 | J142: 63.95 | K142: 45–45 | L142: source link price (69.95 USD) converted | N142: =IF(M142="","",(J142-M142)/J142) | O142: Open | P142: Harper & Wells Boston (1500K) | Q142: US | R142: 100 | S142: 12 photos, 1st 1350×1800 | T142: Main photo free to use (no competitor in your market) | U142: https://lookdeparis.com/products/priya-gilet-elegant-oversize-maille https://wilson-and-carter.com/products/marceline | V142: ='Stellamea – Links'!H142 | W142: 2026-10-02
A143: 139 | C143: Week 1 | D143: B · Broadly proven | E143: 84.1 | F143: Strickjacke Damen | Floral & Leicht | G143: Cardigan | H143: W | I143: top 32% bestseller at Lozenda Fashion (DE, 192K visits/mo) · also at Boutique Élégance Bordeaux (FR, small), Montana Bella (ES, small), Urbanase (US, small) · 1 competitor(s) in ES · added 0 days ago · season fit 1.0 | J143: 37.95 | K143: 45–45 | L143: take over the source link price; below the category sweet spot, can go higher: 44.95 | N143: =IF(M143="","",(J143-M143)/J143) | O143: Open | P143: Lozenda Fashion (192K) | Q143: DE | R143: 71 | S143: 1 photos, 1st 1200×1600 | T143: Same main photo as a competitor in your market → use a different (supplier) photo as main image | V143: ='Stellamea – Links'!H143 | W143: 2026-10-02
A144: 140 | C144: Week 1 | D144: B · Broadly proven | E144: 84 | F144: Completo da donna con blazer e pantaloni | Perfetto per l'autunno | G144: Blazer | H144: W | I144: top 2% bestseller at Vitelli Moda (IT, 121K visits/mo) · also at Karlson Berlin (DE), Nordheim Mode (DE), Nicole Modehaus (DE, small), Vientovida (ES, small) · 1 competitor(s) in ES · season fit 1.0 | J144: 74.95 | K144: 50–70 | L144: take over the source link price | N144: =IF(M144="","",(J144-M144)/J144) | O144: Open | P144: Vitelli Moda (121K) | Q144: IT | R144: 89 | S144: 12 photos, 1st 1080×1080 | T144: Same main photo as 1 competitor(s) in your market → use photo 2 (or a model photo) as main image | U144: https://karlson-berlin.com/products/lucia-zweiteiler-mit-blazer-und-stoffhose https://nordheim-mode.de/products/lucia-hose | V144: ='Stellamea – Links'!H144 | W144: 2026-10-02
A145: 141 | C145: Week 1 | D145: A · Proven elsewhere, open in your market | E145: 84 | F145: Esme | Nordic Patterned Cardigan | G145: Cardigan | H145: ? | I145: top 11% bestseller at Harper & Wells Boston (US, 1500K visits/mo) · also at Boutique Paris (FR) · no competitor sells it in ES yet → open space · season fit 1.0 | J145: 54.95 | K145: 45–45 | L145: source link price (59.95 USD) converted | N145: =IF(M145="","",(J145-M145)/J145) | O145: Open | P145: Harper & Wells Boston (1500K) | Q145: US | R145: 100 | S145: 12 photos, 1st 1350×1800 | T145: Main photo free to use (no competitor in your market) | U145: https://boutique-paris.fr/products/elodie-gilet-feminin-boheme-col-v | V145: ='Stellamea – Links'!H145 | W145: 2026-10-02
A146: 142 | C146: Week 1 | D146: A · Proven elsewhere, open in your market | E146: 83.9 | F146: Maglione invernale a collo alto in tessuto morbido con dettagli sartoriali | G146: Sweater / hoodie | H146: ? | I146: top 17% bestseller at Vitelli Moda (IT, 121K visits/mo) · also at Armand et Fils (FR), Lozenda Fashion (DE), Oliver & Blake (US) · no competitor sells it in ES yet → open space · season fit 1.0 | J146: 54.95 | K146: 44–60 | L146: take over the source link price | N146: =IF(M146="","",(J146-M146)/J146) | O146: Open | P146: Vitelli Moda (121K) | Q146: IT | R146: 80 | S146: 12 photos, 1st 800×800 | T146: Main photo free to use (no competitor in your market) | U146: https://lozendafashion.com/products/pullover-herren-elegant-warmend https://armandetfils.fr/products/pull-homme-col-montant-classique https://oliverandblake.com/products/montclair-cashmere-sweater | V146: ='Stellamea – Links'!H146 | W146: 2026-10-02
A147: 143 | C147: Week 1 | D147: B · Broadly proven | E147: 83.9 | F147: Sweatshirt Damen | Kapuze & Lange Passform | G147: Sweater / hoodie | H147: W | I147: top 34% bestseller at Lozenda Fashion (DE, 192K visits/mo) · also at Velareeh Haus (DE), Mayfair & Finch (UK, small), Mercer & Bloom (US, small) · no competitor sells it in ES yet → open space · added 8 days ago · season fit 1.0 | J147: 42.95 | K147: 44–60 | L147: take over the source link price; below the category sweet spot, can go higher: 54.95 | N147: =IF(M147="","",(J147-M147)/J147) | O147: Open | P147: Lozenda Fashion (192K) | Q147: DE | R147: 87 | S147: 12 photos, 1st 800×1200 | T147: Main photo free to use (no competitor in your market) | U147: https://velareehhaus.com/products/mathilda-oversize-kapuzen-hoodie | V147: ='Stellamea – Links'!H147 | W147: 2026-10-02
A148: 144 | C148: Week 1 | D148: B · Broadly proven | E148: 83.8 | F148: Colton | Classic Rancher Weste | G148: Transition jacket | H148: ? | I148: top 40% bestseller at Karlson Berlin (DE, 981K visits/mo) · also at Lozenda Fashion (DE), Nordheim Mode (DE) · no competitor sells it in ES yet → open space · added 2 days ago · season fit 1.0 | J148: 59.95 | K148: 55–70 | L148: take over the source link price | N148: =IF(M148="","",(J148-M148)/J148) | O148: Open | P148: Karlson Berlin (981K) | Q148: DE | R148: 83 | S148: 5 photos, 1st 1080×1080 | T148: Main photo free to use (no competitor in your market) | U148: https://nordheim-mode.de/products/arthur https://lozendafashion.com/products/strickweste-herren-vielseitig-fur-jede-jahreszeit | V148: ='Stellamea – Links'!H148 | W148: 2026-10-02
A149: 145 | C149: Week 1 | D149: A · Proven elsewhere, open in your market | E149: 83.7 | F149: Premium Herren Pullover | G149: Sweater / hoodie | H149: M | I149: top 11% bestseller at Lozenda Fashion (DE, 192K visits/mo) · also at Leon Boutique (DE), Nordheim Mode (DE), Velareeh Haus (DE), Nicole Modehaus (DE, small) +1 · no competitor sells it in ES yet → open space · season fit 1.0 | J149: 49.95 | K149: 44–60 | L149: take over the source link price | N149: =IF(M149="","",(J149-M149)/J149) | O149: Open | P149: Lozenda Fashion (192K) | Q149: DE | R149: 80 | S149: 11 photos, 1st 800×800 | T149: Main photo free to use (no competitor in your market) | U149: https://nordheim-mode.de/products/ryan-warm-mohair-jersey-blue https://velareehhaus.com/products/matthias-herren-weicher-mohair-rundhals-pullover-fw https://leonboutique.co/products/matthias-herren-weicher-mohair-rundhals-knit-sweater-pullover | V149: ='Stellamea – Links'!H149 | W149: 2026-10-02
A150: 146 | C150: Week 1 | D150: A · Proven elsewhere, open in your market | E150: 83.5 | F150: Doris | Damen Strickpullover mit Lockerer Passform | G150: Sweater / hoodie | H150: W | I150: top 26% bestseller at Leon Boutique (DE, 243K visits/mo) · also at Boutique Paris (FR), Look de Paris (FR), Lozenda Fashion (DE), Nicole Modehaus (DE, small) +1 · no competitor sells it in ES yet → open space · season fit 1.0 | J150: 47.95 | K150: 44–60 | L150: take over the source link price | N150: =IF(M150="","",(J150-M150)/J150) | O150: Open | P150: Leon Boutique (243K) | Q150: DE | R150: 77 | S150: 5 photos, 1st 900×900 | T150: Main photo free to use (no competitor in your market) | U150: https://lozendafashion.com/products/amia-modischer-strickpullover-fur-damen https://lookdeparis.com/products/odile-pull-maille-femme-1 https://boutique-paris.fr/products/marie-pull-en-maille-elegant-pour-femme | V150: ='Stellamea – Links'!H150 | W150: 2026-10-02
A151: 147 | C151: Week 1 | D151: B · Broadly proven | E151: 83.5 | F151: Rollkragenpullover Damen | Weich & Warm | G151: Sweater / hoodie | H151: W | I151: top 36% bestseller at Lozenda Fashion (DE, 192K visits/mo) · also at Falkenberg Mode (DE), Leon Boutique (DE), Lune Mode (IT, small) · no competitor sells it in ES yet → open space · added 7 days ago · season fit 1.0 | J151: 47.95 | K151: 44–60 | L151: take over the source link price | N151: =IF(M151="","",(J151-M151)/J151) | O151: Open | P151: Lozenda Fashion (192K) | Q151: DE | R151: 85 | S151: 6 photos, 1st 750×1000 | T151: Main photo free to use (no competitor in your market) | U151: https://falkenberg-mode.de/products/noura https://leonboutique.co/products/clara-damen-oversized-rollkragen-knit-sweater-aus-weicher-wollmischung | V151: ='Stellamea – Links'!H151 | W151: 2026-10-02
A152: 148 | C152: Week 1 | D152: A · Proven elsewhere, open in your market | E152: 83.4 | F152: Herren Zweiteiliges Anzug Set mit Sakko und Hose | G152: Blazer | H152: M | I152: top 2% bestseller at Alpenkind Mode (DE, 77K visits/mo) · no competitor sells it in ES yet → open space · added 1 days ago · season fit 1.0 | J152: 54.95 | K152: 50–70 | L152: take over the source link price | N152: =IF(M152="","",(J152-M152)/J152) | O152: Open | P152: Alpenkind Mode (77K) | Q152: DE | R152: 75 | S152: 4 photos, 1st 800×1067 | T152: Main photo free to use (no competitor in your market) | V152: ='Stellamea – Links'!H152 | W152: 2026-10-02
A153: 149 | C153: Week 1 | D153: A · Proven elsewhere, open in your market | E153: 83.3 | F153: Maria - Veste De Printemps Élégante | G153: Transition jacket | H153: ? | I153: top 16% bestseller at Boutique Paris (FR, 166K visits/mo) · also at Parisane (FR), Cecile Lavelle (DE, small) · no competitor sells it in ES yet → open space · added 18 days ago · season fit 1.0 | J153: 49.99 | K153: 55–70 | L153: take over the source link price; below the category sweet spot, can go higher: 59.95 | N153: =IF(M153="","",(J153-M153)/J153) | O153: Open | P153: Boutique Paris (166K) | Q153: FR | R153: 86 | S153: 9 photos, 1st 1001×1001 | T153: Main photo free to use (no competitor in your market) | U153: https://parisane.fr/products/veste-en-laine-femme-surchemise-oversize-a-poches | V153: ='Stellamea – Links'!H153 | W153: 2026-10-02
A154: 150 | C154: Week 1 | D154: A · Proven elsewhere, open in your market | E154: 83.2 | F154: Lilla | Strickjacke im französischen Stil | G154: Cardigan | H154: W | I154: top 19% bestseller at Karlson Berlin (DE, 981K visits/mo) · also at Falkenberg Mode (DE), Lozenda Fashion (DE), Velareeh Haus (DE), Amara Fiore (IT, small) +7 · no competitor sells it in ES yet → open space · season fit 1.0 | J154: 44.95 | K154: 45–45 | L154: take over the source link price | N154: =IF(M154="","",(J154-M154)/J154) | O154: Open | P154: Karlson Berlin (981K) | Q154: DE | R154: 87 | S154: 6 photos, 1st 800×1067 | T154: Main photo free to use (no competitor in your market) | U154: https://lozendafashion.com/products/bequeme-strickjacke https://velareehhaus.com/products/annelie-lockere-feminine-strickjacke-fw https://falkenberg-mode.de/products/elvarine | V154: ='Stellamea – Links'!H154 | W154: 2026-10-02
A155: 151 | C155: Week 1 | D155: A · Proven elsewhere, open in your market | E155: 83.1 | F155: Birgit | Damen Freizeit-Strickjacke mit V-Ausschnitt und Knöpfen | G155: Cardigan | H155: W | I155: top 10% bestseller at Leon Boutique (DE, 243K visits/mo) · also at Lozenda Fashion (DE) · no competitor sells it in ES yet → open space · added 6 days ago · season fit 1.0 | J155: 39.95 | K155: 45–45 | L155: take over the source link price; below the category sweet spot, can go higher: 44.95 | N155: =IF(M155="","",(J155-M155)/J155) | O155: Open | P155: Leon Boutique (243K) | Q155: DE | R155: 80 | S155: 12 photos, 1st 800×799 | T155: Main photo free to use (no competitor in your market) | U155: https://lozendafashion.com/products/strickjacke-damen-v-ausschnitt-mit-knopfleiste | V155: ='Stellamea – Links'!H155 | W155: 2026-10-02
A156: 152 | C156: Week 1 | D156: A · Proven elsewhere, open in your market | E156: 83.1 | F156: Adrian | Casual Modern Button Cardigan | G156: Cardigan | H156: ? | I156: top 4% bestseller at Harper & Wells Boston (US, 1500K visits/mo) · also at Wilson & Carter (UK), Lune Mode (IT, small), Paul's Wardrobe (US, small) · no competitor sells it in ES yet → open space · season fit 1.0 | J156: 73.95 | K156: 45–45 | L156: source link price (79.95 USD) converted | N156: =IF(M156="","",(J156-M156)/J156) | O156: Open | P156: Harper & Wells Boston (1500K) | Q156: US | R156: 87 | S156: 8 photos, 1st 1024×1024 | T156: Main photo free to use (no competitor in your market) | U156: https://wilson-and-carter.com/products/godfrey-cardigan | V156: ='Stellamea – Links'!H156 | W156: 2026-10-02
A157: 153 | C157: Week 1 | D157: A · Proven elsewhere, open in your market | E157: 83.1 | F157: Blazer Set Damen | Business Look mit Komfort | G157: Blazer | H157: W | I157: top 21% bestseller at Lozenda Fashion (DE, 192K visits/mo) · also at Velareeh Haus (DE) · no competitor sells it in ES yet → open space · added 9 days ago · season fit 1.0 | J157: 59.95 | K157: 50–70 | L157: take over the source link price | N157: =IF(M157="","",(J157-M157)/J157) | O157: Open | P157: Lozenda Fashion (192K) | Q157: DE | R157: 100 | S157: 6 photos, 1st 1200×1800 | T157: Main photo free to use (no competitor in your market) | U157: https://velareehhaus.com/products/johanna-stilvolles-blazer-hosen-set | V157: ='Stellamea – Links'!H157 | W157: 2026-10-02
A158: 154 | C158: Week 1 | D158: A · Proven elsewhere, open in your market | E158: 82.8 | F158: Mantel Damen | Lang mit breitem Reverskragen | G158: Transition jacket | H158: W | I158: top 15% bestseller at Lozenda Fashion (DE, 192K visits/mo) · also at Karlson Berlin (DE), North Style Fashion (US, small) · no competitor sells it in ES yet → open space · added 8 days ago · season fit 1.0 | J158: 37.95 | K158: 55–70 | L158: take over the source link price; below the category sweet spot, can go higher: 59.95 | N158: =IF(M158="","",(J158-M158)/J158) | O158: Open | P158: Lozenda Fashion (192K) | Q158: DE | R158: 71 | S158: 4 photos, 1st 2160×3754 | T158: Main photo free to use (no competitor in your market) | U158: https://karlson-berlin.com/products/hertha-langer-mantel-mit-breitem-reverskragen | V158: ='Stellamea – Links'!H158 | W158: 2026-10-02
A159: 155 | C159: Week 1 | D159: B · Broadly proven | E159: 82.5 | F159: Strickpullover Damen | Naturprint & Gemütliche Passform | G159: Sweater / hoodie | H159: W | I159: top 32% bestseller at Lozenda Fashion (DE, 192K visits/mo) · also at Amara Fiore (IT, small), Lune Mode (IT, small), Walther Mode (IT, small) · no competitor sells it in ES yet → open space · added 6 days ago · season fit 1.0 | J159: 46.95 | K159: 44–60 | L159: take over the source link price | N159: =IF(M159="","",(J159-M159)/J159) | O159: Open | P159: Lozenda Fashion (192K) | Q159: DE | R159: 76 | S159: 3 photos, 1st 1440×1440 | T159: Main photo free to use (no competitor in your market) | V159: ='Stellamea – Links'!H159 | W159: 2026-10-02
A160: 156 | C160: Week 1 | D160: B · Broadly proven | E160: 82.5 | F160: Sarah | Elegant & Cozy Cardigan | G160: Cardigan | H160: ? | I160: top 1% bestseller at Harper & Wells Boston (US, 1500K visits/mo) · also at Oliver & Blake (US), Wilson & Carter (UK), Lune Mode (IT, small), Mayfair & Finch (UK, small) +3 · 1 competitor(s) in ES · season fit 1.0 | J160: 54.95 | K160: 45–45 | L160: source link price (59.95 USD) converted | N160: =IF(M160="","",(J160-M160)/J160) | O160: Open | P160: Harper & Wells Boston (1500K) | Q160: US | R160: 87 | S160: 7 photos, 1st 817×1089 | T160: Same main photo as 1 competitor(s) in your market → use photo 2 (or a model photo) as main image | U160: https://wilson-and-carter.com/products/camellia-cardigan https://oliverandblake.com/products/ofelia-elegant-long-cardigan-sweater | V160: ='Stellamea – Links'!H160 | W160: 2026-10-02
A161: 157 | C161: Week 1 | D161: A · Proven elsewhere, open in your market | E161: 82.5 | F161: Amelie | Stylish Velvet-Touch Bohemian Cardigan | G161: Cardigan | H161: ? | I161: top 10% bestseller at Wilson & Carter (UK, 200K visits/mo) · also at Donna's Dresses (US, small), Lune Mode (IT, small), Paul's Wardrobe (US, small), Soof & Clay (IT, small) · no competitor sells it in ES yet → open space · season fit 1.0 | J161: 57.95 | K161: 45–45 | L161: source link price (49.95 GBP) converted | N161: =IF(M161="","",(J161-M161)/J161) | O161: Open | P161: Wilson & Carter (200K) | Q161: UK | R161: 100 | S161: 10 photos, 1st 1728×2304 | T161: Main photo free to use (no competitor in your market) | V161: ='Stellamea – Links'!H161 | W161: 2026-10-02
A162: 158 | C162: Week 1 | D162: B · Broadly proven | E162: 82.2 | F162: Robert | Herren Freizeit-Polo-Sweatshirt mit langen Ärmeln | G162: Sweater / hoodie | H162: M | I162: top 10% bestseller at Leon Boutique (DE, 243K visits/mo) · also at Laurent Monaco (FR), Velareeh Haus (DE), Chaps London (UK, small), Vientovida (ES, small) · 1 competitor(s) in ES · season fit 1.0 | J162: 39.95 | K162: 44–60 | L162: take over the source link price; below the category sweet spot, can go higher: 54.95 | N162: =IF(M162="","",(J162-M162)/J162) | O162: Open | P162: Leon Boutique (243K) | Q162: DE | R162: 77 | S162: 10 photos, 1st 500×666 | T162: Same main photo as 1 competitor(s) in your market → use photo 2 (or a model photo) as main image | U162: https://velareehhaus.com/products/robert-herren-langarm-polo-sweatshirt https://laurentmonaco.fr/products/laurent-monaco-pull-over-polo-decontracte | V162: ='Stellamea – Links'!H162 | W162: 2026-10-02
A163: 159 | C163: Week 1 | D163: A · Proven elsewhere, open in your market | E163: 82.2 | F163: Isla™ - Leichte Zip-Up Jacke | G163: Transition jacket | H163: ? | I163: top 7% bestseller at Nordheim Mode (DE, 546K visits/mo) · also at Boutique Paris (FR), Leon Boutique (DE), Look de Paris (FR), Lozenda Fashion (DE) +1 · no competitor sells it in ES yet → open space · added 8 days ago · season fit 0.8 | J163: 39.95 | K163: 55–70 | L163: take over the source link price; below the category sweet spot, can go higher: 59.95 | N163: =IF(M163="","",(J163-M163)/J163) | O163: Open | P163: Nordheim Mode (546K) | Q163: DE | R163: 100 | S163: 12 photos, 1st 1350×1800 | T163: Main photo free to use (no competitor in your market) | U163: https://lozendafashion.com/products/steppjacke-damen-leicht-taillenkurz-geschnitten https://leonboutique.co/products/annika-damen-steppjacke-leichte-zip-up-bomberjacke-strukturierter-stoff https://lookdeparis.com/products/aurelie-veste-elegante-texturee-zippee | V163: ='Stellamea – Links'!H163 | W163: 2026-10-02
A164: 160 | C164: Week 1 | D164: A · Proven elsewhere, open in your market | E164: 82 | F164: Emilio Striped Blazer | G164: Blazer | H164: ? | I164: top 4% bestseller at Oliver & Blake (US, 98K visits/mo) · also at Parisane (FR) · no competitor sells it in ES yet → open space · season fit 1.0 | J164: 63.95 | K164: 50–70 | L164: source link price (69.99 USD) converted | N164: =IF(M164="","",(J164-M164)/J164) | O164: Open | P164: Oliver & Blake (98K) | Q164: US | R164: 96 | S164: 6 photos, 1st 1086×1448 | T164: Main photo free to use (no competitor in your market) | U164: https://parisane.fr/products/blazer-homme-raye-en-seersucker-leger-a-col-crante-et-coupe-cintree | V164: ='Stellamea – Links'!H164 | W164: 2026-10-02
A165: 161 | C165: Week 1 | D165: A · Proven elsewhere, open in your market | E165: 81.8 | F165: Madison | Chic Striped Silhouette Blouse | G165: Blouse / shirt | H165: ? | I165: top 4% bestseller at Harper & Wells Boston (US, 1500K visits/mo) · also at Lozenda Fashion (DE), Wilson & Carter (UK), Margaret Robinson (US, small), Mercer & Bloom (US, small) +1 · no competitor sells it in ES yet → open space · season fit 1.0 | J165: 45.95 | K165: 39–52 | L165: source link price (49.95 USD) converted | N165: =IF(M165="","",(J165-M165)/J165) | O165: Open | P165: Harper & Wells Boston (1500K) | Q165: US | R165: 82 | S165: 3 photos, 1st 1200×1600 | T165: Main photo free to use (no competitor in your market) | U165: https://lozendafashion.com/products/damen-retro-gestreiftes-lockeres-langarm-top https://wilson-and-carter.com/products/juliet-blouse | V165: ='Stellamea – Links'!H165 | W165: 2026-10-02
A166: 162 | C166: Week 1 | D166: A · Proven elsewhere, open in your market | E166: 81.8 | F166: Blazer cintré pour femme – élégant, confortable et polyvalent | G166: Blazer | H166: ? | I166: top 3% bestseller at Lumière Boutique (FR, 275K visits/mo) · also at Harper & Wells Boston (US), Wilson & Carter (UK), Amara Fiore (IT, small), Dolce Paris (FR, small) +4 · no competitor sells it in ES yet → open space · season fit 1.0 | J166: 39.95 | K166: 50–70 | L166: take over the source link price; below the category sweet spot, can go higher: 59.95 | N166: =IF(M166="","",(J166-M166)/J166) | O166: Open | P166: Lumière Boutique (275K) | Q166: FR | R166: 87 | S166: 8 photos, 1st 1024×1024 | T166: Main photo free to use (no competitor in your market) | U166: https://wilson-and-carter.com/products/charlotte-blazer https://harperwells-boston.com/products/sabine | V166: ='Stellamea – Links'!H166 | W166: 2026-10-02
A167: 163 | C167: Week 1 | D167: B · Broadly proven | E167: 81.6 | F167: Strickjacke Damen | Oversized Kapuzencardigan mit Kapuze | G167: Cardigan | H167: W | I167: top 36% bestseller at Lozenda Fashion (DE, 192K visits/mo) · also at Leon Boutique (DE), Falkenhof Mode (DE, small) · no competitor sells it in ES yet → open space · added 4 days ago · season fit 1.0 | J167: 46.95 | K167: 45–45 | L167: take over the source link price | N167: =IF(M167="","",(J167-M167)/J167) | O167: Open | P167: Lozenda Fashion (192K) | Q167: DE | R167: 93 | S167: 12 photos, 1st 1200×1200 | T167: Main photo free to use (no competitor in your market) | U167: https://leonboutique.co/products/annika-strickjacke-damen-oversized-kapuzen-cardigan-mit-fledermausrmeln | V167: ='Stellamea – Links'!H167 | W167: 2026-10-02
A168: 164 | C168: Week 1 | D168: B · Broadly proven | E168: 81.3 | F168: Jacqueline | Rollkragenpullover mit Waldprint | G168: Sweater / hoodie | H168: W | I168: top 39% bestseller at Velareeh Haus (DE, 95K visits/mo) · also at Lozenda Fashion (DE), Maison Villard (FR), Parisane (FR) · no competitor sells it in ES yet → open space · added 3 days ago · season fit 1.0 | J168: 44.95 | K168: 44–60 | L168: take over the source link price | N168: =IF(M168="","",(J168-M168)/J168) | O168: Open | P168: Velareeh Haus (95K) | Q168: DE | R168: 72 | S168: 3 photos, 1st 1080×1080 | T168: Main photo free to use (no competitor in your market) | U168: https://lozendafashion.com/products/rollkragenpullover-damen-warm-weich https://maisonvillard.fr/products/pull-col-montant-imprime-pour-femme-coupe-ample-et-grand-motif-integral-en-maille-douce https://parisane.fr/products/pull-femme-a-col-roule-en-maille-a-imprime-foret | V168: ='Stellamea – Links'!H168 | W168: 2026-10-02
A169: 165 | C169: Week 1 | D169: A · Proven elsewhere, open in your market | E169: 81.3 | F169: Damen Trendige Bluse | G169: Blouse / shirt | H169: W | I169: top 9% bestseller at Lozenda Fashion (DE, 192K visits/mo) · also at Falkenberg Mode (DE), Leon Boutique (DE), Margaret Robinson (US, small), Rosati Milano (IT, small) +1 · no competitor sells it in ES yet → open space · season fit 1.0 | J169: 34.95 | K169: 39–52 | L169: take over the source link price; below the category sweet spot, can go higher: 39.95 | N169: =IF(M169="","",(J169-M169)/J169) | O169: Open | P169: Lozenda Fashion (192K) | Q169: DE | R169: 100 | S169: 12 photos, 1st 1500×2000 | T169: Main photo free to use (no competitor in your market) | U169: https://falkenberg-mode.de/products/halcyon-womens-printed-button-up-shirt https://leonboutique.co/products/johanna-damen-gepunktete-bluse-mit-knopfleiste-und-print | V169: ='Stellamea – Links'!H169 | W169: 2026-10-02
A170: 166 | C170: Week 1 | D170: A · Proven elsewhere, open in your market | E170: 81.2 | F170: LUNA™ - STRICKJACKE | G170: Cardigan | H170: ? | I170: top 6% bestseller at Nordheim Mode (DE, 546K visits/mo) · also at Boutique Paris (FR), Look de Paris (FR), Lozenda Fashion (DE), Lune Mode (IT, small) +2 · no competitor sells it in ES yet → open space · season fit 1.0 | J170: 49.95 | K170: 45–45 | L170: take over the source link price | N170: =IF(M170="","",(J170-M170)/J170) | O170: Open | P170: Nordheim Mode (546K) | Q170: DE | R170: 86 | S170: 9 photos, 1st 1000×1000 | T170: Main photo free to use (no competitor in your market) | U170: https://lozendafashion.com/products/elegante-strickjacke-fur-damen https://lookdeparis.com/products/gabrielle-cardigan-cachemire-elegant-confortable-femme https://boutique-paris.fr/products/odile-cardigan-cachemire-elegant-et-confortable-femme | V170: ='Stellamea – Links'!H170 | W170: 2026-10-02
A171: 167 | C171: Week 1 | D171: A · Proven elsewhere, open in your market | E171: 81.2 | F171: Ava | Chic Two-Piece Blazer & Trouser Set | G171: Blazer | H171: ? | I171: top 4% bestseller at Harper & Wells Boston (US, 1500K visits/mo) · also at Velareeh Haus (DE), Soof & Clay (IT, small) · no competitor sells it in ES yet → open space · season fit 1.0 | J171: 73.95 | K171: 50–70 | L171: source link price (79.95 USD) converted | N171: =IF(M171="","",(J171-M171)/J171) | O171: Open | P171: Harper & Wells Boston (1500K) | Q171: US | R171: 94 | S171: 6 photos, 1st 1024×1536 | T171: Main photo free to use (no competitor in your market) | U171: https://velareehhaus.com/products/vera-eleganter-hosenanzug-mit-blazer | V171: ='Stellamea – Links'!H171 | W171: 2026-10-02
A172: 168 | C172: Week 1 | D172: B · Broadly proven | E172: 81.1 | F172: Daphne - Bunte Strickrollkragenpullover | G172: Sweater / hoodie | H172: W | I172: top 44% bestseller at Nordheim Mode (DE, 546K visits/mo) · also at Leon Boutique (DE), Lozenda Fashion (DE), Mercer & Bloom (US, small) · no competitor sells it in ES yet → open space · added 6 days ago · season fit 1.0 | J172: 34.95 | K172: 44–60 | L172: take over the source link price; below the category sweet spot, can go higher: 54.95 | N172: =IF(M172="","",(J172-M172)/J172) | O172: Open | P172: Nordheim Mode (546K) | Q172: DE | R172: 71 | S172: 1 photos, 1st 1800×2400 | T172: Main photo free to use (no competitor in your market) | U172: https://lozendafashion.com/products/rollkragenpullover-damen-auffalliges-muster-warm https://leonboutique.co/products/charlotte-damen-bunter-rollkragenpullover-strick-turtleneck-sweater | V172: ='Stellamea – Links'!H172 | W172: 2026-10-02
A173: 169 | C173: Week 1 | D173: A · Proven elsewhere, open in your market | E173: 81.1 | F173: Blazer Jacke Damen | Eleganter Kurzschnitt für jeden Anlass | G173: Blazer | H173: W | I173: top 1% bestseller at Lozenda Fashion (DE, 192K visits/mo) · also at Parisane (FR) · no competitor sells it in ES yet → open space · season fit 1.0 | J173: 32.95 | K173: 50–70 | L173: take over the source link price; below the category sweet spot, can go higher: 59.95 | N173: =IF(M173="","",(J173-M173)/J173) | O173: Open | P173: Lozenda Fashion (192K) | Q173: DE | R173: 87 | S173: 7 photos, 1st 800×1066 | T173: Main photo free to use (no competitor in your market) | U173: https://parisane.fr/products/blazer-court-femme-a-manches-3-4-ouvert-devant | V173: ='Stellamea – Links'!H173 | W173: 2026-10-02
... A179: 175 | C179: Week 1 | D179: B · Broadly proven | E179: 80.8 | F179: Emma - Grauer Pullover Für Damen In Übergrößen | G179: Sweater / hoodie | H179: W | I179: top 46% bestseller at Nordheim Mode (DE, 546K visits/mo) · also at Karlson Berlin (DE), Leon Boutique (DE), Lozenda Fashion (DE), Nordmodehaus (DE, small) · no competitor sells it in ES yet → open space · added 5 days ago · season fit 1.0 | J179: 64.95 | K179: 44–60 | L179: take over the source link price | N179: =IF(M179="","",(J179-M179)/J179) | O179: Open | P179: Nordheim Mode (546K) | Q179: DE | R179: 69 | S179: 3 photos, 1st 1000×1000 | T179: Main photo free to use (no competitor in your market) | U179: https://karlson-berlin.com/products/clara-oversize-rollkragenpullover https://lozendafashion.com/products/rollkragenpullover-damen-oversized-grobstrick https://leonboutique.co/products/charlotte-damen-oversized-turtleneck-sweater-grobstrick-longpullover | V179: ='Stellamea – Links'!H179 | W179: 2026-10-02
A180: 176 | C180: Week 1 | D180: A · Proven elsewhere, open in your market | E180: 80.8 | F180: Sofia – Manteau laine femme à col élégant | G180: Transition jacket | H180: W | I180: top 2% bestseller at Look de Paris (FR, 236K visits/mo) · also at Margaret Robinson (US, small), North Style Fashion (US, small), Soof & Clay (IT, small) · no competitor sells it in ES yet → open space · season fit 1.0 | J180: 49.99 | K180: 55–70 | L180: take over the source link price; below the category sweet spot, can go higher: 59.95 | N180: =IF(M180="","",(J180-M180)/J180) | O180: Open | P180: Look de Paris (236K) | Q180: FR | R180: 88 | S180: 12 photos, 1st 832×1248 | T180: Main photo free to use (no competitor in your market) | V180: ='Stellamea – Links'!H180 | W180: 2026-10-02
A181: 177 | C181: Week 1 | D181: B · Broadly proven | E181: 80.7 | F181: Pull Femme Hiver Chaud et Élégant | Style Festif | G181: Sweater / hoodie | H181: W | I181: top 4% bestseller at Lumière Boutique (FR, 275K visits/mo) · also at Parisane (FR), Boutique Élégance Bordeaux (FR, small), Dolce Paris (FR, small), Lune Mode (IT, small) +2 · 1 competitor(s) in ES · season fit 1.0 | J181: 39.95 | K181: 44–60 | L181: take over the source link price; below the category sweet spot, can go higher: 54.95 | N181: =IF(M181="","",(J181-M181)/J181) | O181: Open | P181: Lumière Boutique (275K) | Q181: FR | R181: 72 | S181: 3 photos, 1st 900×1200 | T181: Same main photo as 1 competitor(s) in your market → use photo 2 (or a model photo) as main image | U181: https://parisane.fr/products/pull-en-laine-chaud-pour-femme-a-col-a-revers-coupe-ample | V181: ='Stellamea – Links'!H181 | W181: 2026-10-02
A182: 178 | C182: Week 1 | D182: A · Proven elsewhere, open in your market | E182: 80.7 | F182: LINE – Warmer pullover mit Stehkragen | G182: Sweater / hoodie | H182: ? | I182: top 1% bestseller at Falkenberg Mode (DE, 84K visits/mo) · also at Alpenkind Mode (DE), Boutique Paris (FR), Leon Boutique (DE), Look de Paris (FR) +9 · no competitor sells it in ES yet → open space · season fit 1.0 | J182: 54.95 | K182: 44–60 | L182: take over the source link price | N182: =IF(M182="","",(J182-M182)/J182) | O182: Open | P182: Falkenberg Mode (84K) | Q182: DE | R182: 74 | S182: 5 photos, 1st 800×800 | T182: Main photo free to use (no competitor in your market) | U182: https://nordheim-mode.de/products/eleanor-rollkragenpullover https://alpenkindmode.com/products/damen-strickpullover-mit-stehkragen-und-zickzackmuster https://leonboutique.co/products/michaela-damen-lockere-strickpullover-mit-hohem-kragen | V182: ='Stellamea – Links'!H182 | W182: 2026-10-02
A183: 179 | C183: Week 1 | D183: A · Proven elsewhere, open in your market | E183: 80.5 | F183: Veste en cuir d’agneau pour homme – élégance hivernale, coupe structurée et confort premium | G183: Transition jacket | H183: M | I183: top 1% bestseller at Lumière Boutique (FR, 275K visits/mo) · also at Leon Boutique (DE), Velareeh Haus (DE), Boutique Élégance Bordeaux (FR, small), Lune Mode (IT, small) +1 · no competitor sells it in ES yet → open space · season fit 0.9 | J183: 89.95 | K183: 55–70 | L183: take over the source link price | N183: =IF(M183="","",(J183-M183)/J183) | O183: Open | P183: Lumière Boutique (275K) | Q183: FR | R183: 85 | S183: 7 photos, 1st 740×986 | T183: Main photo free to use (no competitor in your market) | U183: https://velareehhaus.com/products/roland-herren-klassische-gefuetterte-fliegerjacke-fw https://leonboutique.co/products/roland-herren-klassische-fliegerjacke-mit-reissverschluss | V183: ='Stellamea – Links'!H183 | W183: 2026-10-02
A184: 180 | C184: Week 1 | D184: B · Broadly proven | E184: 80.5 | F184: Strickjacke Damen | Zopfmuster & Knopfleiste | G184: Cardigan | H184: W | I184: top 36% bestseller at Lozenda Fashion (DE, 192K visits/mo) · also at Harper & Wells Boston (US), Wilson & Carter (UK) · no competitor sells it in ES yet → open space · added 7 days ago · season fit 1.0 | J184: 72.95 | K184: 45–45 | L184: take over the source link price | N184: =IF(M184="","",(J184-M184)/J184) | O184: Open | P184: Lozenda Fashion (192K) | Q184: DE | R184: 93 | S184: 10 photos, 1st 1350×1350 | T184: Main photo free to use (no competitor in your market) | U184: https://wilson-and-carter.com/products/harlow-cardigan https://harperwells-boston.com/products/lucinda | V184: ='Stellamea – Links'!H184 | W184: 2026-10-02
A185: 181 | C185: Week 1 | D185: B · Broadly proven | E185: 80.5 | F185: Cardigan Damen | Weich & Bequem | G185: Cardigan | H185: W | I185: top 38% bestseller at Lozenda Fashion (DE, 192K visits/mo) · also at Nicole Modehaus (DE, small), Soof & Clay (IT, small) · no competitor sells it in ES yet → open space · added 10 days ago · season fit 1.0 | J185: 47.95 | K185: 45–45 | L185: take over the source link price | N185: =IF(M185="","",(J185-M185)/J185) | O185: Open | P185: Lozenda Fashion (192K) | Q185: DE | R185: 100 | S185: 6 photos, 1st 1200×1600 | T185: Main photo free to use (no competitor in your market) | V185: ='Stellamea – Links'!H185 | W185: 2026-10-02
A186: 182 | C186: Week 1 | D186: B · Broadly proven | E186: 80.4 | F186: Maglione da Uomo con Zip e Colletto Alto, Vestibilità Comoda Autunnale | G186: Sweater / hoodie | H186: M | I186: top 23% bestseller at Vitelli Moda (IT, 121K visits/mo) · also at Boutique Paris (FR), Falkenberg Mode (DE), Karlson Berlin (DE), Leon Boutique (DE) +9 · 1 competitor(s) in ES · season fit 1.0 | J186: 53.95 | K186: 44–60 | L186: take over the source link price | N186: =IF(M186="","",(J186-M186)/J186) | O186: Open | P186: Vitelli Moda (121K) | Q186: IT | R186: 69 | S186: 8 photos, 1st 480×480 | T186: Same main photo as 1 competitor(s) in your market → use photo 2 (or a model photo) as main image | U186: https://karlson-berlin.com/products/orson https://nordheim-mode.de/products/jerry-reissverschluss https://risora-shop.de/products/herrenpullover-mit-reissverschlusskragen-luxus-und-komfort | V186: ='Stellamea – Links'!H186 | W186: 2026-10-02
A187: 183 | C187: Week 1 | D187: A · Proven elsewhere, open in your market | E187: 80.4 | F187: Chemise homme à manches longues | G187: Blouse / shirt | H187: M | I187: top 14% bestseller at Armand et Fils (FR, 195K visits/mo) · also at Vitelli Moda (IT), Chaps London (UK, small), Nordmodehaus (DE, small) · no competitor sells it in ES yet → open space · season fit 1.0 | J187: 43.95 | K187: 39–52 | L187: take over the source link price | N187: =IF(M187="","",(J187-M187)/J187) | O187: Open | P187: Armand et Fils (195K) | Q187: FR | R187: 93 | S187: 10 photos, 1st 2000×2000 | T187: Main photo free to use (no competitor in your market) | U187: https://vitellimoda.com/products/noah-camicia-di-alta-qualita-in-stile-formale-e-casual | V187: ='Stellamea – Links'!H187 | W187: 2026-10-02
A188: 184 | C188: Week 1 | D188: A · Proven elsewhere, open in your market | E188: 80.3 | F188: Abito Blazer Doppiopetto con Scollo a V | Perfetto per l'Autunno | G188: Blazer | H188: ? | I188: top 7% bestseller at Vitelli Moda (IT, 121K visits/mo) · also at Leon Boutique (DE), Falkenhof Mode (DE, small) · no competitor sells it in ES yet → open space · season fit 1.0 | J188: 49.95 | K188: 50–70 | L188: take over the source link price | N188: =IF(M188="","",(J188-M188)/J188) | O188: Open | P188: Vitelli Moda (121K) | Q188: IT | R188: 74 | S188: 5 photos, 1st 800×800 | T188: Main photo free to use (no competitor in your market) | U188: https://leonboutique.co/products/greta-damen-elegantes-blazerkleid-mit-langen-armeln | V188: ='Stellamea – Links'!H188 | W188: 2026-10-02
A189: 185 | C189: Week 1 | D189: B · Broadly proven | E189: 80.3 | F189: Brooklyn™ - Elegante Bluse | G189: Blouse / shirt | H189: ? | I189: top 7% bestseller at Nordheim Mode (DE, 546K visits/mo) · also at Harper & Wells Boston (US), Leon Boutique (DE), Lune Mode (IT, small), Mercer & Bloom (US, small) +3 · 1 competitor(s) in ES · season fit 0.9 | J189: 39.95 | K189: 39–52 | L189: take over the source link price | N189: =IF(M189="","",(J189-M189)/J189) | O189: Open | P189: Nordheim Mode (546K) | Q189: DE | R189: 93 | S189: 10 photos, 1st 1200×1200 | T189: Same main photo as 1 competitor(s) in your market → use photo 2 (or a model photo) as main image | U189: https://leonboutique.co/products/emma-damen-wasserfallkragen-langarm-top https://harperwells-boston.com/products/cordelia-blouse | V189: ='Stellamea – Links'!H189 | W189: 2026-10-02
A190: 186 | C190: Week 1 | D190: A · Proven elsewhere, open in your market | E190: 80.2 | F190: Veste Cardigan Femme Denim Décontracté Boutonné Style Moderne | G190: Cardigan | H190: W | I190: top 9% bestseller at Lumière Boutique (FR, 275K visits/mo) · also at Dolce Paris (FR, small), Lune Mode (IT, small), Soof & Clay (IT, small) · no competitor sells it in ES yet → open space · season fit 1.0 | J190: 39.95 | K190: 45–45 | L190: take over the source link price; below the category sweet spot, can go higher: 44.95 | N190: =IF(M190="","",(J190-M190)/J190) | O190: Open | P190: Lumière Boutique (275K) | Q190: FR | R190: 94 | S190: 5 photos, 1st 1792×2400 | T190: Main photo free to use (no competitor in your market) | V190: ='Stellamea – Links'!H190 | W190: 2026-10-02
A191: 187 | C191: Week 1 | D191: B · Broadly proven | E191: 80.1 | F191: Damen Mantel mit Taschen und Knöpfen, Karomuster, Langarm | G191: Transition jacket | H191: W | I191: top 33% bestseller at Nordheim Mode (DE, 546K visits/mo) · also at Harper & Wells Boston (US), Lumière Boutique (FR), Wilson & Carter (UK), Boutique Élégance Bordeaux (FR, small) · no competitor sells it in ES yet → open space · added 6 days ago · season fit 0.9 | J191: 69.95 | K191: 55–70 | L191: take over the source link price | N191: =IF(M191="","",(J191-M191)/J191) | O191: Open | P191: Nordheim Mode (546K) | Q191: DE | R191: 94 | S191: 5 photos, 1st 1656×2208 | T191: Main photo free to use (no competitor in your market) | U191: https://lumiereboutique.fr/products/manteau-femme-a-carreaux-colores-coupe-ample https://wilson-and-carter.com/products/marjorie-jacket https://harperwells-boston.com/products/penelope-jacket | V191: ='Stellamea – Links'!H191 | W191: 2026-10-02
A192: 188 | C192: Week 1 | D192: B · Broadly proven | E192: 80 | F192: Eleanora | Cable-Knit Button-Front Cardigan | G192: Cardigan | H192: ? | I192: top 27% bestseller at Harper & Wells Boston (US, 1500K visits/mo) · also at Look de Paris (FR), Wilson & Carter (UK) · no competitor sells it in ES yet → open space · season fit 1.0 | J192: 73.95 | K192: 45–45 | L192: source link price (79.95 USD) converted | N192: =IF(M192="","",(J192-M192)/J192) | O192: Open | P192: Harper & Wells Boston (1500K) | Q192: US | R192: 93 | S192: 12 photos, 1st 1773×1773 | T192: Main photo free to use (no competitor in your market) | U192: https://lookdeparis.com/products/isabelle-gilet-elegant-torsade-col-rond https://wilson-and-carter.com/products/cecilia-cardigan | V192: ='Stellamea – Links'!H192 | W192: 2026-10-02
A193: 189 | C193: Week 1 | D193: A · Proven elsewhere, open in your market | E193: 80 | F193: Marilla™ – Klassischer leichter Hemd-Cardigan | G193: Cardigan | H193: ? | I193: top 1% bestseller at Nordheim Mode (DE, 546K visits/mo) · also at Leon Boutique (DE), Lune Mode (IT, small) · no competitor sells it in ES yet → open space · season fit 1.0 | J193: 39.95 | K193: 45–45 | L193: take over the source link price; below the category sweet spot, can go higher: 44.95 | N193: =IF(M193="","",(J193-M193)/J193) | O193: Open | P193: Nordheim Mode (546K) | Q193: DE | R193: 94 | S193: 12 photos, 1st 1024×1536 | T193: Main photo free to use (no competitor in your market) | U193: https://leonboutique.co/products/marie-damen-strickjacke-leichte-baumwoll-leinen-hemd-cardigan-mit-knpfen | V193: ='Stellamea – Links'!H193 | W193: 2026-10-02
A194: 190 | C194: Week 1 | D194: A · Proven elsewhere, open in your market | E194: 79.9 | F194: Blazer Damen | Elegant & Alltagstauglich | G194: Blazer | H194: W | I194: top 10% bestseller at Lozenda Fashion (DE, 192K visits/mo) · also at Karlson Berlin (DE) · no competitor sells it in ES yet → open space · added 21 days ago · season fit 1.0 | J194: 47.95 | K194: 50–70 | L194: take over the source link price; below the category sweet spot, can go higher: 59.95 | N194: =IF(M194="","",(J194-M194)/J194) | O194: Open | P194: Lozenda Fashion (192K) | Q194: DE | R194: 93 | S194: 10 photos, 1st 1600×1600 | T194: Main photo free to use (no competitor in your market) | U194: https://karlson-berlin.com/products/svea-taillierter-blazer-mit-reverskragen | V194: ='Stellamea – Links'!H194 | W194: 2026-10-02
A195: 191 | C195: Week 1 | D195: A · Proven elsewhere, open in your market | E195: 79.8 | F195: Chester | Schickes Japanisches Hemd | G195: Blouse / shirt | H195: ? | I195: top 7% bestseller at Karlson Berlin (DE, 981K visits/mo) · also at Armand et Fils (FR), Lozenda Fashion (DE), Vitelli Moda (IT), Marlovale (IT, small) +1 · no competitor sells it in ES yet → open space · season fit 1.0 | J195: 54.95 | K195: 39–52 | L195: take over the source link price | N195: =IF(M195="","",(J195-M195)/J195) | O195: Open | P195: Karlson Berlin (981K) | Q195: DE | R195: 80 | S195: 8 photos, 1st 800×800 | T195: Main photo free to use (no competitor in your market) | U195: https://lozendafashion.com/products/langarm-polo-herren-stehkragen-bequemer-sitz https://armandetfils.fr/products/chemise-homme-a-col-montant-boutonnee https://vitellimoda.com/products/camicia-da-uomo-in-lino-leggero-con-vestibilita-comoda-i-ideale-per-primavera-ed-estate | V195: ='Stellamea – Links'!H195 | W195: 2026-10-02
A196: 192 | C196: Week 1 | D196: B · Broadly proven | E196: 79.8 | F196: Marius™ - Klassische Urban Jacke | G196: Transition jacket | H196: ? | I196: top 2% bestseller at Nordheim Mode (DE, 546K visits/mo) · also at Oliver & Blake (US), Parisane (FR), Velareeh Haus (DE), Amara Fiore (IT, small) +7 · 1 competitor(s) in ES · season fit 0.9 | J196: 49.95 | K196: 55–70 | L196: take over the source link price; below the category sweet spot, can go higher: 59.95; note: already a bestseller at 1 competitor(s) in your market | N196: =IF(M196="","",(J196-M196)/J196) | O196: Open | P196: Nordheim Mode (546K) | Q196: DE | R196: 86 | S196: 6 photos, 1st 1000×1000 | T196: Same main photo as 1 competitor(s) in your market → use photo 2 (or a model photo) as main image | U196: https://velareehhaus.com/products/dominik-herren-wildleder-bomber-steppjacke-fw https://parisane.fr/products/veste-en-cuir-suede-homme-urbaine-coupe-epuree https://oliverandblake.com/products/leo-suede-bomber | V196: ='Stellamea – Links'!H196 | W196: 2026-10-02
A197: 193 | C197: Week 1 | D197: B · Broadly proven | E197: 79.8 | F197: Camille | Stylish Tailored V-neck Blazer Dress | G197: Blazer | H197: ? | I197: top 6% bestseller at Harper & Wells Boston (US, 1500K visits/mo) · also at Nordheim Mode (DE), Wilson & Carter (UK), Donna's Dresses (US, small), Nicole Modehaus (DE, small) +2 · 1 competitor(s) in ES · season fit 1.0 | J197: 63.95 | K197: 50–70 | L197: source link price (69.95 USD) converted | N197: =IF(M197="","",(J197-M197)/J197) | O197: Open | P197: Harper & Wells Boston (1500K) | Q197: US | R197: 90 | S197: 12 photos, 1st 900×1200 | T197: Same main photo as 1 competitor(s) in your market → use photo 2 (or a model photo) as main image | U197: https://nordheim-mode.de/products/camille-massgeschneiderter-blazer-kleid https://wilson-and-carter.com/products/robyn-dress | V197: ='Stellamea – Links'!H197 | W197: 2026-10-02
A198: 194 | C198: Week 1 | D198: A · Proven elsewhere, open in your market | E198: 79.7 | F198: Peter | Herren warme Cordjacke mit Knopfleiste | G198: Transition jacket | H198: M | I198: top 7% bestseller at Leon Boutique (DE, 243K visits/mo) · also at Harper & Wells Boston (US), Velareeh Haus (DE), Wilson & Carter (UK) · no competitor sells it in ES yet → open space · season fit 0.9 | J198: 74.95 | K198: 55–70 | L198: take over the source link price | N198: =IF(M198="","",(J198-M198)/J198) | O198: Open | P198: Leon Boutique (243K) | Q198: DE | R198: 89 | S198: 6 photos, 1st 1080×1080 | T198: Main photo free to use (no competitor in your market) | U198: https://velareehhaus.com/products/peter-herren-warme-cordjacke-mit-knopfleiste https://wilson-and-carter.com/products/rupert-jacket https://harperwells-boston.com/products/harvey-jacket | V198: ='Stellamea – Links'!H198 | W198: 2026-10-02
A199: 195 | C199: Week 1 | D199: A · Proven elsewhere, open in your market | E199: 79.6 | F199: Cecilia | Soft Button-Front Cardigan | G199: Cardigan | H199: ? | I199: top 20% bestseller at Harper & Wells Boston (US, 1500K visits/mo) · also at Wilson & Carter (UK) · no competitor sells it in ES yet → open space · added 10 days ago · season fit 1.0 | J199: 68.95 | K199: 45–45 | L199: source link price (74.95 USD) converted | N199: =IF(M199="","",(J199-M199)/J199) | O199: Open | P199: Harper & Wells Boston (1500K) | Q199: US | R199: 74 | S199: 5 photos, 1st 800×800 | T199: Main photo free to use (no competitor in your market) | U199: https://wilson-and-carter.com/products/juniper-cardigan | V199: ='Stellamea – Links'!H199 | W199: 2026-10-02
A200: 196 | C200: Week 1 | D200: A · Proven elsewhere, open in your market | E200: 79.6 | F200: Matthew | Classic Button-Down Shirt | G200: Blouse / shirt | H200: ? | I200: top 7% bestseller at Harper & Wells Boston (US, 1500K visits/mo) · also at Leon Boutique (DE), Nordheim Mode (DE), Wilson & Carter (UK), Boutique Élégance Bordeaux (FR, small) +2 · no competitor sells it in ES yet → open space · season fit 1.0 | J200: 54.95 | K200: 39–52 | L200: source link price (59.95 USD) converted | N200: =IF(M200="","",(J200-M200)/J200) | O200: Open | P200: Harper & Wells Boston (1500K) | Q200: US | R200: 77 | S200: 9 photos, 1st 720×720 | T200: Main photo free to use (no competitor in your market) | U200: https://nordheim-mode.de/products/hartwell-classic-shirt https://leonboutique.co/products/leon-herren-langarmhemd-knopfleiste-regular-fit-baumwollhemd https://wilson-and-carter.com/products/oliver | V200: ='Stellamea – Links'!H200 | W200: 2026-10-02
A201: 197 | C201: Week 1 | D201: A · Proven elsewhere, open in your market | E201: 79.6 | F201: Ensemble Femme 3 Pièces Lin Coton Top Imprimé Cardigan Pantalon Large | G201: Cardigan | H201: W | I201: top 1% bestseller at Lumière Boutique (FR, 275K visits/mo) · also at Boutique Élégance Bordeaux (FR, small), Mercer & Bloom (US, small), Soof & Clay (IT, small) · no competitor sells it in ES yet → open space · season fit 1.0 | J201: 59.95 | K201: 45–45 | L201: take over the source link price | N201: =IF(M201="","",(J201-M201)/J201) | O201: Open | P201: Lumière Boutique (275K) | Q201: FR | R201: 81 | S201: 5 photos, 1st 791×1054 | T201: Main photo free to use (no competitor in your market) | V201: ='Stellamea – Links'!H201 | W201: 2026-10-02
A202: 198 | C202: Week 1 | D202: A · Proven elsewhere, open in your market | E202: 79.5 | F202: V-Ausschnitt Bluse Damen | Rüschen & Femininer Stil | G202: Blouse / shirt | H202: ? | I202: top 4% bestseller at Lozenda Fashion (DE, 192K visits/mo) · also at Falkenberg Mode (DE), Harper & Wells Boston (US), Nordheim Mode (DE), Wilson & Carter (UK) +6 · no competitor sells it in ES yet → open space · added 13 days ago · season fit 0.8 | J202: 47.95 | K202: 39–52 | L202: take over the source link price | N202: =IF(M202="","",(J202-M202)/J202) | O202: Open | P202: Lozenda Fashion (192K) | Q202: DE | R202: 87 | S202: 9 photos, 1st 800×1000 | T202: Main photo free to use (no competitor in your market) | U202: https://nordheim-mode.de/products/indie-ruschenshirt-mit-v-ausschnitt-und-langen-armeln https://falkenberg-mode.de/products/indie-blouse-with-ruffles-v-neck-and-long-sleeves https://wilson-and-carter.com/products/matilda-blouse | V202: ='Stellamea – Links'!H202 | W202: 2026-10-02
A203: 199 | C203: Week 1 | D203: A · Proven elsewhere, open in your market | E203: 79.4 | F203: Giacca Invernale Antivento e Impermeabile per la Stagione Fredda | G203: Transition jacket | H203: ? | I203: top 15% bestseller at Vitelli Moda (IT, 121K visits/mo) · also at Leon Boutique (DE), Nordheim Mode (DE), Velareeh Haus (DE), Boutique Élégance Bordeaux (FR, small) +1 · no competitor sells it in ES yet → open space · season fit 0.9 | J203: 79.95 | K203: 55–70 | L203: take over the source link price | N203: =IF(M203="","",(J203-M203)/J203) | O203: Open | P203: Vitelli Moda (121K) | Q203: IT | R203: 83 | S203: 11 photos, 1st 900×900 | T203: Main photo free to use (no competitor in your market) | U203: https://nordheim-mode.de/products/isaac-wasserdichte-outdoor-jacke https://velareehhaus.com/products/maximilian-herren-wasserdichte-outdoor-steppjacke https://leonboutique.co/products/maximilian-herren-wasserdichte-steppjacke-mit-kapuze-winddichte-outdoorjacke | V203: ='Stellamea – Links'!H203 | W203: 2026-10-02
A204: 200 | C204: Week 1 | D204: A · Proven elsewhere, open in your market | E204: 79.4 | F204: Jessica - Warm gefütterte Jacke | G204: Transition jacket | H204: ? | I204: top 7% bestseller at Nordheim Mode (DE, 546K visits/mo) · also at Look de Paris (FR) · no competitor sells it in ES yet → open space · added 9 days ago · season fit 0.9 | J204: 69.95 | K204: 55–70 | L204: take over the source link price | N204: =IF(M204="","",(J204-M204)/J204) | O204: Open | P204: Nordheim Mode (546K) | Q204: DE | R204: 89 | S204: 12 photos, 1st 1080×1080 | T204: Main photo free to use (no competitor in your market) | U204: https://lookdeparis.com/products/delphine-veste-elegante-chaude-capuche | V204: ='Stellamea – Links'!H204 | W204: 2026-10-02
A205: 201 | C205: Week 1 | D205: A · Proven elsewhere, open in your market | E205: 79.3 | F205: Saravia | Lässiger Mantel mit Knopfleiste | G205: Transition jacket | H205: ? | I205: top 25% bestseller at Karlson Berlin (DE, 981K visits/mo) · also at Velareeh Haus (DE), Mayfair & Finch (UK, small), Mercer & Bloom (US, small), Nicole Modehaus (DE, small) · no competitor sells it in ES yet → open space · season fit 1.0 | J205: 69.95 | K205: 55–70 | L205: take over the source link price | N205: =IF(M205="","",(J205-M205)/J205) | O205: Open | P205: Karlson Berlin (981K) | Q205: DE | R205: 80 | S205: 6 photos, 1st 800×800 | T205: Main photo free to use (no competitor in your market) | U205: https://velareehhaus.com/products/mathilda-langer-trenchcoat-mit-knopfleiste-fw | V205: ='Stellamea – Links'!H205 | W205: 2026-10-02
A206: 202 | C206: Week 1 | D206: B · Broadly proven | E206: 79.2 | F206: Andrew | Multicolor Long Sleeve Shirt | G206: Blouse / shirt | H206: ? | I206: top 2% bestseller at Harper & Wells Boston (US, 1500K visits/mo) · also at Lumière Boutique (FR), Wilson & Carter (UK), Nordmodehaus (DE, small), Paul's Wardrobe (US, small) +1 · 1 competitor(s) in ES · season fit 1.0 | J206: 45.95 | K206: 39–52 | L206: source link price (49.95 USD) converted | N206: =IF(M206="","",(J206-M206)/J206) | O206: Open | P206: Harper & Wells Boston (1500K) | Q206: US | R206: 75 | S206: 4 photos, 1st 1000×1000 | T206: Same main photo as 1 competitor(s) in your market → use photo 2 (or a model photo) as main image | U206: https://lumiereboutique.fr/products/t-shirt-homme-col-henley-patchwork-geometrique-manches-longues https://wilson-and-carter.com/products/george-shirt | V206: ='Stellamea – Links'!H206 | W206: 2026-10-02
A207: 203 | C207: Week 1 | D207: B · Broadly proven | E207: 79.2 | F207: Estella | Chunky Knit Cardigan | G207: Cardigan | H207: ? | I207: top 39% bestseller at Harper & Wells Boston (US, 1500K visits/mo) · also at Boutique Paris (FR), Look de Paris (FR), Wilson & Carter (UK) · no competitor sells it in ES yet → open space · season fit 1.0 | J207: 45.95 | K207: 45–45 | L207: source link price (49.95 USD) converted | N207: =IF(M207="","",(J207-M207)/J207) | O207: Open | P207: Harper & Wells Boston (1500K) | Q207: US | R207: 87 | S207: 5 photos, 1st 1340×1340 | T207: Main photo free to use (no competitor in your market) | U207: https://lookdeparis.com/products/isabelle-gilet-elegant-grosse-maille-torsade https://boutique-paris.fr/products/christine-gilet-elegant-grosse-maille-torsadee https://wilson-and-carter.com/products/elowen-cardigan | V207: ='Stellamea – Links'!H207 | W207: 2026-10-02
A208: 204 | C208: Week 1 | D208: B · Broadly proven | E208: 79.2 | F208: Nina | Classic Retro Bohemian Striped Blazer | G208: Blazer | H208: ? | I208: top 7% bestseller at Wilson & Carter (UK, 200K visits/mo) · also at Lumière Boutique (FR), Boutique Élégance Bordeaux (FR, small), Donna's Dresses (US, small), Luz Estilo (ES, small) +1 · 1 competitor(s) in ES · season fit 1.0 | J208: 46.95 | K208: 50–70 | L208: source link price (39.95 GBP) converted; below the category sweet spot, can go higher: 59.95 | N208: =IF(M208="","",(J208-M208)/J208) | O208: Open | P208: Wilson & Carter (200K) | Q208: UK | R208: 90 | S208: 10 photos, 1st 900×1200 | T208: Same main photo as 1 competitor(s) in your market → use photo 2 (or a model photo) as main image | U208: https://lumiereboutique.fr/products/blazer-boheme-raye-pour-femmes-avec-imprime-floral-vintage | V208: ='Stellamea – Links'!H208 | W208: 2026-10-02
A209: 205 | C209: Week 1 | D209: A · Proven elsewhere, open in your market | E209: 79 | F209: Herren Cordblazer- und Westen-Set | G209: Blazer | H209: M | I209: top 5% bestseller at Alpenkind Mode (DE, 77K visits/mo) · no competitor sells it in ES yet → open space · added 13 days ago · season fit 1.0 | J209: 74.95 | K209: 50–70 | L209: take over the source link price | N209: =IF(M209="","",(J209-M209)/J209) | O209: Open | P209: Alpenkind Mode (77K) | Q209: DE | R209: 83 | S209: 5 photos, 1st 1080×1080 | T209: Main photo free to use (no competitor in your market) | V209: ='Stellamea – Links'!H209 | W209: 2026-10-02
A210: 206 | C210: Week 1 | D210: A · Proven elsewhere, open in your market | E210: 79 | F210: Harold | Refined Single Breasted Cardigan | G210: Cardigan | H210: ? | I210: top 2% bestseller at Harper & Wells Boston (US, 1500K visits/mo) · also at Lune Mode (IT, small), Urbanase (US, small) · no competitor sells it in ES yet → open space · season fit 1.0 | J210: 73.95 | K210: 45–45 | L210: source link price (79.95 USD) converted | N210: =IF(M210="","",(J210-M210)/J210) | O210: Open | P210: Harper & Wells Boston (1500K) | Q210: US | R210: 87 | S210: 5 photos, 1st 2048×2048 | T210: Main photo free to use (no competitor in your market) | V210: ='Stellamea – Links'!H210 | W210: 2026-10-02
A211: 207 | C211: Week 1 | D211: A · Proven elsewhere, open in your market | E211: 79 | F211: Aurélie – Manteau femme hiver évasé à col en fausse fourrure | G211: Transition jacket | H211: W | I211: top 5% bestseller at Parisane (FR, 77K visits/mo) · also at Look de Paris (FR), Nordheim Mode (DE), Rosati Milano (IT, small) · no competitor sells it in ES yet → open space · season fit 1.0 | J211: 69.99 | K211: 55–70 | L211: take over the source link price | N211: =IF(M211="","",(J211-M211)/J211) | O211: Open | P211: Parisane (77K) | Q211: FR | R211: 89 | S211: 12 photos, 1st 1080×1080 | T211: Main photo free to use (no competitor in your market) | U211: https://nordheim-mode.de/products/hannah-jacke https://lookdeparis.com/products/louise-manteau-femme-hiver | V211: ='Stellamea – Links'!H211 | W211: 2026-10-02
A212: 208 | C212: Week 1 | D212: A · Proven elsewhere, open in your market | E212: 78.7 | F212: Evangeline | Relaxed Open-Front Cardigan | G212: Cardigan | H212: ? | I212: top 23% bestseller at Harper & Wells Boston (US, 1500K visits/mo) · also at Wilson & Carter (UK) · no competitor sells it in ES yet → open space · added 10 days ago · season fit 1.0 | J212: 77.95 | K212: 45–45 | L212: source link price (84.95 USD) converted | N212: =IF(M212="","",(J212-M212)/J212) | O212: Open | P212: Harper & Wells Boston (1500K) | Q212: US | R212: 74 | S212: 5 photos, 1st 800×800 | T212: Main photo free to use (no competitor in your market) | U212: https://wilson-and-carter.com/products/edith | V212: ='Stellamea – Links'!H212 | W212: 2026-10-02
A213: 209 | C213: Week 1 | D213: C · New & rising | E213: 78.7 | F213: Strickjacke Damen Oversized | V-Ausschnitt & Angenehme Wärme | G213: Cardigan | H213: W | I213: top 31% bestseller at Lozenda Fashion (DE, 192K visits/mo) · also at Leon Boutique (DE) · no competitor sells it in ES yet → open space · added 0 days ago · season fit 1.0 | J213: 55.95 | K213: 45–45 | L213: take over the source link price | N213: =IF(M213="","",(J213-M213)/J213) | O213: Open | P213: Lozenda Fashion (192K) | Q213: DE | R213: 93 | S213: 9 photos, 1st 1392×1392 | T213: Main photo free to use (no competitor in your market) | U213: https://leonboutique.co/products/mia-strickjacke-damen-oversized-flauschige-v-ausschnitt-oberbekleidung | V213: ='Stellamea – Links'!H213 | W213: 2026-10-02
A214: 210 | C214: Week 1 | D214: A · Proven elsewhere, open in your market | E214: 78.6 | F214: Gabrielle - Manteau De Laine Élégant | G214: Transition jacket | H214: ? | I214: top 16% bestseller at Boutique Paris (FR, 166K visits/mo) · also at Nordheim Mode (DE), Falkenhof Mode (DE, small), Mercer & Bloom (US, small), Soof & Clay (IT, small) · no competitor sells it in ES yet → open space · added 3 days ago · season fit 0.8 | J214: 59.99 | K214: 55–70 | L214: take over the source link price | N214: =IF(M214="","",(J214-M214)/J214) | O214: Open | P214: Boutique Paris (166K) | Q214: FR | R214: 93 | S214: 10 photos, 1st 1600×1600 | T214: Main photo free to use (no competitor in your market) | U214: https://nordheim-mode.de/products/hannah-damen-prestige-mantel-mit-taillierter-passform-und-klassischem-design | V214: ='Stellamea – Links'!H214 | W214: 2026-10-02
A215: 211 | C215: Week 1 | D215: A · Proven elsewhere, open in your market | E215: 78.5 | F215: Erich | Herren Lässige Warme Kariert Jacke zum Knöpfen | G215: Transition jacket | H215: M | I215: top 10% bestseller at Leon Boutique (DE, 243K visits/mo) · also at Harper & Wells Boston (US), Velareeh Haus (DE), Wilson & Carter (UK) · no competitor sells it in ES yet → open space · season fit 0.9 | J215: 84.95 | K215: 55–70 | L215: take over the source link price | N215: =IF(M215="","",(J215-M215)/J215) | O215: Open | P215: Leon Boutique (243K) | Q215: DE | R215: 89 | S215: 12 photos, 1st 1080×1080 | T215: Main photo free to use (no competitor in your market) | U215: https://velareehhaus.com/products/erich-herren-warme-karierte-jacke-mit-knopfleiste https://wilson-and-carter.com/products/roland-jacket https://harperwells-boston.com/products/rhett-jacket | V215: ='Stellamea – Links'!H215 | W215: 2026-10-02
A216: 212 | C216: Week 1 | D216: A · Proven elsewhere, open in your market | E216: 78.4 | F216: Dahlia - Stilvoller Cardigan | G216: Cardigan | H216: ? | I216: top 12% bestseller at Nordheim Mode (DE, 546K visits/mo) · also at Leon Boutique (DE) · no competitor sells it in ES yet → open space · season fit 1.0 | J216: 44.95 | K216: 45–45 | L216: take over the source link price | N216: =IF(M216="","",(J216-M216)/J216) | O216: Open | P216: Nordheim Mode (546K) | Q216: DE | R216: 86 | S216: 8 photos, 1st 1000×1000 | T216: Main photo free to use (no competitor in your market) | U216: https://leonboutique.co/products/edith-damen-trendige-flauschige-strickjacke-mit-knopfleiste | V216: ='Stellamea – Links'!H216 | W216: 2026-10-02
A217: 213 | C217: Week 1 | D217: A · Proven elsewhere, open in your market | E217: 78.4 | F217: Theresa | Elegante Wasserfallausschnitt Satinbluse für Damen | G217: Blouse / shirt | H217: W | I217: top 1% bestseller at Leon Boutique (DE, 243K visits/mo) · also at Velareeh Haus (DE), Falkenhof Mode (DE, small), Mayfair & Finch (UK, small), Soof & Clay (IT, small) +1 · no competitor sells it in ES yet → open space · season fit 0.9 | J217: 44.95 | K217: 39–52 | L217: take over the source link price | N217: =IF(M217="","",(J217-M217)/J217) | O217: Open | P217: Leon Boutique (243K) | Q217: DE | R217: 86 | S217: 10 photos, 1st 1000×1000 | T217: Main photo free to use (no competitor in your market) | U217: https://velareehhaus.com/products/theresa-elegante-wasserfall-satinbluse-fw | V217: ='Stellamea – Links'!H217 | W217: 2026-10-02
A218: 214 | C218: Week 1 | D218: A · Proven elsewhere, open in your market | E218: 78.3 | F218: Teri | Damen Strickjacke mit Kapuze und Knöpfen | G218: Cardigan | H218: W | I218: top 3% bestseller at Nordheim Mode (DE, 546K visits/mo) · also at Karlson Berlin (DE), Lune Mode (IT, small), Rosati Milano (IT, small) · no competitor sells it in ES yet → open space · season fit 1.0 | J218: 44.95 | K218: 45–45 | L218: take over the source link price | N218: =IF(M218="","",(J218-M218)/J218) | O218: Open | P218: Nordheim Mode (546K) | Q218: DE | R218: 59 | S218: 4 photos, 1st 540×540 | T218: Main photo free to use (no competitor in your market) | U218: https://karlson-berlin.com/products/teri-strickjacke-mit-kapuze-und-seitentaschen | V218: ='Stellamea – Links'!H218 | W218: 2026-10-02
A219: 215 | C219: Week 1 | D219: A · Proven elsewhere, open in your market | E219: 78.3 | F219: Hazel | Floral Open-Front Cardigan | G219: Cardigan | H219: ? | I219: top 11% bestseller at Harper & Wells Boston (US, 1500K visits/mo) · also at Boutique Paris (FR), Wilson & Carter (UK) · no competitor sells it in ES yet → open space · season fit 1.0 | J219: 59.95 | K219: 45–45 | L219: source link price (64.95 USD) converted | N219: =IF(M219="","",(J219-M219)/J219) | O219: Open | P219: Harper & Wells Boston (1500K) | Q219: US | R219: 62 | S219: 3 photos, 1st 800×800 | T219: Main photo free to use (no competitor in your market) | U219: https://boutique-paris.fr/products/manon-gilet-feminin-fleuri-brode-boutonne https://wilson-and-carter.com/products/greta-cardigan | V219: ='Stellamea – Links'!H219 | W219: 2026-10-02
A220: 216 | C220: Week 1 | D220: B · Broadly proven | E220: 78.2 | F220: Belle | Luxuriöser und bequemer Pullover | G220: Sweater / hoodie | H220: ? | I220: top 27% bestseller at Nordheim Mode (DE, 546K visits/mo) · also at Boutique Paris (FR), Look de Paris (FR) · no competitor sells it in ES yet → open space · added 8 days ago · season fit 1.0 | J220: 44.95 | K220: 44–60 | L220: take over the source link price | N220: =IF(M220="","",(J220-M220)/J220) | O220: Open | P220: Nordheim Mode (546K) | Q220: DE | R220: 66 | S220: 2 photos, 1st 888×1080 | T220: Main photo free to use (no competitor in your market) | U220: https://lookdeparis.com/products/isabelle-pull-chic-vintage-imprime https://boutique-paris.fr/products/aurelie-pull-chic-imprime-vichy | V220: ='Stellamea – Links'!H220 | W220: 2026-10-02
A221: 217 | C221: Week 1 | D221: A · Proven elsewhere, open in your market | E221: 78.2 | F221: Della | Cozy Oversized Cardigan | G221: Cardigan | H221: ? | I221: top 10% bestseller at Harper & Wells Boston (US, 1500K visits/mo) · also at Wilson & Carter (UK), Donna's Dresses (US, small), North Style Fashion (US, small), Soof & Clay (IT, small) · no competitor sells it in ES yet → open space · season fit 1.0 | J221: 73.95 | K221: 45–45 | L221: source link price (79.95 USD) converted | N221: =IF(M221="","",(J221-M221)/J221) | O221: Open | P221: Harper & Wells Boston (1500K) | Q221: US | R221: 77 | S221: 6 photos, 1st 720×720 | T221: Main photo free to use (no competitor in your market) | U221: https://wilson-and-carter.com/products/elise-cardigan | V221: ='Stellamea – Links'!H221 | W221: 2026-10-02
A222: 218 | C222: Week 1 | D222: A · Proven elsewhere, open in your market | E222: 78.1 | F222: Blazer Herren | Regular Fit & Vintage-Look | G222: Blazer | H222: M | I222: top 6% bestseller at Lozenda Fashion (DE, 192K visits/mo) · no competitor sells it in ES yet → open space · season fit 1.0 | J222: 122.95 | K222: 50–70 | L222: take over the source link price | N222: =IF(M222="","",(J222-M222)/J222) | O222: Open | P222: Lozenda Fashion (192K) | Q222: DE | R222: 98 | S222: 12 photos, 1st 1140×1500 | T222: Main photo free to use (no competitor in your market) | V222: ='Stellamea – Links'!H222 | W222: 2026-10-02
A223: 219 | C223: Week 1 | D223: B · Broadly proven | E223: 77.9 | F223: Herren Farbblockierter Halb-Reißverschluss Strickpullover | G223: Sweater / hoodie | H223: M | I223: top 8% bestseller at Nordheim Mode (DE, 546K visits/mo) · also at Velareeh Haus (DE), Boutique Élégance Bordeaux (FR, small), Rosati Milano (IT, small), Vientovida (ES, small) · 1 competitor(s) in ES · season fit 1.0 | J223: 44.95 | K223: 44–60 | L223: take over the source link price | N223: =IF(M223="","",(J223-M223)/J223) | O223: Open | P223: Nordheim Mode (546K) | Q223: DE | R223: 55 | S223: 1 photos, 1st 720×960 | T223: Same main photo as a competitor in your market → use a different (supplier) photo as main image | U223: https://velareehhaus.com/products/daniel-herren-stilvoller-strickpullover | V223: ='Stellamea – Links'!H223 | W223: 2026-10-02
A224: 220 | C224: Week 1 | D224: A · Proven elsewhere, open in your market | E224: 77.9 | F224: Rosenda | Strukturierter Mantel mit Kapuze | G224: Transition jacket | H224: ? | I224: top 18% bestseller at Karlson Berlin (DE, 981K visits/mo) · also at Lozenda Fashion (DE), Nicole Modehaus (DE, small), Rosati Milano (IT, small) · no competitor sells it in ES yet → open space · season fit 1.0 | J224: 59.95 | K224: 55–70 | L224: take over the source link price | N224: =IF(M224="","",(J224-M224)/J224) | O224: Open | P224: Karlson Berlin (981K) | Q224: DE | R224: 90 | S224: 5 photos, 1st 1080×1440 | T224: Main photo free to use (no competitor in your market) | U224: https://lozendafashion.com/products/eleganter-maxi-mantel-mit-kapuze | V224: ='Stellamea – Links'!H224 | W224: 2026-10-02
A225: 221 | C225: Week 1 | D225: B · Broadly proven | E225: 77.8 | F225: Cardigan Damen | Lässige Passform mit Knopfdetails | G225: Cardigan | H225: W | I225: top 38% bestseller at Lozenda Fashion (DE, 192K visits/mo) · also at Nordheim Mode (DE), Margaret Robinson (US, small), Montana Bella (ES, small) · 1 competitor(s) in ES · added 10 days ago · season fit 1.0 | J225: 42.95 | K225: 45–45 | L225: take over the source link price; below the category sweet spot, can go higher: 44.95 | N225: =IF(M225="","",(J225-M225)/J225) | O225: Open | P225: Lozenda Fashion (192K) | Q225: DE | R225: 71 | S225: 1 photos, 1st 1200×1600 | T225: Same main photo as a competitor in your market → use a different (supplier) photo as main image | U225: https://nordheim-mode.de/products/fruhling-wiesen-floral-wiederholungsmuster-bedruckter-knopf-cardigan-pullover | V225: ='Stellamea – Links'!H225 | W225: 2026-10-02
A226: 222 | C226: Week 1 | D226: A · Proven elsewhere, open in your market | E226: 77.7 | F226: Cappotto Lungo Invernale da Donna con Design Elegante, Materiale Ecosostenibile, Perfetto per la Stagione Invernale, Taglie S-3XL | G226: Transition jacket | H226: W | I226: top 21% bestseller at Vitelli Moda (IT, 121K visits/mo) · also at Lozenda Fashion (DE), Velareeh Haus (DE), Amara Fiore (IT, small), Boutique Élégance Bordeaux (FR, small) +3 · no competitor sells it in ES yet → open space · season fit 1.0 | J226: 59.95 | K226: 55–70 | L226: take over the source link price | N226: =IF(M226="","",(J226-M226)/J226) | O226: Open | P226: Vitelli Moda (121K) | Q226: IT | R226: 82 | S226: 6 photos, 1st 667×890 | T226: Main photo free to use (no competitor in your market) | U226: https://lozendafashion.com/products/kuscheliger-langer-mantel https://velareehhaus.com/products/beatrix-langer-eleganter-oversized-mantel-fw | V226: ='Stellamea – Links'!H226 | W226: 2026-10-02
A227: 223 | C227: Week 1 | D227: B · Broadly proven | E227: 77.6 | F227: LAURENT MONACO | VESTE URBAN VOYAGER POUR HOMME | G227: Transition jacket | H227: ? | I227: top 4% bestseller at Laurent Monaco (FR, 269K visits/mo) · also at Armand et Fils (FR), Harper & Wells Boston (US), Nordheim Mode (DE), Oliver & Blake (US) +5 · 1 competitor(s) in ES · added 5 days ago · season fit 0.8 | J227: 89.95 | K227: 55–70 | L227: take over the source link price; note: already a bestseller at 1 competitor(s) in your market | N227: =IF(M227="","",(J227-M227)/J227) | O227: Open | P227: Laurent Monaco (269K) | Q227: FR | R227: 78 | S227: 4 photos, 1st 900×1200 | T227: Same main photo as 1 competitor(s) in your market → use photo 2 (or a model photo) as main image | U227: https://nordheim-mode.de/products/bram-luxuriose-steppjacke https://velareehhaus.com/products/bianca-luxurioese-gesteppte-jacke-fw https://armandetfils.fr/products/veste-matelassee-zippee-a-poches-poitrine | V227: ='Stellamea – Links'!H227 | W227: 2026-10-02
A228: 224 | C228: Week 1 | D228: A · Proven elsewhere, open in your market | E228: 77.6 | F228: Wilhelm - Elegante Jacke für Herbst und Winter | G228: Transition jacket | H228: ? | I228: top 19% bestseller at Falkenberg Mode (DE, 84K visits/mo) · also at Armand et Fils (FR), Look de Paris (FR), Amara Fiore (IT, small), Lune Mode (IT, small) +1 · no competitor sells it in ES yet → open space · season fit 1.0 | J228: 64.95 | K228: 55–70 | L228: take over the source link price | N228: =IF(M228="","",(J228-M228)/J228) | O228: Open | P228: Falkenberg Mode (84K) | Q228: DE | R228: 79 | S228: 6 photos, 1st 823×792 | T228: Main photo free to use (no competitor in your market) | U228: https://lookdeparis.com/products/paul https://armandetfils.fr/products/veste-homme-a-capuche-doublee | V228: ='Stellamea – Links'!H228 | W228: 2026-10-02
A229: 225 | C229: Week 1 | D229: A · Proven elsewhere, open in your market | E229: 77.3 | F229: Teresa | Stylish Soft Cat Pattern Cardigan | G229: Cardigan | H229: ? | I229: top 14% bestseller at Harper & Wells Boston (US, 1500K visits/mo) · also at Lumière Boutique (FR), Nordheim Mode (DE), Boutique Élégance Bordeaux (FR, small), Soof & Clay (IT, small) · no competitor sells it in ES yet → open space · season fit 1.0 | J229: 54.95 | K229: 45–45 | L229: source link price (59.95 USD) converted | N229: =IF(M229="","",(J229-M229)/J229) | O229: Open | P229: Harper & Wells Boston (1500K) | Q229: US | R229: 52 | S229: 1 photos, 1st 650×866 | T229: Main photo free to use (no competitor in your market) | U229: https://nordheim-mode.de/products/charlotte-damen-cardigan-mit-knopfen-und-langen-armeln https://lumiereboutique.fr/products/cardigan-femme-en-maille-a-motif-chat-boutonne | V229: ='Stellamea – Links'!H229 | W229: 2026-10-02
A230: 226 | C230: Week 1 | D230: A · Proven elsewhere, open in your market | E230: 77.3 | F230: Callahan | Shawl Collar Knit Cardigan | G230: Cardigan | H230: ? | I230: top 22% bestseller at Harper & Wells Boston (US, 1500K visits/mo) · also at Wilson & Carter (UK) · no competitor sells it in ES yet → open space · added 10 days ago · season fit 1.0 | J230: 91.95 | K230: 45–45 | L230: source link price (99.95 USD) converted | N230: =IF(M230="","",(J230-M230)/J230) | O230: Open | P230: Harper & Wells Boston (1500K) | Q230: US | R230: 68 | S230: 4 photos, 1st 800×800 | T230: Main photo free to use (no competitor in your market) | U230: https://wilson-and-carter.com/products/wyatt-cardigan | V230: ='Stellamea – Links'!H230 | W230: 2026-10-02
A231: 227 | C231: Week 1 | D231: B · Broadly proven | E231: 77.1 | F231: Frieda | Damen Leichter V-Ausschnitt Geknöpfter Oversized Cardigan | G231: Cardigan | H231: ? | I231: top 48% bestseller at Leon Boutique (DE, 243K visits/mo) · also at Boutique Paris (FR), Look de Paris (FR), Velareeh Haus (DE) · no competitor sells it in ES yet → open space · season fit 1.0 | J231: 35.95 | K231: 45–45 | L231: take over the source link price; below the category sweet spot, can go higher: 44.95 | N231: =IF(M231="","",(J231-M231)/J231) | O231: Open | P231: Leon Boutique (243K) | Q231: DE | R231: 87 | S231: 6 photos, 1st 800×1200 | T231: Main photo free to use (no competitor in your market) | U231: https://velareehhaus.com/products/anne-warme-zeitlose-strickjacke-fw https://lookdeparis.com/products/priya-gilet-elegant-oversize-col-v https://boutique-paris.fr/products/camille-gilet-elegant-oversize-col-v | V231: ='Stellamea – Links'!H231 | W231: 2026-10-02
...

Sheet Stellamea – Links
A1: Stellamea: import links in list order – list 15-25 per day, then set Lister and Status
A3: # | B3: List week | C3: Product Name | D3: Link | E3: Advised price (EUR) | F3: Source | G3: Lister | H3: Status | I3: Comment | J3: Added on
A5: 1 | B5: Week 1 | D5: https://lumiereboutique.fr/products/marivelle | E5: 44.95 | F5: Lumière Boutique (275K) | G5: Davy | H5: Live | J5: 2026-10-02
A6: 2 | B6: Week 1 | D6: https://nordheim-mode.de/products/elly-hochkragen-weiches-stricktop | E6: 39.95 | F6: Nordheim Mode (546K) | G6: Davy | H6: Live | J6: 2026-10-02
A7: 3 | B7: Week 1 | D7: https://karlson-berlin.com/products/sevira | E7: 49.95 | F7: Karlson Berlin (981K) | G7: Davy | H7: Live | J7: 2026-10-02
A8: 4 | B8: Week 1 | D8: https://lookdeparis.com/products/victor-veste-cuir-elegante-moderne-homme | E8: 69.99 | F8: Look de Paris (236K) | G8: Davy | H8: Live | J8: 2026-10-02
A9: 5 | B9: Week 1 | D9: https://leonboutique.co/products/annika-damen-burojacke-figurbetonter-blazer | E9: 35.95 | F9: Leon Boutique (243K) | G9: Davy | H9: Live | J9: 2026-10-02
A10: 6 | B10: Week 1 | D10: https://leonboutique.co/products/annika-damen-eleganter-oversized-pullover | E10: 54.95 | F10: Leon Boutique (243K) | G10: Davy | H10: Live | J10: 2026-10-02
A11: 7 | B11: Week 1 | D11: https://nordheim-mode.de/products/clara-damen-oversized-bomberjacke | E11: 49.95 | F11: Nordheim Mode (546K) | G11: Davy | H11: Duplicate | I11: Already in store | J11: 2026-10-02
A12: 8 | B12: Week 1 | D12: https://nordheim-mode.de/products/isabella-cashmere-rollkragenpullover | E12: 49.95 | F12: Nordheim Mode (546K) | G12: Davy | H12: Live | J12: 2026-10-02
A13: 9 | B13: Week 1 | D13: https://lozendafashion.com/products/eleganter-komfort-pullover | E13: 32.95 | F13: Lozenda Fashion (192K) | G13: Davy | H13: Live | J13: 2026-10-02
A14: 10 | B14: Week 1 | D14: https://wentworthlondon.com/products/long-sleeve-polo-for-men | E14: 28.95 | F14: Wentworth London (87K) | G14: Davy | H14: Live | J14: 2026-10-02
A15: 11 | B15: Week 1 | D15: https://leonboutique.co/products/maximilian-herren-vintage-biker-quilted-jacket-echtleder-reiverschluss | E15: 91.95 | F15: Leon Boutique (243K) | G15: Davy | H15: Live | J15: 2026-10-02
A16: 12 | B16: Week 1 | D16: https://lookdeparis.com/products/juliette-ensemble-blazer-elegant-femme | E16: 59.99 | F16: Look de Paris (236K) | G16: Davy | H16: Duplicate | I16: Already in store | J16: 2026-10-02
A17: 13 | B17: Week 1 | D17: https://harperwells-boston.com/products/margaret-sweatshirt | E17: 45.95 | F17: Harper & Wells Boston (1500K) | G17: Davy | H17: Live | J17: 2026-10-02
A18: 14 | B18: Week 1 | D18: https://karlson-berlin.com/products/wilson | E18: 54.95 | F18: Karlson Berlin (981K) | G18: Davy | H18: Live | J18: 2026-10-02
A19: 15 | B19: Week 1 | D19: https://nordheim-mode.de/products/jade-strickpullover | E19: 39.95 | F19: Nordheim Mode (546K) | G19: Davy | H19: Live | J19: 2026-10-02
A20: 16 | B20: Week 1 | D20: https://nordheim-mode.de/products/leopardenmuster-denim-patchwork-pullover | E20: 54.95 | F20: Nordheim Mode (546K) | G20: Davy | H20: Live | J20: 2026-10-02
A21: 17 | B21: Week 1 | D21: https://leonboutique.co/products/karl-lassiger-herren-hoodie-mit-reissverschluss | E21: 49.95 | F21: Leon Boutique (243K) | G21: Davy | H21: Duplicate | I21: Already in store | J21: 2026-10-02
A22: 18 | B22: Week 1 | D22: https://vitellimoda.com/products/donna-inverno-cardigan-solido-bottoni-maniche-lunghe | E22: 54.95 | F22: Vitelli Moda (121K) | G22: Davy | H22: Live | J22: 2026-10-02
A23: 19 | B23: Week 1 | D23: https://nordheim-mode.de/products/gabriele-jacke | E23: 49.95 | F23: Nordheim Mode (546K) | G23: Davy | H23: Live | J23: 2026-10-02
A24: 20 | B24: Week 1 | D24: https://lozendafashion.com/products/cordjacke-damen-gemutlich-wandelbar | E24: 57.95 | F24: Lozenda Fashion (192K) | G24: Davy | H24: Live | J24: 2026-10-02
A25: 21 | B25: Week 1 | D25: https://karlson-berlin.com/products/harron | E25: 49.95 | F25: Karlson Berlin (981K) | G25: Davy | H25: Live | J25: 2026-10-02
A26: 22 | B26: Week 1 | D26: https://lookdeparis.com/products/chanel-manteau-de-pluie-femme-long | E26: 59.99 | F26: Look de Paris (236K) | G26: Davy | H26: Live | J26: 2026-10-02
A27: 23 | B27: Week 1 | D27: https://falkenberg-mode.de/products/fabiola | E27: 49.95 | F27: Falkenberg Mode (84K) | G27: Davy | H27: Live | J27: 2026-10-02
A28: 24 | B28: Week 1 | D28: https://nordheim-mode.de/products/giuseppina-regenmantel | E28: 49.95 | F28: Nordheim Mode (546K) | G28: Davy | H28: Live | J28: 2026-10-02
A29: 25 | B29: Week 1 | D29: https://lookdeparis.com/products/louise-cardigan-elegant-automne-femme | E29: 59.99 | F29: Look de Paris (236K) | G29: Davy | H29: Live | J29: 2026-10-02
A30: 26 | B30: Week 1 | C30: Jersey de punto para mujer con canesú de estilo nórdico para el otoño | D30: https://leonboutique.co/products/dorothea-damen-strickpullover-mit-rundhalsausschnitt-fur-den-alltag | E30: 44.95 | F30: Leon Boutique (243K) | G30: Fatima | H30: Live | J30: 2026-10-02
A31: 27 | B31: Week 1 | C31: Jersey de punto para mujer con bloques de color y detalle de leopardo | D31: https://leonboutique.co/products/viola-damen-weicher-strickpullover-mit-farbblock-und-leopardenmuster | E31: 52.95 | F31: Leon Boutique (243K) | G31: Fatima | H31: Live | J31: 2026-10-02
A32: 28 | B32: Week 1 | C32: Jersey de punto acanalado para hombre con media cremallera para el otoño | D32: https://laurentmonaco.fr/products/laurent-monaco-pull-tendance-avec-zip-moyen-homme | E32: 44.95 | F32: Laurent Monaco (269K) | G32: Fatima | H32: Live | J32: 2026-10-02
A33: 29 | B33: Week 1 | C33: Chaqueta de punto para hombre con cremallera y dibujo de rombos para el invierno | D33: https://risora-shop.de/products/klassikcardigan-strickjacke-stilvoll-und-bequem | E33: 59.95 | F33: Risora (121K) | G33: Fatima | H33: Live | J33: 2026-10-02
A34: 30 | B34: Week 1 | C34: Blazer para mujer de efecto terciopelo con botones dorados para ocasiones elegantes | D34: https://leonboutique.co/products/sabina-damen-klassischer-blazer-mit-ein-knopf-verschluss | E34: 74.95 | F34: Leon Boutique (243K) | G34: Fatima | H34: Live | J34: 2026-10-02
A35: 31 | B35: Week 1 | C35: Polo de manga larga para hombre con tapeta de tres botones para el otoño | D35: https://karlson-berlin.com/products/orion | E35: 59.95 | F35: Karlson Berlin (981K) | G35: Fatima | H35: Live | J35: 2026-10-02
A36: 32 | B36: Week 1 | C36: Blazer abierto para mujer con mangas fruncidas para el día a día | D36: https://leonboutique.co/products/edith-damen-stilvoller-massgeschneiderter-blazer-fur-freizeitlook | E36: 45.95 | F36: Leon Boutique (243K) | G36: Fatima | H36: Live | J36: 2026-10-02
A37: 33 | B37: Week 1 | C37: Blazer para hombre de efecto ante con cuello mao para el otoño | D37: https://vitellimoda.com/products/blazer-uomo-con-bottoni-a-taglio-strutturato-in-tessuto-premium-ideale-per-lautunno | E37: 67.95 | F37: Vitelli Moda (121K) | G37: Fatima | H37: Live | J37: 2026-10-02
A38: 34 | B38: Week 1 | C38: Jersey para mujer con estampado geométrico 3D para el día a día | D38: https://nordheim-mode.de/products/sanae-trendy-alltags-pullover | E38: 39.95 | F38: Nordheim Mode (546K) | G38: Fatima | H38: Live | J38: 2026-10-02
A39: 35 | B39: Week 1 | C39: Jersey de punto fino para mujer con mangas murciélago para el entretiempo | D39: https://nordheim-mode.de/products/sara-komfortpullover | E39: 34.95 | F39: Nordheim Mode (546K) | G39: Fatima | H39: Live | J39: 2026-10-02
A40: 36 | B40: Week 1 | D40: https://leonboutique.co/products/charlotte-damen-oversized-fledermausarm-strick-sweater | E40: 36.95 | F40: Leon Boutique (243K) | G40: Fatima | H40: Duplicate | I40: Already in store | J40: 2026-10-02
A41: 37 | B41: Week 1 | C41: Jersey de punto para mujer con cuello alto y cordón para el otoño | D41: https://vitellimoda.com/products/maglione-con-collo-alto-in-lana-merino-traspirante-e-termico-versatile-per-occasioni-casual-e-formali | E41: 49.95 | F41: Vitelli Moda (121K) | G41: Fatima | H41: Live | J41: 2026-10-02
A42: 38 | B42: Week 1 | C42: Chaqueta ligera para hombre con forro de cuadros y cremallera para el entretiempo | D42: https://laurentmonaco.fr/products/veste-legere-doublee-a-carreaux-pour-homme | E42: 49.95 | F42: Laurent Monaco (269K) | G42: Fatima | H42: Live | J42: 2026-10-02
A43: 39 | B43: Week 1 | C43: Jersey de punto trenzado para hombre con media cremallera para el invierno | D43: https://velareehhaus.com/products/andreas-herren-zopfstrick-pullover-mit-reissverschluss-fw | E43: 54.95 | F43: Velareeh Haus (95K) | G43: Fatima | H43: Live | J43: 2026-10-02
A44: 40 | B44: Week 1 | C44: Jersey de punto grueso para mujer con cuello alto para el invierno | D44: https://falkenberg-mode.de/products/luna | E44: 54.95 | F44: Falkenberg Mode (84K) | G44: Fatima | H44: Live | J44: 2026-10-02
A45: 41 | B45: Week 1 | D45: https://karlson-berlin.com/products/euna | E45: 59.95 | F45: Karlson Berlin (981K) | G45: Fatima | H45: Issues | J45: 2026-10-02
A46: 42 | B46: Week 1 | C46: Chaqueta acolchada entallada para mujer con cuello alto para el entretiempo | D46: https://karlson-berlin.com/products/frieda | E46: 69.95 | F46: Karlson Berlin (981K) | G46: Fatima | H46: Live | J46: 2026-10-02
A47: 43 | B47: Week 1 | C47: Sudadera oversize para mujer con aberturas laterales para el día a día | D47: https://oliverandblake.com/products/luna-oversized-sweatshirt | E47: 40.95 | F47: Oliver & Blake (98K) | G47: Fatima | H47: Live | J47: 2026-10-02
A48: 44 | B48: Week 1 | C48: Chaqueta acolchada para mujer con cuello alto y bolsillos para el otoño | D48: https://nordheim-mode.de/products/sloane-gestepptes-jackett | E48: 54.95 | F48: Nordheim Mode (546K) | G48: Fatima | H48: Live | J48: 2026-10-02
A49: 45 | B49: Week 1 | D49: https://leonboutique.co/products/claudia-damen-alltagstauglicher-winter-strickpullover | E49: 49.95 | F49: Leon Boutique (243K) | G49: Fatima | H49: Duplicate | I49: Already in store | J49: 2026-10-02
A50: 46 | B50: Week 1 | C50: Jersey holgado para mujer con cuello redondo para el otoño y el invierno | D50: https://leonboutique.co/products/isabella-damen-lassiger-locker-geschnittener-pullover | E50: 49.95 | F50: Leon Boutique (243K) | G50: Fatima | H50: Live | J50: 2026-10-02
A51: 47 | B51: Week 1 | C51: Blazer blanco para hombre con cuello mao y botones dorados para ocasiones especiales | D51: https://wilson-and-carter.com/products/alaric-blazer | E51: 57.95 | F51: Wilson & Carter (200K) | G51: Fatima | H51: Live | J51: 2026-10-02
A52: 48 | B52: Week 1 | C52: Jersey de punto para hombre con dibujo de rombos y cuello redondo para el invierno | D52: https://laurentmonaco.fr/products/laurent-monaco-pull-homme-a-carreaux | E52: 44.95 | F52: Laurent Monaco (269K) | G52: Fatima | H52: Live | J52: 2026-10-02
A53: 49 | B53: Week 1 | C53: Cárdigan de punto para mujer con cuello camisero y botones para el otoño | D53: https://harperwells-boston.com/products/adele-cardigan | E53: 54.95 | F53: Harper & Wells Boston (1500K) | G53: Fatima | H53: Live | J53: 2026-10-02
A54: 50 | B54: Week 1 | D54: https://lozendafashion.com/products/warmerpullover | E54: 39.95 | F54: Lozenda Fashion (192K) | G54: Fatima | H54: Issues | J54: 2026-10-02
A55: 51 | B55: Week 1 | C55: Conjunto de blazer y chaleco para hombre de efecto pana para ocasiones elegantes | D55: https://karlson-berlin.com/products/connor | E55: 119.95 | F55: Karlson Berlin (981K) | G55: Fatima | H55: Live | J55: 2026-10-02
A56: 52 | B56: Week 1 | C56: Cárdigan de punto con capucha para mujer con botones para el entretiempo | D56: https://leonboutique.co/products/clara-damen-kapuzen-cardigan-mit-knopfleiste-relaxed-fit-langarm | E56: 53.95 | F56: Leon Boutique (243K) | G56: Fatima | H56: Live | J56: 2026-10-02
A57: 53 | B57: Week 1 | C57: Chaqueta biker para hombre de efecto cuero con cuello alto para el otoño | D57: https://vitellimoda.com/products/giacca-in-pelle-premium-uomo-con-fodera-isolante-e-polsini-regolabili-i-ideale-per-autunno-inverno | E57: 74.95 | F57: Vitelli Moda (121K) | G57: Fatima | H57: Live | J57: 2026-10-02
A58: 54 | B58: Week 1 | C58: Jersey de punto para mujer con cuello de pico para el otoño y el invierno | D58: https://boutique-paris.fr/products/chloe-pull-doux-femme | E58: 44.99 | F58: Boutique Paris (166K) | G58: Fatima | H58: Live | J58: 2026-10-02
A59: 55 | B59: Week 1 | C59: Jersey de cuello alto para mujer con textura de rombos para el otoño y el invierno | D59: https://nordheim-mode.de/products/charlotte-schicker-high-neck-pullover | E59: 39.95 | F59: Nordheim Mode (546K) | G59: Dhafnie | H59: Live | J59: 2026-10-02
A60: 56 | B60: Week 1 | C60: Blusa de manga larga para mujer con escote en V y detalles de encaje para el entretiempo | D60: https://leonboutique.co/products/isabella-damen-v-ausschnitt-langarm-bluse-mit-floralen-details | E60: 36.95 | F60: Leon Boutique (243K) | G60: Dhafnie | H60: Live | J60: 2026-10-02
A61: 57 | B61: Week 1 | C61: Jersey de cuello alto para mujer con estampado de arcoíris para el otoño | D61: https://nordheim-mode.de/products/ada-1 | E61: 39.95 | F61: Nordheim Mode (546K) | G61: Dhafnie | H61: Live | J61: 2026-10-02
A62: 58 | B62: Week 1 | C62: Chaqueta de efecto cuero para mujer con capucha desmontable y corte entallado para el entretiempo | D62: https://lozendafashion.com/products/jacke-damen-abnehmbare-kapuze-taillierte-passform | E62: 78.95 | F62: Lozenda Fashion (192K) | G62: Dhafnie | H62: Live | J62: 2026-10-02
A63: 59 | B63: Week 1 | C63: Jersey para mujer con estampado geométrico en tonos pastel y botones para el día a día | D63: https://nordheim-mode.de/products/vera-pullover-mit-abstraktem-geometrischem-muster | E63: 44.95 | F63: Nordheim Mode (546K) | G63: Dhafnie | H63: Live | J63: 2026-10-02
A64: 60 | B64: Week 1 | C64: Jersey de punto liso para hombre con media cremallera para la oficina y el otoño | D64: https://oliverandblake.com/products/torino-half-zip-sweater | E64: 50.95 | F64: Oliver & Blake (98K) | G64: Dhafnie | H64: Live | J64: 2026-10-02
A65: 61 | B65: Week 1 | C65: Abrigo para mujer con cuello mao y bolsillos laterales para el entretiempo | D65: https://nordheim-mode.de/products/sonia-zeitlose-elegante-jacke | E65: 69.95 | F65: Nordheim Mode (546K) | G65: Dhafnie | H65: Live | J65: 2026-10-02
A66: 62 | B66: Week 1 | C66: Sudadera con capucha para hombre en dos tonos con cordón para el tiempo libre | D66: https://leonboutique.co/products/jens-herren-zwei-ton-freizeit-pullover-hoodie | E66: 54.95 | F66: Leon Boutique (243K) | G66: Dhafnie | H66: Live | J66: 2026-10-02
... A76: 72 | B76: Week 1 | C76: Chaqueta corta de efecto tweed para mujer con botones y bolsillos para el entretiempo | D76: https://leonboutique.co/products/yvonne-damen-elegante-tweed-jacke-mit-knopfleiste | E76: 82.95 | F76: Leon Boutique (243K) | G76: Dhafnie | H76: Live | J76: 2026-10-02
A77: 73 | B77: Week 1 | D77: https://leonboutique.co/products/katharina-damen-strickjacke-mit-klassischer-knopfleiste | E77: 48.75 | F77: Leon Boutique (243K) | G77: Dhafnie | H77: Duplicate | I77: Already in store | J77: 2026-10-02
A78: 74 | B78: Week 1 | D78: https://lookdeparis.com/products/elina-pull-automne-vintage-femme | E78: 44.99 | F78: Look de Paris (236K) | G78: Dhafnie | H78: Duplicate | I78: Already in store | J78: 2026-10-02
A79: 75 | B79: Week 1 | C79: Polo de manga larga para hombre con bolsillo en el pecho para el día a día | D79: https://karlson-berlin.com/products/daniel | E79: 49.95 | F79: Karlson Berlin (981K) | G79: Dhafnie | H79: Live | J79: 2026-10-02
A80: 76 | B80: Week 1 | C80: Polo de manga larga para hombre con mangas raglán y tapeta de botones para el otoño | D80: https://harperwells-boston.com/products/travis-owen | E80: 54.95 | F80: Harper & Wells Boston (1500K) | G80: Dhafnie | H80: Live | J80: 2026-10-02
A81: 77 | B81: Week 1 | C81: Sudadera con capucha oversize para hombre con estampado de letras para el día a día | D81: https://parisane.fr/products/sweat-a-capuche-homme-a-poche-kangourou-coupe-oversize | E81: 36.99 | F81: Parisane (77K) | G81: Dhafnie | H81: Live | J81: 2026-10-02
A82: 78 | B82: Week 1 | D82: https://laurentmonaco.fr/products/laurent-monaco-pull-automnal-homme | E82: 39.95 | F82: Laurent Monaco (269K) | G82: Dhafnie | H82: Issues | I82: Skipped – brand name in title | J82: 2026-10-02
A83: 79 | B83: Week 1 | C83: Chaqueta de punto calado para mujer con cremallera para el entretiempo | D83: https://nordheim-mode.de/products/desiree-luxurioser-strickcardigan | E83: 54.95 | F83: Nordheim Mode (546K) | G83: Dhafnie | H83: Live | J83: 2026-10-02
A84: 80 | B84: Week 1 | C84: Jersey de punto texturizado para hombre con cuello chal y botón para el invierno | D84: https://lookdeparis.com/products/pierre-homme-pull-thermique-tricote | E84: 49.99 | F84: Look de Paris (236K) | G84: Dhafnie | H84: Live | J84: 2026-10-02
A85: 81 | B85: Week 1 | C85: Jersey de cuello alto para hombre con media cremallera y bajo acanalado para el entretiempo | D85: https://armandetfils.fr/products/pull-homme-col-montant-zippe | E85: 69.95 | F85: Armand et Fils (195K) | G85: Dhafnie | H85: Live | J85: 2026-10-02
A86: 82 | B86: Week 1 | C86: Chaqueta de efecto cuero para mujer con cinturón y solapas para el entretiempo | D86: https://oliverandblake.com/products/victoria-sheepskin-jacket | E86: 119.95 | F86: Oliver & Blake (98K) | G86: Dhafnie | H86: Live | J86: 2026-10-02
A87: 83 | B87: Week 1 | D87: https://karlson-berlin.com/products/iriana | E87: 49.95 | F87: Karlson Berlin (981K) | G87: Dhafnie | H87: Duplicate | I87: Already in store | J87: 2026-10-02
A88: 84 | B88: Week 1 | C88: Chaqueta bomber para mujer con cremallera y puños elásticos para el entretiempo | D88: https://leonboutique.co/products/annika-damen-klassische-bomberjacke-mit-reissverschluss-vorne | E88: 51.95 | F88: Leon Boutique (243K) | G88: Dhafnie | H88: Live | J88: 2026-10-02
A89: 85 | B89: Week 1 | C89: Jersey clásico para hombre con media cremallera y puños acanalados para la oficina | D89: https://boutique-paris.fr/products/pierre-pull-zippe-cachemire-homme | E89: 39.99 | F89: Boutique Paris (166K) | G89: Dhafnie | H89: Live | J89: 2026-10-02
A90: 86 | B90: Week 1 | C90: Jersey para mujer con estampado de flores silvestres para el otoño | D90: https://nordheim-mode.de/products/jade-pullover-coat-mit-art-floral | E90: 39.95 | F90: Nordheim Mode (546K) | G90: Dhafnie | H90: Live | J90: 2026-10-02
A91: 87 | B91: Week 1 | C91: Abrigo largo para mujer de efecto ante con botones para el otoño | D91: https://nordheim-mode.de/products/teresa-klassischer-wildleder-trenchcoat-mit-vintage-flair | E91: 69.95 | F91: Nordheim Mode (546K) | G91: Dhafnie | H91: Live | J91: 2026-10-02
A92: 88 | B92: Week 1 | C92: Polo de punto para hombre de manga larga con cuello abierto para el otoño | D92: https://lozendafashion.com/products/polo-pullover-herren-bequeme-passform-knitterfrei | E92: 42.95 | F92: Lozenda Fashion (192K) | G92: Dhafnie | H92: Live | J92: 2026-10-02
A93: 89 | B93: Week 1 | D93: https://nordheim-mode.de/products/angelo-kapuzenpullover | E93: 39.95 | F93: Nordheim Mode (546K) | G93: Dhafnie | H93: Duplicate | I93: Already in store | J93: 2026-10-02
A94: 90 | B94: Week 1 | C94: Cárdigan para mujer con botones grandes y bajo ondulado para el otoño | D94: https://nordheim-mode.de/products/damen-oversized-cardigan-mit-grossen-metallischen-knopfen-und-laternenarmeln | E94: 54.95 | F94: Nordheim Mode (546K) | G94: Dhafnie | H94: Live | J94: 2026-10-02
A95: 91 | B95: Week 1 | C95: Poncho de punto para mujer con cuello alto y botones laterales para el otoño | D95: https://lozendafashion.com/products/rollkragen-poncho-damen-windschutz-bewegungsfreiheit | E95: 40.95 | F95: Lozenda Fashion (192K) | G95: Dhafnie | H95: Live | J95: 2026-10-02
A96: 92 | B96: Week 1 | C96: Jersey de punto texturizado para hombre con cuello alto y cremallera corta para el invierno | D96: https://boutique-paris.fr/products/lucas-pull-tricote-coton-homme | E96: 39.99 | F96: Boutique Paris (166K) | G96: Dhafnie | H96: Live | J96: 2026-10-02
A97: 93 | B97: Week 1 | C97: Cárdigan de punto para hombre con escote en V y botones para la oficina | D97: https://lozendafashion.com/products/strickjacke-herren-elegant-alltagstauglich | E97: 42.95 | F97: Lozenda Fashion (192K) | G97: Dhafnie | H97: Live | J97: 2026-10-02
A98: 94 | B98: Week 1 | C98: Chaqueta para hombre con cuello de efecto borreguito y bolsillos para el invierno | D98: https://vitellimoda.com/products/julian-giubbotto-bomber-premium-da-uomo | E98: 79.95 | F98: Vitelli Moda (121K) | G98: Dhafnie | H98: Live | J98: 2026-10-02
A99: 95 | B99: Week 1 | C99: Chaqueta de punto para mujer con cuello polo y botones para el invierno | D99: https://parisane.fr/products/emilie-cardigan-d-hiver-elegant-en-maille-avec-col-femme | E99: 49.99 | F99: Parisane (77K) | G99: Dhafnie | H99: Live | J99: 2026-10-02
A100: 96 | B100: Week 1 | C100: Chaqueta de punto con capucha y cordón para mujer con botones para el otoño | D100: https://harperwells-boston.com/products/freya-cardigan | E100: 77.95 | F100: Harper & Wells Boston (1500K) | G100: Dhafnie | H100: Live | J100: 2026-10-02
A101: 97 | B101: Week 1 | C101: Cárdigan largo con capucha para mujer con estampado artístico para el otoño | D101: https://nordheim-mode.de/products/cassidy-gemutlicher-kunstlerischer-langer-cardigan | E101: 49.95 | F101: Nordheim Mode (546K) | G101: Dhafnie | H101: Live | J101: 2026-10-02
A102: 98 | B102: Week 1 | C102: Jersey de punto liso para mujer con cuello alto bajo y corte recto para el día a día | D102: https://nordheim-mode.de/products/donna-klassischer-rollkragenpullover | E102: 54.95 | F102: Nordheim Mode (546K) | G102: Dhafnie | H102: Live | J102: 2026-10-02
A103: 99 | B103: Week 1 | C103: Jersey de punto para hombre con cuello abotonado y detalles en contraste para el otoño | D103: https://leonboutique.co/products/thomas-herren-lassiger-gerippter-pullover-mit-knopfleiste-am-kragen | E103: 44.95 | F103: Leon Boutique (243K) | G103: Dhafnie | H103: Live | J103: 2026-10-02
A104: 100 | B104: Week 1 | C104: Blusa de manga corta para mujer con escote en V para el verano | D104: https://lozendafashion.com/products/modische-weisse-bluse-fur-damen | E104: 34.95 | F104: Lozenda Fashion (192K) | G104: Dhafnie | H104: Live | J104: 2026-10-02
A105: 101 | B105: Week 1 | C105: Cárdigan de punto para mujer con estampado floral y botones para el entretiempo | D105: https://lozendafashion.com/products/strick-cardigan-damen-blumenmuster-knopfleiste | E105: 44.95 | F105: Lozenda Fashion (192K) | G105: Dhafnie | H105: Live | J105: 2026-10-02
... A108: 104 | B108: Week 1 | C108: Polo de punto para hombre de manga larga con botones para la oficina | D108: https://nordheim-mode.de/products/tobias-kaschmir-pullover | E108: 59.95 | F108: Nordheim Mode (546K) | G108: Dhafnie | H108: Live | J108: 2026-10-02
A109: 105 | B109: Week 1 | D109: https://laurentmonaco.fr/products/laurent-monaco-veste-en-cuir | E109: 54.95 | F109: Laurent Monaco (269K) | G109: Dhafnie | H109: Duplicate | I109: Already in store | J109: 2026-10-02
A110: 106 | B110: Week 1 | C110: Chaqueta de punto fino para hombre con cremallera y cuello alto para la oficina | D110: https://lumiereboutique.fr/products/cardigan-homme-zippe-elegant-en-maille-fine | E110: 44.95 | F110: Lumière Boutique (275K) | G110: Dhafnie | H110: Live | J110: 2026-10-02
A111: 107 | B111: Week 1 | C111: Chaleco de punto para hombre con cuello en V y ribetes en contraste para el otoño | D111: https://armandetfils.fr/products/pull-sans-manches-homme-col-v | E111: 57.95 | F111: Armand et Fils (195K) | G111: Dhafnie | H111: Live | J111: 2026-10-02
A112: 108 | B112: Week 1 | C112: Sudadera con capucha para hombre de corte holgado con bolsillo canguro para el otoño | D112: https://lozendafashion.com/products/hoodie-herren-mit-kapuze-tasche | E112: 47.95 | F112: Lozenda Fashion (192K) | G112: Dhafnie | H112: Live | J112: 2026-10-02
A113: 109 | B113: Week 1 | D113: https://nordheim-mode.de/products/silvia-retro-pullover-5 | E113: 42.95 | F113: Nordheim Mode (546K) | G113: Dhafnie | H113: Duplicate | I113: Already in store | J113: 2026-10-02
...

Sheet Davento
A1: Davento – 669 products to list (Italy/Germany, EUR)
A2: Sorted by list order · sources only big competitors (≥75K visits/month, verified) · status is set on the Links tab
A4: # | B4: Photo | C4: List week | D4: Strategy | E4: Score | F4: Product (source title) | G4: Category | H4: W/M | I4: Why this product | J4: Advised price (EUR) | K4: Category sweet spot (EUR) | L4: Price note | M4: Cost price – fill in (EUR) | N4: Margin % | O4: Source (import link) | P4: Source | Q4: Source country | R4: Photo score | S4: Photos | T4: Photo advice | U4: Other (big) sources | V4: Status (from Links) | W4: Added on
A5: 1 | C5: Week 1 | D5: B · Broadly proven | E5: 92.9 | F5: Damen Langarm-Strickjacke mit Knöpfen | G5: Cardigan | H5: W | I5: top 12% bestseller at Nordheim Mode (DE, 546K visits/mo) · also at Lumière Boutique (FR), Boutique Élégance Bordeaux (FR, small), Serenti Moda (ES, small) · 1 competitor(s) in IT/DE · added 20 days ago · season fit 1.0 | J5: 54.95 | K5: 45–60 | L5: take over the source link price; note: already a bestseller at 1 competitor(s) in your market | N5: =IF(M5="","",(J5-M5)/J5) | O5: Open | P5: Nordheim Mode (546K) | Q5: DE ⚠ own market | R5: 90 | S5: 11 photos, 1st 900×1200 | T5: Same main photo as 1 competitor(s) in your market → use photo 2 (or a model photo) as main image | U5: https://lumiereboutique.fr/products/cardigan-femme-oversize-a-col-boutonne-en-maille-cotelee | V5: ='Davento – Links'!H5 | W5: 2026-10-02
A6: 2 | C6: Week 1 | D6: B · Broadly proven | E6: 92.8 | F6: Manteau femme à carreaux colorés coupe ample | G6: Transition jacket | H6: W | I6: top 37% bestseller at Lumière Boutique (FR, 275K visits/mo) · also at Harper & Wells Boston (US), Nordheim Mode (DE), Wilson & Carter (UK), Boutique Élégance Bordeaux (FR, small) · 1 competitor(s) in IT/DE · added 6 days ago · season fit 1.0 | J6: 54.95 | K6: 50–70 | L6: take over the source link price | N6: =IF(M6="","",(J6-M6)/J6) | O6: Open | P6: Lumière Boutique (275K) | Q6: FR | R6: 94 | S6: 5 photos, 1st 1656×2208 | T6: Same main photo as 1 competitor(s) in your market → use photo 2 (or a model photo) as main image | U6: https://nordheim-mode.de/products/damen-multicolor-karottenmantel-mit-gemutlicher-fleece-textur-und-taschen https://wilson-and-carter.com/products/marjorie-jacket https://harperwells-boston.com/products/penelope-jacket | V6: ='Davento – Links'!H6 | W6: 2026-10-02
A7: 3 | C7: Week 1 | D7: B · Broadly proven | E7: 90.7 | F7: Adele | Refined Collared Cardigan | G7: Cardigan | H7: ? | I7: top 16% bestseller at Harper & Wells Boston (US, 1500K visits/mo) · also at Lozenda Fashion (DE), Parisane (FR), Wilson & Carter (UK) · 1 competitor(s) in IT/DE · added 5 days ago · season fit 1.0 | J7: 54.95 | K7: 45–60 | L7: source link price (59.95 USD) converted | N7: =IF(M7="","",(J7-M7)/J7) | O7: Open | P7: Harper & Wells Boston (1500K) | Q7: US | R7: 70 | S7: 5 photos, 1st 700×700 | T7: Same main photo as 1 competitor(s) in your market → use photo 2 (or a model photo) as main image | U7: https://lozendafashion.com/products/strickjacke-damen-weich-vielseitig https://parisane.fr/products/gilet-en-maille-femme-a-col-boutonne https://wilson-and-carter.com/products/constance-cardigan | V7: ='Davento – Links'!H7 | W7: 2026-10-02
A8: 4 | C8: Week 1 | D8: A · Proven elsewhere, open in your market | E8: 89.5 | F8: Veste Légère Doublée À Carreaux Pour Homme | G8: Transition jacket | H8: M | I8: top 7% bestseller at Laurent Monaco (FR, 269K visits/mo) · also at Boutique Paris (FR), Look de Paris (FR), Dolce Paris (FR, small) · no competitor sells it in IT/DE yet → open space · added 15 days ago · season fit 1.0 | J8: 49.95 | K8: 50–70 | L8: take over the source link price | N8: =IF(M8="","",(J8-M8)/J8) | O8: Open | P8: Laurent Monaco (269K) | Q8: FR | R8: 84 | S8: 5 photos, 1st 900×1200 | T8: Main photo free to use (no competitor in your market) | U8: https://lookdeparis.com/products/marc-veste-elegante-polaire-zippee https://boutique-paris.fr/products/vincent-veste-elegante-polaire-col-montant | V8: ='Davento – Links'!H8 | W8: 2026-10-02
A9: 5 | C9: Week 1 | D9: B · Broadly proven | E9: 89.5 | F9: Sonia™ - Zeitlose Elegante Jacke | G9: Transition jacket | H9: ? | I9: top 11% bestseller at Nordheim Mode (DE, 546K visits/mo) · also at Boutique Paris (FR), Look de Paris (FR) · 1 competitor(s) in IT/DE · added 8 days ago · season fit 1.0 | J9: 69.95 | K9: 50–70 | L9: take over the source link price; note: already a bestseller at 1 competitor(s) in your market | N9: =IF(M9="","",(J9-M9)/J9) | O9: Open | P9: Nordheim Mode (546K) | Q9: DE ⚠ own market | R9: 87 | S9: 12 photos, 1st 800×1066 | T9: Same main photo as 1 competitor(s) in your market → use photo 2 (or a model photo) as main image | U9: https://lookdeparis.com/products/valerie-veste-elegante-boutonnee-col-montant https://boutique-paris.fr/products/manon-veste-elegante-col-montant-boutonnee | V9: ='Davento – Links'!H9 | W9: 2026-10-02
A10: 6 | C10: Week 1 | D10: A · Proven elsewhere, open in your market | E10: 88 | F10: Freya | Hooded Button-Down Cardigan | G10: Cardigan | H10: ? | I10: top 24% bestseller at Harper & Wells Boston (US, 1500K visits/mo) · also at Boutique Paris (FR), Lumière Boutique (FR), Wilson & Carter (UK), Boutique Élégance Bordeaux (FR, small) · no competitor sells it in IT/DE yet → open space · added 11 days ago · season fit 1.0 | J10: 77.95 | K10: 45–60 | L10: source link price (84.95 USD) converted | N10: =IF(M10="","",(J10-M10)/J10) | O10: Open | P10: Harper & Wells Boston (1500K) | Q10: US | R10: 74 | S10: 5 photos, 1st 800×800 | T10: Main photo free to use (no competitor in your market) | U10: https://lumiereboutique.fr/products/cardigan-femme-a-capuche-boutonne-en-maille-douce https://boutique-paris.fr/products/camille-gilet-elegant-a-capuche-boutonne https://wilson-and-carter.com/products/estella-cardigan | V10: ='Davento – Links'!H10 | W10: 2026-10-02
A11: 7 | C11: Week 1 | D11: B · Broadly proven | E11: 87.4 | F11: Rosalind | Timeless Turndown Collar Coat | G11: Transition jacket | H11: ? | I11: top 12% bestseller at Harper & Wells Boston (US, 1500K visits/mo) · also at Karlson Berlin (DE), Wilson & Carter (UK) · 1 competitor(s) in IT/DE · added 7 days ago · season fit 1.0 | J11: 91.95 | K11: 50–70 | L11: source link price (99.95 USD) converted | N11: =IF(M11="","",(J11-M11)/J11) | O11: Open | P11: Harper & Wells Boston (1500K) | Q11: US | R11: 74 | S11: 5 photos, 1st 800×800 | T11: Same main photo as 1 competitor(s) in your market → use photo 2 (or a model photo) as main image | U11: https://karlson-berlin.com/products/notburga-mantel-mit-umlegekragen-und-seitentaschen https://wilson-and-carter.com/products/marina-coat | V11: ='Davento – Links'!H11 | W11: 2026-10-02
A12: 8 | C12: Week 1 | D12: B · Broadly proven | E12: 86.8 | F12: LAURENT MONACO | HERREN STRICKTEXTUR WESTE | G12: Transition jacket | H12: M | I12: top 6% bestseller at Nordheim Mode (DE, 546K visits/mo) · also at Laurent Monaco (FR), Wentworth London (UK) · 1 competitor(s) in IT/DE · added 5 days ago · season fit 1.0 | J12: 59.95 | K12: 50–70 | L12: take over the source link price; note: already a bestseller at 1 competitor(s) in your market | N12: =IF(M12="","",(J12-M12)/J12) | O12: Open | P12: Nordheim Mode (546K) | Q12: DE ⚠ own market | R12: 78 | S12: 4 photos, 1st 900×1200 | T12: Same main photo as 1 competitor(s) in your market → use photo 2 (or a model photo) as main image | U12: https://laurentmonaco.fr/products/laurent-monaco-gilet-a-col-montant-en-maille-pour-hommes https://wentworthlondon.com/products/textured-knit-button-jacket-for-men | V12: ='Davento – Links'!H12 | W12: 2026-10-02
A13: 9 | C13: Week 1 | D13: B · Broadly proven | E13: 86.3 | F13: Fernando - Veste Denim Casual Homme | G13: Transition jacket | H13: M | I13: top 17% bestseller at Look de Paris (FR, 236K visits/mo) · also at Boutique Paris (FR), Lozenda Fashion (DE), Parisane (FR) · 1 competitor(s) in IT/DE · added 15 days ago · season fit 1.0 | J13: 44.99 | K13: 50–70 | L13: take over the source link price; below the category sweet spot, can go higher: 59.95; note: already a bestseller at 1 competitor(s) in your market | N13: =IF(M13="","",(J13-M13)/J13) | O13: Open | P13: Look de Paris (236K) | Q13: FR | R13: 80 | S13: 8 photos, 1st 800×800 | T13: Same main photo as 1 competitor(s) in your market → use photo 2 (or a model photo) as main image | U13: https://lozendafashion.com/products/jacke-herren-zeitlos-lassig https://boutique-paris.fr/products/nicolas-veste-elegante-en-jean https://parisane.fr/products/gilet-homme-en-jean-decontracte | V13: ='Davento – Links'!H13 | W13: 2026-10-02
A14: 10 | C14: Week 1 | D14: B · Broadly proven | E14: 86.1 | F14: Veste femme brodée à volants et boutons décoratifs | G14: Transition jacket | H14: W | I14: top 22% bestseller at Lumière Boutique (FR, 275K visits/mo) · also at Nordheim Mode (DE), Parisane (FR), Boutique Élégance Bordeaux (FR, small), Donna's Dresses (US, small) +1 · 1 competitor(s) in IT/DE · added 15 days ago · season fit 1.0 | J14: 54.95 | K14: 50–70 | L14: take over the source link price | N14: =IF(M14="","",(J14-M14)/J14) | O14: Open | P14: Lumière Boutique (275K) | Q14: FR | R14: 72 | S14: 3 photos, 1st 900×1200 | T14: Same main photo as 1 competitor(s) in your market → use photo 2 (or a model photo) as main image | U14: https://nordheim-mode.de/products/damen-ruschjacke-mit-bohemian-paisley-druck-und-ruschensaum https://parisane.fr/products/veste-femme-brodee-a-fleurs-a-volants-et-col-chemise | V14: ='Davento – Links'!H14 | W14: 2026-10-02
A15: 11 | C15: Week 1 | D15: B · Broadly proven | E15: 86.1 | F15: Trenchcoat Damen | Wasserdicht mit Kapuze | G15: Transition jacket | H15: W | I15: top 40% bestseller at Lozenda Fashion (DE, 192K visits/mo) · also at Donna's Dresses (US, small), Margaret Robinson (US, small) · 1 competitor(s) in IT/DE · added 1 days ago · season fit 1.0 | J15: 62.95 | K15: 50–70 | L15: take over the source link price | N15: =IF(M15="","",(J15-M15)/J15) | O15: Open | P15: Lozenda Fashion (192K) | Q15: DE ⚠ own market | R15: 93 | S15: 9 photos, 1st 1200×1200 | T15: Same main photo as 1 competitor(s) in your market → use photo 2 (or a model photo) as main image | V15: ='Davento – Links'!H15 | W15: 2026-10-02
A16: 12 | C16: Week 1 | D16: B · Broadly proven | E16: 84.8 | F16: Elliot | Tailored Button-Front Knit Cardigan | G16: Cardigan | H16: ? | I16: top 2% bestseller at Harper & Wells Boston (US, 1500K visits/mo) · also at Wilson & Carter (UK), Lune Mode (IT, small), Paul's Wardrobe (US, small) · 1 competitor(s) in IT/DE · season fit 1.0 | J16: 63.95 | K16: 45–60 | L16: source link price (69.95 USD) converted | N16: =IF(M16="","",(J16-M16)/J16) | O16: Open | P16: Harper & Wells Boston (1500K) | Q16: US | R16: 96 | S16: 10 photos, 1st 1080×1350 | T16: Same main photo as 1 competitor(s) in your market → use photo 2 (or a model photo) as main image | U16: https://wilson-and-carter.com/products/lawrence-cardigan | V16: ='Davento – Links'!H16 | W16: 2026-10-02
A17: 13 | C17: Week 1 | D17: B · Broadly proven | E17: 84.6 | F17: Strickjacke Damen | Zopfmuster & Knopfleiste | G17: Cardigan | H17: W | I17: top 36% bestseller at Lozenda Fashion (DE, 192K visits/mo) · also at Harper & Wells Boston (US), Wilson & Carter (UK) · 1 competitor(s) in IT/DE · added 7 days ago · season fit 1.0 | J17: 72.95 | K17: 45–60 | L17: take over the source link price | N17: =IF(M17="","",(J17-M17)/J17) | O17: Open | P17: Lozenda Fashion (192K) | Q17: DE ⚠ own market | R17: 93 | S17: 10 photos, 1st 1350×1350 | T17: Same main photo as 1 competitor(s) in your market → use photo 2 (or a model photo) as main image | U17: https://wilson-and-carter.com/products/harlow-cardigan https://harperwells-boston.com/products/lucinda | V17: ='Davento – Links'!H17 | W17: 2026-10-02
A18: 14 | C18: Week 1 | D18: A · Proven elsewhere, open in your market | E18: 84.2 | F18: Bridget | Relaxed Open-Front Cardigan | G18: Cardigan | H18: ? | I18: top 24% bestseller at Harper & Wells Boston (US, 1500K visits/mo) · also at Look de Paris (FR), Wilson & Carter (UK) · no competitor sells it in IT/DE yet → open space · season fit 1.0 | J18: 63.95 | K18: 45–60 | L18: source link price (69.95 USD) converted | N18: =IF(M18="","",(J18-M18)/J18) | O18: Open | P18: Harper & Wells Boston (1500K) | Q18: US | R18: 100 | S18: 12 photos, 1st 1350×1800 | T18: Main photo free to use (no competitor in your market) | U18: https://lookdeparis.com/products/priya-gilet-elegant-oversize-maille https://wilson-and-carter.com/products/marceline | V18: ='Davento – Links'!H18 | W18: 2026-10-02
A19: 15 | C19: Week 1 | D19: A · Proven elsewhere, open in your market | E19: 84 | F19: Esme | Nordic Patterned Cardigan | G19: Cardigan | H19: ? | I19: top 11% bestseller at Harper & Wells Boston (US, 1500K visits/mo) · also at Boutique Paris (FR) · no competitor sells it in IT/DE yet → open space · season fit 1.0 | J19: 54.95 | K19: 45–60 | L19: source link price (59.95 USD) converted | N19: =IF(M19="","",(J19-M19)/J19) | O19: Open | P19: Harper & Wells Boston (1500K) | Q19: US | R19: 100 | S19: 12 photos, 1st 1350×1800 | T19: Main photo free to use (no competitor in your market) | U19: https://boutique-paris.fr/products/elodie-gilet-feminin-boheme-col-v | V19: ='Davento – Links'!H19 | W19: 2026-10-02
A20: 16 | C20: Week 1 | D20: B · Broadly proven | E20: 83.9 | F20: Veste Femme Effet Superposé Maille Et Denim Style Moderne | G20: Transition jacket | H20: ? | I20: top 13% bestseller at Lumière Boutique (FR, 275K visits/mo) · also at Harper & Wells Boston (US), Wilson & Carter (UK), Amara Fiore (IT, small), Boutique Élégance Bordeaux (FR, small) +2 · 1 competitor(s) in IT/DE · season fit 1.0 | J20: 64.95 | K20: 50–70 | L20: take over the source link price; note: already a bestseller at 1 competitor(s) in your market | N20: =IF(M20="","",(J20-M20)/J20) | O20: Open | P20: Lumière Boutique (275K) | Q20: FR | R20: 93 | S20: 6 photos, 1st 1512×1512 | T20: Same main photo as 1 competitor(s) in your market → use photo 2 (or a model photo) as main image | U20: https://wilson-and-carter.com/products/elaine-button-jacket https://harperwells-boston.com/products/bethany-button-jacket | V20: ='Davento – Links'!H20 | W20: 2026-10-02
A21: 17 | C21: Week 1 | D21: B · Broadly proven | E21: 83.7 | F21: Chanel - Manteau de pluie femme long | G21: Transition jacket | H21: W | I21: top 6% bestseller at Look de Paris (FR, 236K visits/mo) · also at Boutique Paris (FR), Karlson Berlin (DE), Leon Boutique (DE), Margaret Robinson (US, small) · 2 competitor(s) in IT/DE · added 7 days ago · season fit 1.0 | J21: 59.99 | K21: 50–70 | L21: take over the source link price | N21: =IF(M21="","",(J21-M21)/J21) | O21: Open | P21: Look de Paris (236K) | Q21: FR | R21: 87 | S21: 6 photos, 1st 800×1000 | T21: Same main photo as 2 competitor(s) in your market → use photo 2 (or a model photo) as main image | U21: https://karlson-berlin.com/products/telse-regenmantel-mit-reissverschluss-und-taillenraffung https://leonboutique.co/products/charlotte-damen-wasserabweisender-langer-kapuzen-trenchcoat-aus-polyester https://boutique-paris.fr/products/zoe-manteau-de-pluie-femme-long | V21: ='Davento – Links'!H21 | W21: 2026-10-02
A22: 18 | C22: Week 1 | D22: B · Broadly proven | E22: 83.5 | F22: Louise - Cardigan élégant automne femme | G22: Cardigan | H22: W | I22: top 15% bestseller at Look de Paris (FR, 236K visits/mo) · also at Boutique Paris (FR), Lozenda Fashion (DE), Mayfair & Finch (UK, small), Paul's Wardrobe (US, small) +1 · 2 competitor(s) in IT/DE · added 0 days ago · season fit 1.0 | J22: 59.99 | K22: 45–60 | L22: take over the source link price | N22: =IF(M22="","",(J22-M22)/J22) | O22: Open | P22: Look de Paris (236K) | Q22: FR | R22: 87 | S22: 6 photos, 1st 800×1000 | T22: Same main photo as 2 competitor(s) in your market → use photo 2 (or a model photo) as main image | U22: https://lozendafashion.com/products/strickjacke-damen-knopfverschluss-elegante-silhouette https://boutique-paris.fr/products/marie-cardigan-elegant-automne-femme | V22: ='Davento – Links'!H22 | W22: 2026-10-02
A23: 19 | C23: Week 1 | D23: A · Proven elsewhere, open in your market | E23: 83.1 | F23: Cardigan Homme Zippé Élégant en Maille Fine | G23: Cardigan | H23: M | I23: top 21% bestseller at Lumière Boutique (FR, 275K visits/mo) · also at Boutique Paris (FR), Look de Paris (FR) · no competitor sells it in IT/DE yet → open space · added 15 days ago · season fit 1.0 | J23: 44.95 | K23: 45–60 | L23: take over the source link price | N23: =IF(M23="","",(J23-M23)/J23) | O23: Open | P23: Lumière Boutique (275K) | Q23: FR | R23: 96 | S23: 10 photos, 1st 1080×1350 | T23: Main photo free to use (no competitor in your market) | U23: https://lookdeparis.com/products/nicolas-cardigan-elegant-zippe-col-montant https://boutique-paris.fr/products/nicolas-cardigan-elegant-zippe-col-montant | V23: ='Davento – Links'!H23 | W23: 2026-10-02
A24: 20 | C24: Week 1 | D24: B · Broadly proven | E24: 83.1 | F24: Arthur | Classic Herringbone Tweed Waistcoat | G24: Transition jacket | H24: ? | I24: top 5% bestseller at Wilson & Carter (UK, 200K visits/mo) · also at Velareeh Haus (DE), Paul's Wardrobe (US, small) · 1 competitor(s) in IT/DE · season fit 1.0 | J24: 40.95 | K24: 50–70 | L24: source link price (34.95 GBP) converted; below the category sweet spot, can go higher: 59.95 | N24: =IF(M24="","",(J24-M24)/J24) | O24: Open | P24: Wilson & Carter (200K) | Q24: UK | R24: 99 | S24: 12 photos, 1st 1166×1500 | T24: Same main photo as 1 competitor(s) in your market → use photo 2 (or a model photo) as main image | U24: https://velareehhaus.com/products/felina-stilvolle-vielseitige-weste-fw | V24: ='Davento – Links'!H24 | W24: 2026-10-02
A25: 21 | C25: Week 1 | D25: B · Broadly proven | E25: 82.3 | F25: Ensemble Femme 3 Pièces Lin Coton Top Imprimé Cardigan Pantalon Large | G25: Cardigan | H25: W | I25: top 1% bestseller at Lumière Boutique (FR, 275K visits/mo) · also at Boutique Élégance Bordeaux (FR, small), Mercer & Bloom (US, small), Soof & Clay (IT, small) · 1 competitor(s) in IT/DE · season fit 1.0 | J25: 59.95 | K25: 45–60 | L25: take over the source link price | N25: =IF(M25="","",(J25-M25)/J25) | O25: Open | P25: Lumière Boutique (275K) | Q25: FR | R25: 81 | S25: 5 photos, 1st 791×1054 | T25: Same main photo as 1 competitor(s) in your market → use photo 2 (or a model photo) as main image | V25: ='Davento – Links'!H25 | W25: 2026-10-02
A26: 22 | C26: Week 1 | D26: C · New & rising | E26: 82.2 | F26: Wollmantel Damen | Eleganter Umschlagkragen | G26: Transition jacket | H26: W | I26: top 16% bestseller at Lozenda Fashion (DE, 192K visits/mo) · also at Borowska Kraków (PL, small) · 1 competitor(s) in IT/DE · added 8 days ago · season fit 1.0 | J26: 63.95 | K26: 50–70 | L26: take over the source link price; note: already a bestseller at 1 competitor(s) in your market | N26: =IF(M26="","",(J26-M26)/J26) | O26: Open | P26: Lozenda Fashion (192K) | Q26: DE ⚠ own market | R26: 83 | S26: 5 photos, 1st 1080×1080 | T26: Same main photo as 1 competitor(s) in your market → use photo 2 (or a model photo) as main image | V26: ='Davento – Links'!H26 | W26: 2026-10-02
A27: 23 | C27: Week 1 | D27: A · Proven elsewhere, open in your market | E27: 82.2 | F27: CLASSIC COTTON JACKET FOR MEN | G27: Transition jacket | H27: M | I27: top 4% bestseller at Wentworth London (UK, 87K visits/mo) · also at Laurent Monaco (FR) · no competitor sells it in IT/DE yet → open space · added 13 days ago · season fit 1.0 | J27: 69.95 | K27: 50–70 | L27: source link price (59.95 GBP) converted | N27: =IF(M27="","",(J27-M27)/J27) | O27: Open | P27: Wentworth London (87K) | Q27: UK | R27: 90 | S27: 7 photos, 1st 900×1200 | T27: Main photo free to use (no competitor in your market) | U27: https://laurentmonaco.fr/products/laurent-monaco-veste-vintage-delavee-pour-hommes | V27: ='Davento – Links'!H27 | W27: 2026-10-02
A28: 24 | C28: Week 1 | D28: A · Proven elsewhere, open in your market | E28: 82.1 | F28: Iris | Relaxed Open-Front Cardigan | G28: Cardigan | H28: ? | I28: top 34% bestseller at Harper & Wells Boston (US, 1500K visits/mo) · also at Boutique Paris (FR), Look de Paris (FR), Wilson & Carter (UK) · no competitor sells it in IT/DE yet → open space · season fit 1.0 | J28: 73.95 | K28: 45–60 | L28: source link price (79.95 USD) converted | N28: =IF(M28="","",(J28-M28)/J28) | O28: Open | P28: Harper & Wells Boston (1500K) | Q28: US | R28: 74 | S28: 5 photos, 1st 800×800 | T28: Main photo free to use (no competitor in your market) | U28: https://lookdeparis.com/products/priya-gilet-elegant-oversize-a-poches https://boutique-paris.fr/products/isabelle-gilet-elegant-oversize-a-poches https://wilson-and-carter.com/products/juliet-cardigan | V28: ='Davento – Links'!H28 | W28: 2026-10-02
A29: 25 | C29: Week 1 | D29: B · Broadly proven | E29: 82 | F29: Lucia | Tailored Longline Coat | G29: Transition jacket | H29: ? | I29: top 37% bestseller at Harper & Wells Boston (US, 1500K visits/mo) · also at Karlson Berlin (DE), Wilson & Carter (UK) · 1 competitor(s) in IT/DE · added 7 days ago · season fit 1.0 | J29: 105.95 | K29: 50–70 | L29: source link price (114.95 USD) converted | N29: =IF(M29="","",(J29-M29)/J29) | O29: Open | P29: Harper & Wells Boston (1500K) | Q29: US | R29: 80 | S29: 12 photos, 1st 800×800 | T29: Same main photo as 1 competitor(s) in your market → use photo 2 (or a model photo) as main image | U29: https://karlson-berlin.com/products/walpurga-langer-mantel-mit-pattentaschen https://wilson-and-carter.com/products/frances-coat | V29: ='Davento – Links'!H29 | W29: 2026-10-02
A30: 26 | C30: Week 1 | D30: A · Proven elsewhere, open in your market | E30: 82 | F30: Faye | Cozy Hooded Jacket | G30: Transition jacket | H30: ? | I30: top 18% bestseller at Harper & Wells Boston (US, 1500K visits/mo) · also at Wilson & Carter (UK) · no competitor sells it in IT/DE yet → open space · added 10 days ago · season fit 1.0 | J30: 54.95 | K30: 50–70 | L30: source link price (59.95 USD) converted | N30: =IF(M30="","",(J30-M30)/J30) | O30: Open | P30: Harper & Wells Boston (1500K) | Q30: US | R30: 80 | S30: 6 photos, 1st 800×800 | T30: Main photo free to use (no competitor in your market) | U30: https://wilson-and-carter.com/products/adaline | V30: ='Davento – Links'!H30 | W30: 2026-10-02
A31: 27 | C31: Week 1 | D31: B · Broadly proven | E31: 81.8 | F31: Maria - Veste De Printemps Élégante | G31: Transition jacket | H31: ? | I31: top 16% bestseller at Boutique Paris (FR, 166K visits/mo) · also at Parisane (FR), Cecile Lavelle (DE, small) · 1 competitor(s) in IT/DE · added 18 days ago · season fit 1.0 | J31: 49.99 | K31: 50–70 | L31: take over the source link price; note: already a bestseller at 1 competitor(s) in your market | N31: =IF(M31="","",(J31-M31)/J31) | O31: Open | P31: Boutique Paris (166K) | Q31: FR | R31: 86 | S31: 9 photos, 1st 1001×1001 | T31: Same main photo as 1 competitor(s) in your market → use photo 2 (or a model photo) as main image | U31: https://parisane.fr/products/veste-en-laine-femme-surchemise-oversize-a-poches | V31: ='Davento – Links'!H31 | W31: 2026-10-02
A32: 28 | C32: Week 1 | D32: B · Broadly proven | E32: 81.7 | F32: Magalie™ Boho-Stil Jacke | G32: Transition jacket | H32: ? | I32: top 20% bestseller at Nordheim Mode (DE, 546K visits/mo) · also at Boutique Paris (FR), Look de Paris (FR) · 1 competitor(s) in IT/DE · added 8 days ago · season fit 1.0 | J32: 74.95 | K32: 50–70 | L32: take over the source link price; note: already a bestseller at 1 competitor(s) in your market | N32: =IF(M32="","",(J32-M32)/J32) | O32: Open | P32: Nordheim Mode (546K) | Q32: DE ⚠ own market | R32: 70 | S32: 2 photos, 1st 1512×1512 | T32: Same main photo as 1 competitor(s) in your market → use photo 2 (or a model photo) as main image | U32: https://lookdeparis.com/products/caroline-veste-chic-vintage-velours https://boutique-paris.fr/products/emilie-veste-chic-boheme-velours | V32: ='Davento – Links'!H32 | W32: 2026-10-02
A33: 29 | C33: Week 1 | D33: B · Broadly proven | E33: 81.6 | F33: Adrian | Casual Modern Button Cardigan | G33: Cardigan | H33: ? | I33: top 4% bestseller at Harper & Wells Boston (US, 1500K visits/mo) · also at Wilson & Carter (UK), Lune Mode (IT, small), Paul's Wardrobe (US, small) · 1 competitor(s) in IT/DE · season fit 1.0 | J33: 73.95 | K33: 45–60 | L33: source link price (79.95 USD) converted | N33: =IF(M33="","",(J33-M33)/J33) | O33: Open | P33: Harper & Wells Boston (1500K) | Q33: US | R33: 87 | S33: 8 photos, 1st 1024×1024 | T33: Same main photo as 1 competitor(s) in your market → use photo 2 (or a model photo) as main image | U33: https://wilson-and-carter.com/products/godfrey-cardigan | V33: ='Davento – Links'!H33 | W33: 2026-10-02
A34: 30 | C34: Week 1 | D34: B · Broadly proven | E34: 81.6 | F34: Veste Kimono Femme Bohème Fluide Motifs Artistiques Élégants | G34: Transition jacket | H34: W | I34: top 8% bestseller at Lumière Boutique (FR, 275K visits/mo) · also at Nordheim Mode (DE), Boutique Élégance Bordeaux (FR, small), Vientovida (ES, small) · 1 competitor(s) in IT/DE · season fit 1.0 | J34: 49.95 | K34: 50–70 | L34: take over the source link price; note: already a bestseller at 1 competitor(s) in your market | N34: =IF(M34="","",(J34-M34)/J34) | O34: Open | P34: Lumière Boutique (275K) | Q34: FR | R34: 88 | S34: 4 photos, 1st 1728×2304 | T34: Same main photo as 1 competitor(s) in your market → use photo 2 (or a model photo) as main image | U34: https://nordheim-mode.de/products/aria-boho-kimono-jacke | V34: ='Davento – Links'!H34 | W34: 2026-10-02
A35: 31 | C35: Week 1 | D35: A · Proven elsewhere, open in your market | E35: 81.5 | F35: Rosetta | Artisan Open-Front Jacket | G35: Transition jacket | H35: ? | I35: top 13% bestseller at Harper & Wells Boston (US, 1500K visits/mo) · also at Parisane (FR), Wilson & Carter (UK) · no competitor sells it in IT/DE yet → open space · added 12 days ago · season fit 1.0 | J35: 63.95 | K35: 50–70 | L35: source link price (69.95 USD) converted | N35: =IF(M35="","",(J35-M35)/J35) | O35: Open | P35: Harper & Wells Boston (1500K) | Q35: US | R35: 56 | S35: 2 photos, 1st 800×800 | T35: Main photo free to use (no competitor in your market) | U35: https://parisane.fr/products/veste-femme-ouverte-imprime-ethnique-a-poches-mi-saison https://wilson-and-carter.com/products/saskia | V35: ='Davento – Links'!H35 | W35: 2026-10-02
A36: 32 | C36: Week 1 | D36: A · Proven elsewhere, open in your market | E36: 81.5 | F36: Veste femme à capuche avec poches et détails cloutés | G36: Transition jacket | H36: W | I36: top 24% bestseller at Lumière Boutique (FR, 275K visits/mo) · also at Boutique Élégance Bordeaux (FR, small), Luz Estilo (ES, small), Vientovida (ES, small) · no competitor sells it in IT/DE yet → open space · season fit 1.0 | J36: 54.95 | K36: 50–70 | L36: take over the source link price | N36: =IF(M36="","",(J36-M36)/J36) | O36: Open | P36: Lumière Boutique (275K) | Q36: FR | R36: 67 | S36: 2 photos, 1st 900×1200 | T36: Main photo free to use (no competitor in your market) | V36: ='Davento – Links'!H36 | W36: 2026-10-02
A37: 33 | C37: Week 1 | D37: B · Broadly proven | E37: 81.3 | F37: Trenchcoat Damen | Taillengürtel & Zeitlose Eleganz | G37: Transition jacket | H37: W | I37: top 36% bestseller at Lozenda Fashion (DE, 192K visits/mo) · also at Margaret Robinson (US, small), Mercer & Bloom (US, small) · 1 competitor(s) in IT/DE · added 7 days ago · season fit 1.0 | J37: 42.95 | K37: 50–70 | L37: take over the source link price; below the category sweet spot, can go higher: 59.95 | N37: =IF(M37="","",(J37-M37)/J37) | O37: Open | P37: Lozenda Fashion (192K) | Q37: DE ⚠ own market | R37: 80 | S37: 4 photos, 1st 956×1200 | T37: Same main photo as 1 competitor(s) in your market → use photo 2 (or a model photo) as main image | V37: ='Davento – Links'!H37 | W37: 2026-10-02
A38: 34 | C38: Week 1 | D38: C · New & rising | E38: 81.3 | F38: Steppjacke Damen | Glänzend & Wärmend | G38: Transition jacket | H38: W | I38: top 21% bestseller at Lozenda Fashion (DE, 192K visits/mo) · 1 competitor(s) in IT/DE · added 4 days ago · season fit 1.0 | J38: 62.95 | K38: 50–70 | L38: take over the source link price; note: already a bestseller at 1 competitor(s) in your market | N38: =IF(M38="","",(J38-M38)/J38) | O38: Open | P38: Lozenda Fashion (192K) | Q38: DE ⚠ own market | R38: 100 | S38: 6 photos, 1st 1600×1986 | T38: Same main photo as 1 competitor(s) in your market → use photo 2 (or a model photo) as main image | V38: ='Davento – Links'!H38 | W38: 2026-10-02
A39: 35 | C39: Week 1 | D39: A · Proven elsewhere, open in your market | E39: 80.8 | F39: Ensemble trois pièces femme avec cardigan imprimé | G39: Cardigan | H39: W | I39: top 10% bestseller at Lumière Boutique (FR, 275K visits/mo) · also at Boutique Élégance Bordeaux (FR, small) · no competitor sells it in IT/DE yet → open space · season fit 1.0 | J39: 49.95 | K39: 45–60 | L39: take over the source link price | N39: =IF(M39="","",(J39-M39)/J39) | O39: Open | P39: Lumière Boutique (275K) | Q39: FR | R39: 94 | S39: 12 photos, 1st 1023×1537 | T39: Main photo free to use (no competitor in your market) | V39: ='Davento – Links'!H39 | W39: 2026-10-02
A40: 36 | C40: Week 1 | D40: B · Broadly proven | E40: 80.5 | F40: Veste en laine mélangée femme à col montant coupe droite | G40: Transition jacket | H40: W | I40: top 24% bestseller at Parisane (FR, 77K visits/mo) · also at Nicole Modehaus (DE, small), North Style Fashion (US, small), Paul's Wardrobe (US, small), Vientovida (ES, small) · 1 competitor(s) in IT/DE · season fit 1.0 | J40: 44.99 | K40: 50–70 | L40: take over the source link price; below the category sweet spot, can go higher: 59.95; note: already a bestseller at 1 competitor(s) in your market | N40: =IF(M40="","",(J40-M40)/J40) | O40: Open | P40: Parisane (77K) | Q40: FR | R40: 87 | S40: 10 photos, 1st 1024×1024 | T40: Same main photo as 1 competitor(s) in your market → use photo 2 (or a model photo) as main image | V40: ='Davento – Links'!H40 | W40: 2026-10-02
A41: 37 | C41: Week 1 | D41: C · New & rising | E41: 80.4 | F41: Unisex Schneejacke mit Kapuze | G41: Transition jacket | H41: ? | I41: top 1% bestseller at Alpenkind Mode (DE, 77K visits/mo) · 1 competitor(s) in IT/DE · added 0 days ago · season fit 1.0 | J41: 74.95 | K41: 50–70 | L41: take over the source link price; note: already a bestseller at 1 competitor(s) in your market | N41: =IF(M41="","",(J41-M41)/J41) | O41: Open | P41: Alpenkind Mode (77K) | Q41: DE ⚠ own market | R41: 77 | S41: 4 photos, 1st 1080×1080 | T41: Same main photo as 1 competitor(s) in your market → use photo 2 (or a model photo) as main image | V41: ='Davento – Links'!H41 | W41: 2026-10-02
A42: 38 | C42: Week 1 | D42: B · Broadly proven | E42: 80 | F42: Eleanora | Cable-Knit Button-Front Cardigan | G42: Cardigan | H42: ? | I42: top 27% bestseller at Harper & Wells Boston (US, 1500K visits/mo) · also at Look de Paris (FR), Wilson & Carter (UK) · no competitor sells it in IT/DE yet → open space · season fit 1.0 | J42: 73.95 | K42: 45–60 | L42: source link price (79.95 USD) converted | N42: =IF(M42="","",(J42-M42)/J42) | O42: Open | P42: Harper & Wells Boston (1500K) | Q42: US | R42: 93 | S42: 12 photos, 1st 1773×1773 | T42: Main photo free to use (no competitor in your market) | U42: https://lookdeparis.com/products/isabelle-gilet-elegant-torsade-col-rond https://wilson-and-carter.com/products/cecilia-cardigan | V42: ='Davento – Links'!H42 | W42: 2026-10-02
A43: 39 | C43: Week 1 | D43: B · Broadly proven | E43: 79.9 | F43: Cardigan Corto Donna Autunnale con Collo Alto e Bottoni | G43: Cardigan | H43: W | I43: top 26% bestseller at Vitelli Moda (IT, 121K visits/mo) · also at Boutique Paris (FR), Look de Paris (FR), Mercer & Bloom (US, small) · 1 competitor(s) in IT/DE · season fit 1.0 | J43: 41.95 | K43: 45–60 | L43: take over the source link price; below the category sweet spot, can go higher: 49.95 | N43: =IF(M43="","",(J43-M43)/J43) | O43: Open | P43: Vitelli Moda (121K) | Q43: IT ⚠ own market | R43: 74 | S43: 5 photos, 1st 800×800 | T43: Same main photo as 1 competitor(s) in your market → use photo 2 (or a model photo) as main image | U43: https://lookdeparis.com/products/emilie-gilet-elegant-en-cachemire-col-officier https://boutique-paris.fr/products/isabelle-gilet-raffine-cachemire-col-montant-boutonne | V43: ='Davento – Links'!H43 | W43: 2026-10-02
A44: 40 | C44: Week 1 | D44: A · Proven elsewhere, open in your market | E44: 79.7 | F44: Cléa - Veste imperméable pour femmes | G44: Transition jacket | H44: W | I44: top 22% bestseller at Boutique Paris (FR, 166K visits/mo) · also at Look de Paris (FR) · no competitor sells it in IT/DE yet → open space · added 9 days ago · season fit 1.0 | J44: 59.99 | K44: 50–70 | L44: take over the source link price | N44: =IF(M44="","",(J44-M44)/J44) | O44: Open | P44: Boutique Paris (166K) | Q44: FR | R44: 73 | S44: 6 photos, 1st 600×600 | T44: Main photo free to use (no competitor in your market) | U44: https://lookdeparis.com/products/nathalie-veste-elegante-impermeable-capuche | V44: ='Davento – Links'!H44 | W44: 2026-10-02
A45: 41 | C45: Week 1 | D45: A · Proven elsewhere, open in your market | E45: 79.6 | F45: Cecilia | Soft Button-Front Cardigan | G45: Cardigan | H45: ? | I45: top 20% bestseller at Harper & Wells Boston (US, 1500K visits/mo) · also at Wilson & Carter (UK) · no competitor sells it in IT/DE yet → open space · added 10 days ago · season fit 1.0 | J45: 68.95 | K45: 45–60 | L45: source link price (74.95 USD) converted | N45: =IF(M45="","",(J45-M45)/J45) | O45: Open | P45: Harper & Wells Boston (1500K) | Q45: US | R45: 74 | S45: 5 photos, 1st 800×800 | T45: Main photo free to use (no competitor in your market) | U45: https://wilson-and-carter.com/products/juniper-cardigan | V45: ='Davento – Links'!H45 | W45: 2026-10-02
A46: 42 | C46: Week 1 | D46: B · Broadly proven | E46: 79.3 | F46: Gideon | Classic Textured Athletic Jacket | G46: Transition jacket | H46: ? | I46: top 5% bestseller at Wilson & Carter (UK, 200K visits/mo) · also at Donna's Dresses (US, small), Lune Mode (IT, small), North Style Fashion (US, small), Paul's Wardrobe (US, small) · 1 competitor(s) in IT/DE · season fit 1.0 | J46: 46.95 | K46: 50–70 | L46: source link price (39.95 GBP) converted; below the category sweet spot, can go higher: 59.95 | N46: =IF(M46="","",(J46-M46)/J46) | O46: Open | P46: Wilson & Carter (200K) | Q46: UK | R46: 87 | S46: 7 photos, 1st 800×1000 | T46: Same main photo as 1 competitor(s) in your market → use photo 2 (or a model photo) as main image | V46: ='Davento – Links'!H46 | W46: 2026-10-02
A47: 43 | C47: Week 1 | D47: B · Broadly proven | E47: 79.2 | F47: Estella | Chunky Knit Cardigan | G47: Cardigan | H47: ? | I47: top 39% bestseller at Harper & Wells Boston (US, 1500K visits/mo) · also at Boutique Paris (FR), Look de Paris (FR), Wilson & Carter (UK) · no competitor sells it in IT/DE yet → open space · season fit 1.0 | J47: 45.95 | K47: 45–60 | L47: source link price (49.95 USD) converted | N47: =IF(M47="","",(J47-M47)/J47) | O47: Open | P47: Harper & Wells Boston (1500K) | Q47: US | R47: 87 | S47: 5 photos, 1st 1340×1340 | T47: Main photo free to use (no competitor in your market) | U47: https://lookdeparis.com/products/isabelle-gilet-elegant-grosse-maille-torsade https://boutique-paris.fr/products/christine-gilet-elegant-grosse-maille-torsadee https://wilson-and-carter.com/products/elowen-cardigan | V47: ='Davento – Links'!H47 | W47: 2026-10-02
A48: 44 | C48: Week 1 | D48: C · New & rising | E48: 78.9 | F48: Taktische Allwetterjacke wasserdicht & atmungsaktiv – StormShield Pro | G48: Transition jacket | H48: ? | I48: top 12% bestseller at Nordspur (DE, 89K visits/mo) · 1 competitor(s) in IT/DE · added 2 days ago · season fit 1.0 | J48: 49.95 | K48: 50–70 | L48: take over the source link price; note: already a bestseller at 1 competitor(s) in your market | N48: =IF(M48="","",(J48-M48)/J48) | O48: Open | P48: Nordspur (89K) | Q48: DE ⚠ own market | R48: 89 | S48: 12 photos, 1st 1080×1080 | T48: Same main photo as 1 competitor(s) in your market → use photo 2 (or a model photo) as main image | V48: ='Davento – Links'!H48 | W48: 2026-10-02
A49: 45 | C49: Week 1 | D49: B · Broadly proven | E49: 78.9 | F49: LAURENT MONACO | VESTE EN CUIR HAUT DE GAMME ÉLÉGANTE POUR HOMME | G49: Transition jacket | H49: M | I49: top 1% bestseller at Laurent Monaco (FR, 269K visits/mo) · also at Lumière Boutique (FR), Wentworth London (UK), Falkenhof Mode (DE, small) · 1 competitor(s) in IT/DE · season fit 1.0 | J49: 59.95 | K49: 50–70 | L49: take over the source link price; note: already a bestseller at 1 competitor(s) in your market | N49: =IF(M49="","",(J49-M49)/J49) | O49: Open | P49: Laurent Monaco (269K) | Q49: FR | R49: 90 | S49: 10 photos, 1st 900×1200 | T49: Same main photo as 1 competitor(s) in your market → use photo 2 (or a model photo) as main image | U49: https://lumiereboutique.fr/products/dumont-lyon-veste-en-cuir-haut-de-gamme-elegante-pour-homme https://wentworthlondon.com/products/faux-leather-jacket-for-men | V49: ='Davento – Links'!H49 | W49: 2026-10-02
A50: 46 | C50: Week 1 | D50: B · Broadly proven | E50: 78.8 | F50: Hugh | Tailored Longline Coat | G50: Transition jacket | H50: M | I50: top 47% bestseller at Wilson & Carter (UK, 200K visits/mo) · also at Harper & Wells Boston (US), Lozenda Fashion (DE) · 1 competitor(s) in IT/DE · added 8 days ago · season fit 1.0 | J50: 57.95 | K50: 50–70 | L50: source link price (49.95 GBP) converted | N50: =IF(M50="","",(J50-M50)/J50) | O50: Open | P50: Wilson & Carter (200K) | Q50: UK | R50: 93 | S50: 12 photos, 1st 1340×1340 | T50: Same main photo as 1 competitor(s) in your market → use photo 2 (or a model photo) as main image | U50: https://lozendafashion.com/products/trenchcoat-herren-elegant-zeitlos https://harperwells-boston.com/products/warner | V50: ='Davento – Links'!H50 | W50: 2026-10-02
A51: 47 | C51: Week 1 | D51: A · Proven elsewhere, open in your market | E51: 78.7 | F51: Evangeline | Relaxed Open-Front Cardigan | G51: Cardigan | H51: ? | I51: top 23% bestseller at Harper & Wells Boston (US, 1500K visits/mo) · also at Wilson & Carter (UK) · no competitor sells it in IT/DE yet → open space · added 10 days ago · season fit 1.0 | J51: 77.95 | K51: 45–60 | L51: source link price (84.95 USD) converted | N51: =IF(M51="","",(J51-M51)/J51) | O51: Open | P51: Harper & Wells Boston (1500K) | Q51: US | R51: 74 | S51: 5 photos, 1st 800×800 | T51: Main photo free to use (no competitor in your market) | U51: https://wilson-and-carter.com/products/edith | V51: ='Davento – Links'!H51 | W51: 2026-10-02
A52: 48 | C52: Week 1 | D52: A · Proven elsewhere, open in your market | E52: 78.7 | F52: Trevor | Patchwork Vest with Herringbone Pattern | G52: Transition jacket | H52: ? | I52: top 12% bestseller at Harper & Wells Boston (US, 1500K visits/mo) · also at Wilson & Carter (UK), Paul's Wardrobe (US, small) · no competitor sells it in IT/DE yet → open space · season fit 1.0 | J52: 63.95 | K52: 50–70 | L52: source link price (69.95 USD) converted | N52: =IF(M52="","",(J52-M52)/J52) | O52: Open | P52: Harper & Wells Boston (1500K) | Q52: US | R52: 100 | S52: 9 photos, 1st 1340×1785 | T52: Main photo free to use (no competitor in your market) | U52: https://wilson-and-carter.com/products/benedict | V52: ='Davento – Links'!H52 | W52: 2026-10-02
A53: 49 | C53: Week 1 | D53: B · Broadly proven | E53: 78.5 | F53: Weste Herren | Praktisch & Vielseitig Kombinierbar | G53: Transition jacket | H53: M | I53: top 16% bestseller at Lozenda Fashion (DE, 192K visits/mo) · also at Boutique Paris (FR), Look de Paris (FR) · 1 competitor(s) in IT/DE · added 14 days ago · season fit 1.0 | J53: 42.95 | K53: 50–70 | L53: take over the source link price; below the category sweet spot, can go higher: 59.95; note: already a bestseller at 1 competitor(s) in your market | N53: =IF(M53="","",(J53-M53)/J53) | O53: Open | P53: Lozenda Fashion (192K) | Q53: DE ⚠ own market | R53: 77 | S53: 4 photos, 1st 1080×1080 | T53: Same main photo as 1 competitor(s) in your market → use photo 2 (or a model photo) as main image | U53: https://lookdeparis.com/products/michel-veste-elegante-zippee-col-montant https://boutique-paris.fr/products/julien-veste-elegante-zippee-col-montant | V53: ='Davento – Links'!H53 | W53: 2026-10-02
A54: 50 | C54: Week 1 | D54: C · New & rising | E54: 78.5 | F54: Fellmantel Damen | Oversize & Kuschelig Warm | G54: Transition jacket | H54: W | I54: top 8% bestseller at Lozenda Fashion (DE, 192K visits/mo) · 1 competitor(s) in IT/DE · added 11 days ago · season fit 1.0 | J54: 63.95 | K54: 50–70 | L54: take over the source link price; note: already a bestseller at 1 competitor(s) in your market | N54: =IF(M54="","",(J54-M54)/J54) | O54: Open | P54: Lozenda Fashion (192K) | Q54: DE ⚠ own market | R54: 84 | S54: 12 photos, 1st 720×1036 | T54: Same main photo as 1 competitor(s) in your market → use photo 2 (or a model photo) as main image | V54: ='Davento – Links'!H54 | W54: 2026-10-02
A55: 51 | C55: Week 1 | D55: C · New & rising | E55: 78.4 | F55: Steppjacke Damen | Kuschelig Warm & Oversize | G55: Transition jacket | H55: W | I55: top 31% bestseller at Lozenda Fashion (DE, 192K visits/mo) · 1 competitor(s) in IT/DE · added 0 days ago · season fit 1.0 | J55: 67.95 | K55: 50–70 | L55: take over the source link price | N55: =IF(M55="","",(J55-M55)/J55) | O55: Open | P55: Lozenda Fashion (192K) | Q55: DE ⚠ own market | R55: 96 | S55: 7 photos, 1st 1080×1621 | T55: Same main photo as 1 competitor(s) in your market → use photo 2 (or a model photo) as main image | V55: ='Davento – Links'!H55 | W55: 2026-10-02
A56: 52 | C56: Week 1 | D56: A · Proven elsewhere, open in your market | E56: 78.3 | F56: Hazel | Floral Open-Front Cardigan | G56: Cardigan | H56: ? | I56: top 11% bestseller at Harper & Wells Boston (US, 1500K visits/mo) · also at Boutique Paris (FR), Wilson & Carter (UK) · no competitor sells it in IT/DE yet → open space · season fit 1.0 | J56: 59.95 | K56: 45–60 | L56: source link price (64.95 USD) converted | N56: =IF(M56="","",(J56-M56)/J56) | O56: Open | P56: Harper & Wells Boston (1500K) | Q56: US | R56: 62 | S56: 3 photos, 1st 800×800 | T56: Main photo free to use (no competitor in your market) | U56: https://boutique-paris.fr/products/manon-gilet-feminin-fleuri-brode-boutonne https://wilson-and-carter.com/products/greta-cardigan | V56: ='Davento – Links'!H56 | W56: 2026-10-02
A57: 53 | C57: Week 1 | D57: B · Broadly proven | E57: 78.1 | F57: Alaric | Classic Single-Breasted Blazer | G57: Blazer | H57: ? | I57: top 11% bestseller at Wilson & Carter (UK, 200K visits/mo) · also at Drune (DE), Paul's Wardrobe (US, small) · 1 competitor(s) in IT/DE · added 2 days ago · season fit 0.8 | J57: 57.95 | K57: 50–70 | L57: source link price (49.95 GBP) converted | N57: =IF(M57="","",(J57-M57)/J57) | O57: Open | P57: Wilson & Carter (200K) | Q57: UK | R57: 87 | S57: 5 photos, 1st 2048×2048 | T57: Same main photo as 1 competitor(s) in your market → use photo 2 (or a model photo) as main image | U57: https://drune.de/products/herren-strukturierter-leinenblazer-mit-stehkragen-und-dekorativer-knopfreihe-drune-zwerq4ya2z | V57: ='Davento – Links'!H57 | W57: 2026-10-02
A58: 54 | C58: Week 1 | D58: A · Proven elsewhere, open in your market | E58: 77.8 | F58: Ensemble trois pièces femme gilet ouvert imprimé, top et pantalon | G58: Transition jacket | H58: W | I58: top 8% bestseller at Parisane (FR, 77K visits/mo) · no competitor sells it in IT/DE yet → open space · season fit 1.0 | J58: 44.99 | K58: 50–70 | L58: take over the source link price; below the category sweet spot, can go higher: 59.95 | N58: =IF(M58="","",(J58-M58)/J58) | O58: Open | P58: Parisane (77K) | Q58: FR | R58: 94 | S58: 12 photos, 1st 1023×1537 | T58: Main photo free to use (no competitor in your market) | V58: ='Davento – Links'!H58 | W58: 2026-10-02
A59: 55 | C59: Week 1 | D59: A · Proven elsewhere, open in your market | E59: 77.7 | F59: Georgina | Hooded Longline Coat | G59: Transition jacket | H59: ? | I59: top 23% bestseller at Harper & Wells Boston (US, 1500K visits/mo) · also at Wilson & Carter (UK) · no competitor sells it in IT/DE yet → open space · added 12 days ago · season fit 1.0 | J59: 91.95 | K59: 50–70 | L59: source link price (99.95 USD) converted | N59: =IF(M59="","",(J59-M59)/J59) | O59: Open | P59: Harper & Wells Boston (1500K) | Q59: US | R59: 74 | S59: 5 photos, 1st 800×800 | T59: Main photo free to use (no competitor in your market) | U59: https://wilson-and-carter.com/products/marion-coat | V59: ='Davento – Links'!H59 | W59: 2026-10-02
A60: 56 | C60: Week 1 | D60: B · Broadly proven | E60: 77.5 | F60: Harold | Refined Single Breasted Cardigan | G60: Cardigan | H60: ? | I60: top 2% bestseller at Harper & Wells Boston (US, 1500K visits/mo) · also at Lune Mode (IT, small), Urbanase (US, small) · 1 competitor(s) in IT/DE · season fit 1.0 | J60: 73.95 | K60: 45–60 | L60: source link price (79.95 USD) converted | N60: =IF(M60="","",(J60-M60)/J60) | O60: Open | P60: Harper & Wells Boston (1500K) | Q60: US | R60: 87 | S60: 5 photos, 1st 2048×2048 | T60: Same main photo as 1 competitor(s) in your market → use photo 2 (or a model photo) as main image | V60: ='Davento – Links'!H60 | W60: 2026-10-02
A61: 57 | C61: Week 1 | D61: A · Proven elsewhere, open in your market | E61: 77.5 | F61: Dario Cotton Overshirt | G61: Transition jacket | H61: ? | I61: top 23% bestseller at Oliver & Blake (US, 98K visits/mo) · no competitor sells it in IT/DE yet → open space · added 6 days ago · season fit 1.0 | J61: 54.95 | K61: 50–70 | L61: source link price (59.99 USD) converted | N61: =IF(M61="","",(J61-M61)/J61) | O61: Open | P61: Oliver & Blake (98K) | Q61: US | R61: 93 | S61: 6 photos, 1st 1254×1254 | T61: Main photo free to use (no competitor in your market) | V61: ='Davento – Links'!H61 | W61: 2026-10-02
A62: 58 | C62: Week 1 | D62: C · New & rising | E62: 77.4 | F62: Jacke Damen Lang | Kapuze & Verstellbarer Kordelzug | G62: Transition jacket | H62: W | I62: top 32% bestseller at Lozenda Fashion (DE, 192K visits/mo) · 1 competitor(s) in IT/DE · added 0 days ago · season fit 1.0 | J62: 75.95 | K62: 50–70 | L62: take over the source link price | N62: =IF(M62="","",(J62-M62)/J62) | O62: Open | P62: Lozenda Fashion (192K) | Q62: DE ⚠ own market | R62: 93 | S62: 10 photos, 1st 2048×2048 | T62: Same main photo as 1 competitor(s) in your market → use photo 2 (or a model photo) as main image | V62: ='Davento – Links'!H62 | W62: 2026-10-02
A63: 59 | C63: Week 1 | D63: A · Proven elsewhere, open in your market | E63: 77.3 | F63: Callahan | Shawl Collar Knit Cardigan | G63: Cardigan | H63: ? | I63: top 22% bestseller at Harper & Wells Boston (US, 1500K visits/mo) · also at Wilson & Carter (UK) · no competitor sells it in IT/DE yet → open space · added 10 days ago · season fit 1.0 | J63: 91.95 | K63: 45–60 | L63: source link price (99.95 USD) converted | N63: =IF(M63="","",(J63-M63)/J63) | O63: Open | P63: Harper & Wells Boston (1500K) | Q63: US | R63: 68 | S63: 4 photos, 1st 800×800 | T63: Main photo free to use (no competitor in your market) | U63: https://wilson-and-carter.com/products/wyatt-cardigan | V63: ='Davento – Links'!H63 | W63: 2026-10-02
A64: 60 | C64: Week 1 | D64: B · Broadly proven | E64: 77.2 | F64: Connor | Signatur Modernes Sakko-Set | G64: Blazer | H64: ? | I64: top 3% bestseller at Karlson Berlin (DE, 981K visits/mo) · also at Lozenda Fashion (DE), Vientovida (ES, small) · 2 competitor(s) in IT/DE · added 11 days ago · season fit 1.0 | J64: 119.95 | K64: 50–70 | L64: take over the source link price; note: already a bestseller at 1 competitor(s) in your market | N64: =IF(M64="","",(J64-M64)/J64) | O64: Open | P64: Karlson Berlin (981K) | Q64: DE ⚠ own market | R64: 89 | S64: 6 photos, 1st 1080×1080 | T64: Same main photo as 2 competitor(s) in your market → use photo 2 (or a model photo) as main image | U64: https://lozendafashion.com/products/blazer-set-damen-elegant-atmungsaktiv | V64: ='Davento – Links'!H64 | W64: 2026-10-02
A65: 61 | C65: Week 1 | D65: A · Proven elsewhere, open in your market | E65: 77.1 | F65: Camille – Trench Mi-Long Pour Femmes, Une Option Élégante Pour Toutes Les Occasions | G65: Transition jacket | H65: W | I65: top 9% bestseller at Boutique Paris (FR, 166K visits/mo) · also at Look de Paris (FR) · no competitor sells it in IT/DE yet → open space · season fit 1.0 | J65: 59.99 | K65: 50–70 | L65: take over the source link price | N65: =IF(M65="","",(J65-M65)/J65) | O65: Open | P65: Boutique Paris (166K) | Q65: FR | R65: 80 | S65: 7 photos, 1st 800×800 | T65: Main photo free to use (no competitor in your market) | U65: https://lookdeparis.com/products/veronique | V65: ='Davento – Links'!H65 | W65: 2026-10-02
A66: 62 | C66: Week 1 | D66: A · Proven elsewhere, open in your market | E66: 77 | F66: Liv Leather Jacket | G66: Transition jacket | H66: ? | I66: top 3% bestseller at Oliver & Blake (US, 98K visits/mo) · also at Mayfair & Finch (UK, small), Mercer & Bloom (US, small) · no competitor sells it in IT/DE yet → open space · season fit 1.0 | J66: 63.95 | K66: 50–70 | L66: source link price (69.99 USD) converted | N66: =IF(M66="","",(J66-M66)/J66) | O66: Open | P66: Oliver & Blake (98K) | Q66: US | R66: 93 | S66: 8 photos, 1st 1600×1600 | T66: Main photo free to use (no competitor in your market) | V66: ='Davento – Links'!H66 | W66: 2026-10-02
A67: 63 | C67: Week 1 | D67: B · Broadly proven | E67: 76.7 | F67: Della | Cozy Oversized Cardigan | G67: Cardigan | H67: ? | I67: top 10% bestseller at Harper & Wells Boston (US, 1500K visits/mo) · also at Wilson & Carter (UK), Donna's Dresses (US, small), North Style Fashion (US, small), Soof & Clay (IT, small) · 1 competitor(s) in IT/DE · season fit 1.0 | J67: 73.95 | K67: 45–60 | L67: source link price (79.95 USD) converted | N67: =IF(M67="","",(J67-M67)/J67) | O67: Open | P67: Harper & Wells Boston (1500K) | Q67: US | R67: 77 | S67: 6 photos, 1st 720×720 | T67: Same main photo as 1 competitor(s) in your market → use photo 2 (or a model photo) as main image | U67: https://wilson-and-carter.com/products/elise-cardigan | V67: ='Davento – Links'!H67 | W67: 2026-10-02
A68: 64 | C68: Week 1 | D68: C · New & rising | E68: 76.7 | F68: Mantel Damen Lang | Lockerer Schnitt für Herbst | G68: Transition jacket | H68: W | I68: top 20% bestseller at Lozenda Fashion (DE, 192K visits/mo) · 1 competitor(s) in IT/DE · added 3 days ago · season fit 1.0 | J68: 72.95 | K68: 50–70 | L68: take over the source link price; note: already a bestseller at 1 competitor(s) in your market | N68: =IF(M68="","",(J68-M68)/J68) | O68: Open | P68: Lozenda Fashion (192K) | Q68: DE ⚠ own market | R68: 80 | S68: 8 photos, 1st 800×800 | T68: Same main photo as 1 competitor(s) in your market → use photo 2 (or a model photo) as main image | V68: ='Davento – Links'!H68 | W68: 2026-10-02
A69: 65 | C69: Week 1 | D69: C · New & rising | E69: 76.7 | F69: Herrenjacke mit langen Ärmeln | Vielseitig & stilvoll | Weiches, atmungsaktives Gewebe | G69: Transition jacket | H69: M | I69: top 2% bestseller at Lozenda Fashion (DE, 192K visits/mo) · 1 competitor(s) in IT/DE · added 11 days ago · season fit 1.0 | J69: 49.95 | K69: 50–70 | L69: take over the source link price; note: already a bestseller at 1 competitor(s) in your market | N69: =IF(M69="","",(J69-M69)/J69) | O69: Open | P69: Lozenda Fashion (192K) | Q69: DE ⚠ own market | R69: 90 | S69: 11 photos, 1st 900×1200 | T69: Same main photo as 1 competitor(s) in your market → use photo 2 (or a model photo) as main image | V69: ='Davento – Links'!H69 | W69: 2026-10-02
A70: 66 | C70: Week 1 | D70: B · Broadly proven | E70: 76.6 | F70: Strick-Cardigan Damen | Blumenmuster & Knopfleiste | G70: Cardigan | H70: W | I70: top 32% bestseller at Lozenda Fashion (DE, 192K visits/mo) · also at Leon Boutique (DE), Donna's Dresses (US, small), Mayfair & Finch (UK, small), Mercer & Bloom (US, small) +1 · 2 competitor(s) in IT/DE · added 3 days ago · season fit 1.0 | J70: 44.95 | K70: 45–60 | L70: take over the source link price | N70: =IF(M70="","",(J70-M70)/J70) | O70: Open | P70: Lozenda Fashion (192K) | Q70: DE ⚠ own market | R70: 90 | S70: 8 photos, 1st 900×1200 | T70: Same main photo as 2 competitor(s) in your market → use photo 2 (or a model photo) as main image | U70: https://leonboutique.co/products/lena-damen-klassische-gemusterte-strickjacke-mit-knopfen | V70: ='Davento – Links'!H70 | W70: 2026-10-02
A71: 67 | C71: Week 1 | D71: B · Broadly proven | E71: 76.6 | F71: LAURENT MONACO | VESTE EN CUIR SUEDE URBAINE | G71: Transition jacket | H71: ? | I71: top 1% bestseller at Laurent Monaco (FR, 269K visits/mo) · also at Lumière Boutique (FR), Lune Mode (IT, small) · 1 competitor(s) in IT/DE · season fit 1.0 | J71: 49.95 | K71: 50–70 | L71: take over the source link price | N71: =IF(M71="","",(J71-M71)/J71) | O71: Open | P71: Laurent Monaco (269K) | Q71: FR | R71: 90 | S71: 7 photos, 1st 900×1200 | T71: Same main photo as 1 competitor(s) in your market → use photo 2 (or a model photo) as main image | U71: https://lumiereboutique.fr/products/dumont-lyon-veste-en-cuir-suede-urbaine | V71: ='Davento – Links'!H71 | W71: 2026-10-02
A72: 68 | C72: Week 1 | D72: A · Proven elsewhere, open in your market | E72: 76.5 | F72: Amélie - Trenchcoat Femme | G72: Transition jacket | H72: W | I72: top 9% bestseller at Boutique Paris (FR, 166K visits/mo) · also at Dolce Paris (FR, small), Mercer & Bloom (US, small) · no competitor sells it in IT/DE yet → open space · season fit 1.0 | J72: 64.99 | K72: 50–70 | L72: take over the source link price | N72: =IF(M72="","",(J72-M72)/J72) | O72: Open | P72: Boutique Paris (166K) | Q72: FR | R72: 87 | S72: 5 photos, 1st 1500×1500 | T72: Main photo free to use (no competitor in your market) | V72: ='Davento – Links'!H72 | W72: 2026-10-02
A73: 69 | C73: Week 1 | D73: C · New & rising | E73: 76.5 | F73: Bomberjacke Damen | Reißverschluss & Elastische Bündchen | G73: Transition jacket | H73: W | I73: top 16% bestseller at Lozenda Fashion (DE, 192K visits/mo) · 1 competitor(s) in IT/DE · added 15 days ago · season fit 1.0 | J73: 37.95 | K73: 50–70 | L73: take over the source link price; below the category sweet spot, can go higher: 59.95; note: already a bestseller at 1 competitor(s) in your market | N73: =IF(M73="","",(J73-M73)/J73) | O73: Open | P73: Lozenda Fashion (192K) | Q73: DE ⚠ own market | R73: 94 | S73: 5 photos, 1st 1340×1785 | T73: Same main photo as 1 competitor(s) in your market → use photo 2 (or a model photo) as main image | V73: ='Davento – Links'!H73 | W73: 2026-10-02
A74: 70 | C74: Week 1 | D74: A · Proven elsewhere, open in your market | E74: 76.3 | F74: LAURENT MONACO | VESTE THERMIQUE IMPERMÉABLE | G74: Transition jacket | H74: ? | I74: top 6% bestseller at Laurent Monaco (FR, 269K visits/mo) · also at Lumière Boutique (FR), Wentworth London (UK) · no competitor sells it in IT/DE yet → open space · season fit 1.0 | J74: 59.95 | K74: 50–70 | L74: take over the source link price | N74: =IF(M74="","",(J74-M74)/J74) | O74: Open | P74: Laurent Monaco (269K) | Q74: FR | R74: 90 | S74: 8 photos, 1st 900×1200 | T74: Main photo free to use (no competitor in your market) | U74: https://lumiereboutique.fr/products/dumont-lyon-veste-thermique-impermeable https://wentworthlondon.com/products/wentworth-london-waterproof-thermal-jacket | V74: ='Davento – Links'!H74 | W74: 2026-10-02
A75: 71 | C75: Week 1 | D75: C · New & rising | E75: 75.9 | F75: Nordspur | Vellora Leichte Steppjacke Für Damen | G75: Transition jacket | H75: W | I75: top 34% bestseller at Nordspur (DE, 89K visits/mo) · 1 competitor(s) in IT/DE · added 0 days ago · season fit 1.0 | J75: 74.95 | K75: 50–70 | L75: take over the source link price | N75: =IF(M75="","",(J75-M75)/J75) | O75: Open | P75: Nordspur (89K) | Q75: DE ⚠ own market | R75: 93 | S75: 12 photos, 1st 1536×1536 | T75: Same main photo as 1 competitor(s) in your market → use photo 2 (or a model photo) as main image | V75: ='Davento – Links'!H75 | W75: 2026-10-02
A76: 72 | C76: Week 1 | D76: C · New & rising | E76: 75.8 | F76: Nordspur | Levian Leichte Damen-Steppjacke Mit Kapuze | G76: Transition jacket | H76: W | I76: top 34% bestseller at Nordspur (DE, 89K visits/mo) · 1 competitor(s) in IT/DE · added 0 days ago · season fit 1.0 | J76: 104.95 | K76: 50–70 | L76: take over the source link price | N76: =IF(M76="","",(J76-M76)/J76) | O76: Open | P76: Nordspur (89K) | Q76: DE ⚠ own market | R76: 93 | S76: 12 photos, 1st 1536×1536 | T76: Same main photo as 1 competitor(s) in your market → use photo 2 (or a model photo) as main image | V76: ='Davento – Links'!H76 | W76: 2026-10-02
A77: 73 | C77: Week 1 | D77: C · New & rising | E77: 75.8 | F77: Nordspur | Aurina Leichte Steppjacke Für Damen | G77: Transition jacket | H77: W | I77: top 34% bestseller at Nordspur (DE, 89K visits/mo) · 1 competitor(s) in IT/DE · added 0 days ago · season fit 1.0 | J77: 84.95 | K77: 50–70 | L77: take over the source link price | N77: =IF(M77="","",(J77-M77)/J77) | O77: Open | P77: Nordspur (89K) | Q77: DE ⚠ own market | R77: 93 | S77: 12 photos, 1st 1536×1536 | T77: Same main photo as 1 competitor(s) in your market → use photo 2 (or a model photo) as main image | V77: ='Davento – Links'!H77 | W77: 2026-10-02
A78: 74 | C78: Week 1 | D78: B · Broadly proven | E78: 75.4 | F78: Matthieu - Homme Veste Bomber Urbaine | G78: Transition jacket | H78: ? | I78: top 26% bestseller at Boutique Paris (FR, 166K visits/mo) · also at Look de Paris (FR), Nordheim Mode (DE), Vientovida (ES, small) · 1 competitor(s) in IT/DE · season fit 1.0 | J78: 59.99 | K78: 50–70 | L78: take over the source link price; note: already a bestseller at 1 competitor(s) in your market | N78: =IF(M78="","",(J78-M78)/J78) | O78: Open | P78: Boutique Paris (166K) | Q78: FR | R78: 66 | S78: 3 photos, 1st 713×1069 | T78: Same main photo as 1 competitor(s) in your market → use photo 2 (or a model photo) as main image | U78: https://nordheim-mode.de/products/harry-stone-jacke https://lookdeparis.com/products/mathieu-2 | V78: ='Davento – Links'!H78 | W78: 2026-10-02
A79: 75 | C79: Week 1 | D79: C · New & rising | E79: 75.3 | F79: Herren Ski Set mit Kapuzenjacke und Hose | G79: Transition jacket | H79: M | I79: top 6% bestseller at Alpenkind Mode (DE, 77K visits/mo) · 1 competitor(s) in IT/DE · added 0 days ago · season fit 1.0 | J79: 129.95 | K79: 50–70 | L79: take over the source link price; note: already a bestseller at 1 competitor(s) in your market | N79: =IF(M79="","",(J79-M79)/J79) | O79: Open | P79: Alpenkind Mode (77K) | Q79: DE ⚠ own market | R79: 75 | S79: 4 photos, 1st 1020×1020 | T79: Same main photo as 1 competitor(s) in your market → use photo 2 (or a model photo) as main image | V79: ='Davento – Links'!H79 | W79: 2026-10-02
A80: 76 | C80: Week 1 | D80: A · Proven elsewhere, open in your market | E80: 75.3 | F80: LAURENT MONACO | VESTE EN CUIR SUEDE | G80: Transition jacket | H80: ? | I80: top 11% bestseller at Laurent Monaco (FR, 269K visits/mo) · also at Wentworth London (UK) · no competitor sells it in IT/DE yet → open space · season fit 1.0 | J80: 59.95 | K80: 50–70 | L80: take over the source link price | N80: =IF(M80="","",(J80-M80)/J80) | O80: Open | P80: Laurent Monaco (269K) | Q80: FR | R80: 78 | S80: 4 photos, 1st 900×1200 | T80: Main photo free to use (no competitor in your market) | U80: https://wentworthlondon.com/products/brushed-suede-jacket-for-men | V80: ='Davento – Links'!H80 | W80: 2026-10-02
A81: 77 | C81: Week 1 | D81: B · Broadly proven | E81: 75.1 | F81: Anaïs – Veste de ski femme avec capuche et poches | G81: Transition jacket | H81: W | I81: top 2% bestseller at Parisane (FR, 77K visits/mo) · also at Look de Paris (FR), Falkenhof Mode (DE, small) · 1 competitor(s) in IT/DE · season fit 1.0 | J81: 72.99 | K81: 50–70 | L81: take over the source link price | N81: =IF(M81="","",(J81-M81)/J81) | O81: Open | P81: Parisane (77K) | Q81: FR | R81: 80 | S81: 12 photos, 1st 800×800 | T81: Same main photo as 1 competitor(s) in your market → use photo 2 (or a model photo) as main image | U81: https://lookdeparis.com/products/clara-veste-de-ski-femme-avec-capuche-et-poches | V81: ='Davento – Links'!H81 | W81: 2026-10-02
A82: 78 | C82: Week 1 | D82: C · New & rising | E82: 75.1 | F82: Mantel Damen | Warm & Voluminös | G82: Transition jacket | H82: W | I82: top 21% bestseller at Lozenda Fashion (DE, 192K visits/mo) · 1 competitor(s) in IT/DE · added 11 days ago · season fit 1.0 | J82: 77.95 | K82: 50–70 | L82: take over the source link price; note: already a bestseller at 1 competitor(s) in your market | N82: =IF(M82="","",(J82-M82)/J82) | O82: Open | P82: Lozenda Fashion (192K) | Q82: DE ⚠ own market | R82: 89 | S82: 12 photos, 1st 1080×1080 | T82: Same main photo as 1 competitor(s) in your market → use photo 2 (or a model photo) as main image | V82: ='Davento – Links'!H82 | W82: 2026-10-02
A83: 79 | C83: Week 1 | D83: C · New & rising | E83: 75 | F83: Cardigan Damen mit Kapuze | Lässiger Offener Schnitt | G83: Cardigan | H83: W | I83: top 21% bestseller at Lozenda Fashion (DE, 192K visits/mo) · 1 competitor(s) in IT/DE · added 10 days ago · season fit 1.0 | J83: 67.95 | K83: 45–60 | L83: take over the source link price; note: already a bestseller at 1 competitor(s) in your market | N83: =IF(M83="","",(J83-M83)/J83) | O83: Open | P83: Lozenda Fashion (192K) | Q83: DE ⚠ own market | R83: 87 | S83: 11 photos, 1st 800×1150 | T83: Same main photo as 1 competitor(s) in your market → use photo 2 (or a model photo) as main image | V83: ='Davento – Links'!H83 | W83: 2026-10-02
A84: 80 | C84: Week 1 | D84: B · Broadly proven | E84: 74.9 | F84: Christine - Cardigan Élégant Oversize Boutonné | G84: Cardigan | H84: ? | I84: top 31% bestseller at Look de Paris (FR, 236K visits/mo) · also at Boutique Paris (FR), Mayfair & Finch (UK, small) · no competitor sells it in IT/DE yet → open space · season fit 1.0 | J84: 44.99 | K84: 45–60 | L84: take over the source link price | N84: =IF(M84="","",(J84-M84)/J84) | O84: Open | P84: Look de Paris (236K) | Q84: FR | R84: 87 | S84: 5 photos, 1st 1414×1414 | T84: Main photo free to use (no competitor in your market) | U84: https://boutique-paris.fr/products/isabelle-gilet-elegant-oversize-boutonne | V84: ='Davento – Links'!H84 | W84: 2026-10-02
A85: 81 | C85: Week 1 | D85: A · Proven elsewhere, open in your market | E85: 74.9 | F85: LAURENT MONACO | GILET ÉLÉGANT POUR HOMME | G85: Transition jacket | H85: M | I85: top 2% bestseller at Laurent Monaco (FR, 269K visits/mo) · also at Lumière Boutique (FR), Vientovida (ES, small) · no competitor sells it in IT/DE yet → open space · season fit 1.0 | J85: 44.95 | K85: 50–70 | L85: take over the source link price; below the category sweet spot, can go higher: 59.95 | N85: =IF(M85="","",(J85-M85)/J85) | O85: Open | P85: Laurent Monaco (269K) | Q85: FR | R85: 90 | S85: 10 photos, 1st 900×1200 | T85: Main photo free to use (no competitor in your market) | U85: https://lumiereboutique.fr/products/dumont-lyon-gilet-elegant-pour-homme | V85: ='Davento – Links'!H85 | W85: 2026-10-02
A86: 82 | C86: Week 1 | D86: C · New & rising | E86: 74.7 | F86: Weste Herren | Vintage Design mit Knopfleiste | G86: Transition jacket | H86: M | I86: top 15% bestseller at Lozenda Fashion (DE, 192K visits/mo) · 1 competitor(s) in IT/DE · added 3 days ago · season fit 1.0 | J86: 47.95 | K86: 50–70 | L86: take over the source link price; below the category sweet spot, can go higher: 59.95; note: already a bestseller at 1 competitor(s) in your market | N86: =IF(M86="","",(J86-M86)/J86) | O86: Open | P86: Lozenda Fashion (192K) | Q86: DE ⚠ own market | R86: 86 | S86: 6 photos, 1st 1000×1000 | T86: Same main photo as 1 competitor(s) in your market → use photo 2 (or a model photo) as main image | V86: ='Davento – Links'!H86 | W86: 2026-10-02
A87: 83 | C87: Week 1 | D87: A · Proven elsewhere, open in your market | E87: 74.7 | F87: Gilet court en maille femme côtelé boutonné col rond | G87: Transition jacket | H87: W | I87: top 19% bestseller at Parisane (FR, 77K visits/mo) · no competitor sells it in IT/DE yet → open space · added 18 days ago · season fit 1.0 | J87: 37.99 | K87: 50–70 | L87: take over the source link price; below the category sweet spot, can go higher: 59.95 | N87: =IF(M87="","",(J87-M87)/J87) | O87: Open | P87: Parisane (77K) | Q87: FR | R87: 89 | S87: 12 photos, 1st 1080×1080 | T87: Main photo free to use (no competitor in your market) | V87: ='Davento – Links'!H87 | W87: 2026-10-02
A88: 84 | C88: Week 1 | D88: A · Proven elsewhere, open in your market | E88: 74.7 | F88: Margot | High-Neck Button Cardigan | G88: Cardigan | H88: ? | I88: top 18% bestseller at Harper & Wells Boston (US, 1500K visits/mo) · also at Wilson & Carter (UK), Marlow & Quinn (US, small) · no competitor sells it in IT/DE yet → open space · season fit 1.0 | J88: 73.95 | K88: 45–60 | L88: source link price (79.95 USD) converted | N88: =IF(M88="","",(J88-M88)/J88) | O88: Open | P88: Harper & Wells Boston (1500K) | Q88: US | R88: 93 | S88: 12 photos, 1st 1341×1341 | T88: Main photo free to use (no competitor in your market) | U88: https://wilson-and-carter.com/products/vera-cardigan | V88: ='Davento – Links'!H88 | W88: 2026-10-02
A89: 85 | C89: Week 1 | D89: A · Proven elsewhere, open in your market | E89: 74.5 | F89: MOREAU LYON | GILET EN TRICOT À FERMETURE ÉCLAIR POUR FEMMES | G89: Transition jacket | H89: W | I89: top 16% bestseller at Moreau Lyon (FR, 426K visits/mo) · no competitor sells it in IT/DE yet → open space · season fit 1.0 | J89: 39.95 | K89: 50–70 | L89: take over the source link price; below the category sweet spot, can go higher: 59.95 | N89: =IF(M89="","",(J89-M89)/J89) | O89: Open | P89: Moreau Lyon (426K) | Q89: FR | R89: 90 | S89: 7 photos, 1st 900×1200 | T89: Main photo free to use (no competitor in your market) | V89: ='Davento – Links'!H89 | W89: 2026-10-02
A90: 86 | C90: Week 1 | D90: A · Proven elsewhere, open in your market | E90: 74.4 | F90: Foster | Textured Button-Up Jacket | G90: Transition jacket | H90: ? | I90: top 19% bestseller at Harper & Wells Boston (US, 1500K visits/mo) · also at Wilson & Carter (UK), Donna's Dresses (US, small) · no competitor sells it in IT/DE yet → open space · season fit 1.0 | J90: 54.95 | K90: 50–70 | L90: source link price (59.95 USD) converted | N90: =IF(M90="","",(J90-M90)/J90) | O90: Open | P90: Harper & Wells Boston (1500K) | Q90: US | R90: 93 | S90: 12 photos, 1st 1350×1350 | T90: Main photo free to use (no competitor in your market) | U90: https://wilson-and-carter.com/products/clifford-overshirt | V90: ='Davento – Links'!H90 | W90: 2026-10-02
A91: 87 | C91: Week 1 | D91: B · Broadly proven | E91: 74.3 | F91: Castello Wool-Blend Overcoat | G91: Transition jacket | H91: ? | I91: top 2% bestseller at Oliver & Blake (US, 98K visits/mo) · also at Chaps London (UK, small), Nordmodehaus (DE, small) · 1 competitor(s) in IT/DE · season fit 1.0 | J91: 50.95 | K91: 50–70 | L91: source link price (54.99 USD) converted | N91: =IF(M91="","",(J91-M91)/J91) | O91: Open | P91: Oliver & Blake (98K) | Q91: US | R91: 86 | S91: 9 photos, 1st 1001×1001 | T91: Same main photo as 1 competitor(s) in your market → use photo 2 (or a model photo) as main image | V91: ='Davento – Links'!H91 | W91: 2026-10-02
A92: 88 | C92: Week 1 | D92: A · Proven elsewhere, open in your market | E92: 74.2 | F92: Vicki | Vintage Trench Collar Coat | G92: Transition jacket | H92: ? | I92: top 12% bestseller at Harper & Wells Boston (US, 1500K visits/mo) · also at Wilson & Carter (UK), Paul's Wardrobe (US, small) · no competitor sells it in IT/DE yet → open space · season fit 1.0 | J92: 63.95 | K92: 50–70 | L92: source link price (69.95 USD) converted | N92: =IF(M92="","",(J92-M92)/J92) | O92: Open | P92: Harper & Wells Boston (1500K) | Q92: US | R92: 83 | S92: 5 photos, 1st 1080×1080 | T92: Main photo free to use (no competitor in your market) | U92: https://wilson-and-carter.com/products/cordelia-collar-coat | V92: ='Davento – Links'!H92 | W92: 2026-10-02
A93: 89 | C93: Week 1 | D93: A · Proven elsewhere, open in your market | E93: 74.1 | F93: Bordeaux Merino Zip Jacket | G93: Transition jacket | H93: ? | I93: top 2% bestseller at Oliver & Blake (US, 98K visits/mo) · also at Parisane (FR) · no competitor sells it in IT/DE yet → open space · season fit 1.0 | J93: 59.95 | K93: 50–70 | L93: source link price (64.99 USD) converted | N93: =IF(M93="","",(J93-M93)/J93) | O93: Open | P93: Oliver & Blake (98K) | Q93: US | R93: 72 | S93: 5 photos, 1st 742×742 | T93: Main photo free to use (no competitor in your market) | U93: https://parisane.fr/products/veste-en-maille-homme-zippee-a-col-montant | V93: ='Davento – Links'!H93 | W93: 2026-10-02
A94: 90 | C94: Week 1 | D94: A · Proven elsewhere, open in your market | E94: 74.1 | F94: Trench femme long simple boutonnage à col chemise | G94: Transition jacket | H94: W | I94: top 23% bestseller at Parisane (FR, 77K visits/mo) · no competitor sells it in IT/DE yet → open space · added 18 days ago · season fit 1.0 | J94: 52.99 | K94: 50–70 | L94: take over the source link price | N94: =IF(M94="","",(J94-M94)/J94) | O94: Open | P94: Parisane (77K) | Q94: FR | R94: 91 | S94: 7 photos, 1st 928×1152 | T94: Main photo free to use (no competitor in your market) | V94: ='Davento – Links'!H94 | W94: 2026-10-02
A95: 91 | C95: Week 1 | D95: C · New & rising | E95: 74 | F95: Damen Langjacke mit Kapuze und asymmetrischem Reißverschluss | G95: Transition jacket | H95: W | I95: top 12% bestseller at Alpenkind Mode (DE, 77K visits/mo) · 1 competitor(s) in IT/DE · added 13 days ago · season fit 1.0 | J95: 44.95 | K95: 50–70 | L95: take over the source link price; below the category sweet spot, can go higher: 59.95; note: already a bestseller at 1 competitor(s) in your market | N95: =IF(M95="","",(J95-M95)/J95) | O95: Open | P95: Alpenkind Mode (77K) | Q95: DE ⚠ own market | R95: 80 | S95: 6 photos, 1st 800×800 | T95: Same main photo as 1 competitor(s) in your market → use photo 2 (or a model photo) as main image | V95: ='Davento – Links'!H95 | W95: 2026-10-02
A96: 92 | C96: Week 1 | D96: C · New & rising | E96: 74 | F96: Heritage-Mantel für Damen mit Knopfverschluss | G96: Transition jacket | H96: W | I96: top 10% bestseller at Alpenkind Mode (DE, 77K visits/mo) · 1 competitor(s) in IT/DE · added 19 days ago · season fit 1.0 | J96: 32.95 | K96: 50–70 | L96: take over the source link price; below the category sweet spot, can go higher: 59.95; note: already a bestseller at 1 competitor(s) in your market | N96: =IF(M96="","",(J96-M96)/J96) | O96: Open | P96: Alpenkind Mode (77K) | Q96: DE ⚠ own market | R96: 87 | S96: 10 photos, 1st 1024×1024 | T96: Same main photo as 1 competitor(s) in your market → use photo 2 (or a model photo) as main image | V96: ='Davento – Links'!H96 | W96: 2026-10-02
A97: 93 | C97: Week 1 | D97: A · Proven elsewhere, open in your market | E97: 73.9 | F97: Lydia | Elegant Midi Dress and Cardigan Set | G97: Cardigan | H97: ? | I97: top 17% bestseller at Harper & Wells Boston (US, 1500K visits/mo) · also at Wilson & Carter (UK), Paul's Wardrobe (US, small) · no competitor sells it in IT/DE yet → open space · season fit 1.0 | J97: 63.95 | K97: 45–60 | L97: source link price (69.95 USD) converted | N97: =IF(M97="","",(J97-M97)/J97) | O97: Open | P97: Harper & Wells Boston (1500K) | Q97: US | R97: 87 | S97: 8 photos, 1st 800×1200 | T97: Main photo free to use (no competitor in your market) | U97: https://wilson-and-carter.com/products/georgia | V97: ='Davento – Links'!H97 | W97: 2026-10-02
A98: 94 | C98: Week 1 | D98: A · Proven elsewhere, open in your market | E98: 73.8 | F98: Camille - Cardigan Élégant Boutonné Col Chemise | G98: Cardigan | H98: ? | I98: top 23% bestseller at Look de Paris (FR, 236K visits/mo) · also at Boutique Paris (FR) · no competitor sells it in IT/DE yet → open space · season fit 1.0 | J98: 44.99 | K98: 45–60 | L98: take over the source link price | N98: =IF(M98="","",(J98-M98)/J98) | O98: Open | P98: Look de Paris (236K) | Q98: FR | R98: 87 | S98: 9 photos, 1st 800×1066 | T98: Main photo free to use (no competitor in your market) | U98: https://boutique-paris.fr/products/caroline-gilet-chic-boutonne-col-chemise | V98: ='Davento – Links'!H98 | W98: 2026-10-02
A99: 95 | C99: Week 1 | D99: B · Broadly proven | E99: 73.7 | F99: Juliette - Ensemble blazer élégant femme | G99: Blazer | H99: W | I99: top 6% bestseller at Look de Paris (FR, 236K visits/mo) · also at Boutique Paris (FR), Drune (DE), Lune Mode (IT, small), Vientovida (ES, small) · 2 competitor(s) in IT/DE · added 2 days ago · season fit 0.8 | J99: 59.99 | K99: 50–70 | L99: take over the source link price | N99: =IF(M99="","",(J99-M99)/J99) | O99: Open | P99: Look de Paris (236K) | Q99: FR | R99: 96 | S99: 6 photos, 1st 1075×1344 | T99: Same main photo as 2 competitor(s) in your market → use photo 2 (or a model photo) as main image | U99: https://drune.de/products/drune-elegantes-blazer-set-o4u8u1 https://boutique-paris.fr/products/lina-ensemble-blazer-femme-elegant | V99: ='Davento – Links'!H99 | W99: 2026-10-02
